Workbook

Sheet Read Me
A1: Medibook — Production Readiness Test Checklist
A2: Patient mobile app (Flutter, Android + iOS) · end-to-end manual test pass before release
A4: Run details
A5: Build / version under test
A6: Environment (API host)
A7: Test cycle
A8: Start date
A9: End date
A10: QA lead
A12: How to use this workbook
A13: 1. Known Blockers — re-verify each item first. Many checklist rows cannot run until these are resolved.
A14: 2. Checklist — start with module 00 (prerequisites) and 01 (end-to-end journeys), then work down. Filter by Module, Priority or Platform.
... A23: Status values
A24: Not Run | B24: Not executed yet (default).
A25: Pass | B25: Behaved exactly as the Expected result says.
A26: Fail | B26: Did not — log a defect.
A27: Blocked | B27: Could not be run (environment, blocker, dependency). Say why in Notes.
A28: N/A | B28: Does not apply to this release. Say why in Notes.
A30: Priority
A31: P0 | B31: Release blocker: money, sign-in, data loss, security, privacy, store rejection, or a core journey.
A32: P1 | B32: Must be fixed before public launch; acceptable only for a limited internal beta.
A33: P2 | B33: Should be fixed; a visible flaw with a workaround.
A34: P3 | B34: Polish.
A36: Check types on the Business Logic sheet
A37: Rule | B37: A decision the app makes (who may do what, and when).
A38: Boundary | B38: A limit: lengths, sizes, ages, time windows, counts. Test just inside and just outside.
A39: State | B39: What changes after an action, and what is kept or cleared.
A40: Calculation | B40: A derived value: amounts, percentages, counts, dates, labels built from data.
A41: Data mapping | B41: A server value shown as the right label or screen.
A42: Error handling | B42: A specific refusal or failure and the message it must produce.
A43: Verify gap | B43: The code appears to behave differently from what a user or the API contract would expect. Found by reading the code, not by running the app — confirm on a device, then log a defect or mark N/A with the owner's decision.
A45: Example of a filled-in checklist row
A46: ID | B46: Test case | C46: Notes / Actual result | D46: Status | E46: Tester | F46: Date tested | G46: Build | H46: Device / OS
A47: AUTH-019 | B47: Wrong password | C47: Shows 'attempts remaining: 4'. Fields stay filled. | D47: Pass | E47: A. Tester | F47: 06-Oct-2026 | G47: 1.0.0+7 | H47: Pixel 8 / Android 15
A49: Where the test cases come from
A50: Screens and routes | B50: lib/app/router/app_routes.dart and the screen files under lib/features/*/presentation/screen
A51: Expected API behaviour | B51: docs-flutter/FLUTTER_API_INTEGRATION.md (error codes, limits, timers, idempotency, token lifecycle)
A52: Business rules | B52: Read from the domain, application and controller code of each feature (lib/features/*/domain, */application, */presentation/controllers) and lib/core; each row cites its file.
A53: Cache scenarios | B53: docs-flutter/HIVE implementation.md (the ten scenarios) and lib/core/storage/hive/boxes.dart (CacheConfig)
A54: Code quality gates | B54: docs-flutter/QA.md (audit prompts 1–5 and the architecture audit)
A55: Known blockers | B55: docs/FLUTTER_INTEGRATION_GAPS_ROUND_2.md (dated 2026-10-01) plus the files named on the Known Blockers sheet
A56: Not derived from the repo | B56: Device matrix, performance targets (3 s cold start, 16 ms frames), the 95% execution threshold and store-submission items are common practice — adjust to your team's standards.
A58: Sheets
A59: Summary | B59: Release gate, progress by priority and by module for both test sheets (formulas).
A60: Business Logic | B60: 408 business-rule checks in 14 modules, each split into sub-modules.
A61: Checklist | B61: 438 functional, non-functional and release cases in 26 modules.
A62: Known Blockers | B62: 13 items found in the repo that stop or weaken the test pass.
A63: Screen Coverage | B63: 51 screens × 8 states/conditions.
A64: Device Matrix | B64: Recommended devices and OS versions.
A65: Defect Log | B65: One row per defect.
A66: Sign-off | B66: Exit criteria and approvals.

Sheet Summary
A1: Medibook — Production Readiness Test Summary
A2: Every figure on this sheet is a formula over the Checklist sheet. Do not type over them.
A4: Release gate
A5: P0 cases not yet passed | B5: =COUNTIF(Checklist!$G$2:$G$1000,"P0")+COUNTIF('Business Logic'!$G$2:$G$1000,"P0")-(COUNTIFS(Checklist!$G$2:$G$1000,"P0",Checklist!$K$2:$K$1000,"Pass")+COUNTIFS('Business Logic'!$G$2:$G$1000,"P0",'Business Logic'!$K$2:$K$1000,"Pass"))-(COUNTIFS(Checklist!$G$2:$G$1000,"P0",Checklist!$K$2:$K$1000,"N/A")+COUNTIFS('Business Logic'!$G$2:$G$1000,"P0",'Business Logic'!$K$2:$K$1000,"N/A")) | C5: Every P0 must be Pass (or N/A with a written reason).
A6: P0 / P1 cases failing | B6: =COUNTIFS(Checklist!$G$2:$G$1000,"P0",Checklist!$K$2:$K$1000,"Fail")+COUNTIFS('Business Logic'!$G$2:$G$1000,"P0",'Business Logic'!$K$2:$K$1000,"Fail")+COUNTIFS(Checklist!$G$2:$G$1000,"P1",Checklist!$K$2:$K$1000,"Fail")+COUNTIFS('Business Logic'!$G$2:$G$1000,"P1",'Business Logic'!$K$2:$K$1000,"Fail") | C6: No open P0 or P1 failures.
A7: Cases blocked | B7: =COUNTIF(Checklist!$K$2:$K$1000,"Blocked")+COUNTIF('Business Logic'!$K$2:$K$1000,"Blocked") | C7: Blocked cases must be unblocked or accepted on the Sign-off sheet.
A8: Known blockers still open | B8: ='Known Blockers'!$I$1 | C8: From the Known Blockers sheet.
A9: Verdict | B9: =IF(AND(B5=0,B6=0,B7=0,B8=0),"GO","NO-GO") | C9: GO only when the four counts above are all zero. Counts cover the Checklist and Business Logic sheets together.
A11: Progress by priority (both sheets)
A12: Priority | B12: Total | C12: Pass | D12: Fail | E12: Blocked | F12: N/A | G12: Not Run | H12: % executed | I12: Pass rate
A13: P0 — release blocker | B13: =COUNTIF(Checklist!$G$2:$G$1000,"P0")+COUNTIF('Business Logic'!$G$2:$G$1000,"P0") | C13: =COUNTIFS(Checklist!$G$2:$G$1000,"P0",Checklist!$K$2:$K$1000,"Pass")+COUNTIFS('Business Logic'!$G$2:$G$1000,"P0",'Business Logic'!$K$2:$K$1000,"Pass") | D13: =COUNTIFS(Checklist!$G$2:$G$1000,"P0",Checklist!$K$2:$K$1000,"Fail")+COUNTIFS('Business Logic'!$G$2:$G$1000,"P0",'Business Logic'!$K$2:$K$1000,"Fail") | E13: =COUNTIFS(Checklist!$G$2:$G$1000,"P0",Checklist!$K$2:$K$1000,"Blocked")+COUNTIFS('Business Logic'!$G$2:$G$1000,"P0",'Business Logic'!$K$2:$K$1000,"Blocked") | F13: =COUNTIFS(Checklist!$G$2:$G$1000,"P0",Checklist!$K$2:$K$1000,"N/A")+COUNTIFS('Business Logic'!$G$2:$G$1000,"P0",'Business Logic'!$K$2:$K$1000,"N/A") | G13: =COUNTIFS(Checklist!$G$2:$G$1000,"P0",Checklist!$K$2:$K$1000,"Not Run")+COUNTIFS('Business Logic'!$G$2:$G$1000,"P0",'Business Logic'!$K$2:$K$1000,"Not Run") | H13: =IF(B13=0,0,(B13-G13)/B13) | I13: =IF(C13+D13=0,0,C13/(C13+D13))
A14: P1 — must fix before launch | B14: =COUNTIF(Checklist!$G$2:$G$1000,"P1")+COUNTIF('Business Logic'!$G$2:$G$1000,"P1") | C14: =COUNTIFS(Checklist!$G$2:$G$1000,"P1",Checklist!$K$2:$K$1000,"Pass")+COUNTIFS('Business Logic'!$G$2:$G$1000,"P1",'Business Logic'!$K$2:$K$1000,"Pass") | D14: =COUNTIFS(Checklist!$G$2:$G$1000,"P1",Checklist!$K$2:$K$1000,"Fail")+COUNTIFS('Business Logic'!$G$2:$G$1000,"P1",'Business Logic'!$K$2:$K$1000,"Fail") | E14: =COUNTIFS(Checklist!$G$2:$G$1000,"P1",Checklist!$K$2:$K$1000,"Blocked")+COUNTIFS('Business Logic'!$G$2:$G$1000,"P1",'Business Logic'!$K$2:$K$1000,"Blocked") | F14: =COUNTIFS(Checklist!$G$2:$G$1000,"P1",Checklist!$K$2:$K$1000,"N/A")+COUNTIFS('Business Logic'!$G$2:$G$1000,"P1",'Business Logic'!$K$2:$K$1000,"N/A") | G14: =COUNTIFS(Checklist!$G$2:$G$1000,"P1",Checklist!$K$2:$K$1000,"Not Run")+COUNTIFS('Business Logic'!$G$2:$G$1000,"P1",'Business Logic'!$K$2:$K$1000,"Not Run") | H14: =IF(B14=0,0,(B14-G14)/B14) | I14: =IF(C14+D14=0,0,C14/(C14+D14))
A15: P2 — should fix | B15: =COUNTIF(Checklist!$G$2:$G$1000,"P2")+COUNTIF('Business Logic'!$G$2:$G$1000,"P2") | C15: =COUNTIFS(Checklist!$G$2:$G$1000,"P2",Checklist!$K$2:$K$1000,"Pass")+COUNTIFS('Business Logic'!$G$2:$G$1000,"P2",'Business Logic'!$K$2:$K$1000,"Pass") | D15: =COUNTIFS(Checklist!$G$2:$G$1000,"P2",Checklist!$K$2:$K$1000,"Fail")+COUNTIFS('Business Logic'!$G$2:$G$1000,"P2",'Business Logic'!$K$2:$K$1000,"Fail") | E15: =COUNTIFS(Checklist!$G$2:$G$1000,"P2",Checklist!$K$2:$K$1000,"Blocked")+COUNTIFS('Business Logic'!$G$2:$G$1000,"P2",'Business Logic'!$K$2:$K$1000,"Blocked") | F15: =COUNTIFS(Checklist!$G$2:$G$1000,"P2",Checklist!$K$2:$K$1000,"N/A")+COUNTIFS('Business Logic'!$G$2:$G$1000,"P2",'Business Logic'!$K$2:$K$1000,"N/A") | G15: =COUNTIFS(Checklist!$G$2:$G$1000,"P2",Checklist!$K$2:$K$1000,"Not Run")+COUNTIFS('Business Logic'!$G$2:$G$1000,"P2",'Business Logic'!$K$2:$K$1000,"Not Run") | H15: =IF(B15=0,0,(B15-G15)/B15) | I15: =IF(C15+D15=0,0,C15/(C15+D15))
A16: P3 — nice to have | B16: =COUNTIF(Checklist!$G$2:$G$1000,"P3")+COUNTIF('Business Logic'!$G$2:$G$1000,"P3") | C16: =COUNTIFS(Checklist!$G$2:$G$1000,"P3",Checklist!$K$2:$K$1000,"Pass")+COUNTIFS('Business Logic'!$G$2:$G$1000,"P3",'Business Logic'!$K$2:$K$1000,"Pass") | D16: =COUNTIFS(Checklist!$G$2:$G$1000,"P3",Checklist!$K$2:$K$1000,"Fail")+COUNTIFS('Business Logic'!$G$2:$G$1000,"P3",'Business Logic'!$K$2:$K$1000,"Fail") | E16: =COUNTIFS(Checklist!$G$2:$G$1000,"P3",Checklist!$K$2:$K$1000,"Blocked")+COUNTIFS('Business Logic'!$G$2:$G$1000,"P3",'Business Logic'!$K$2:$K$1000,"Blocked") | F16: =COUNTIFS(Checklist!$G$2:$G$1000,"P3",Checklist!$K$2:$K$1000,"N/A")+COUNTIFS('Business Logic'!$G$2:$G$1000,"P3",'Business Logic'!$K$2:$K$1000,"N/A") | G16: =COUNTIFS(Checklist!$G$2:$G$1000,"P3",Checklist!$K$2:$K$1000,"Not Run")+COUNTIFS('Business Logic'!$G$2:$G$1000,"P3",'Business Logic'!$K$2:$K$1000,"Not Run") | H16: =IF(B16=0,0,(B16-G16)/B16) | I16: =IF(C16+D16=0,0,C16/(C16+D16))
A17: All cases | B17: =COUNTA(Checklist!$A$2:$A$1000)+COUNTA('Business Logic'!$A$2:$A$1000) | C17: =COUNTIF(Checklist!$K$2:$K$1000,"Pass")+COUNTIF('Business Logic'!$K$2:$K$1000,"Pass") | D17: =COUNTIF(Checklist!$K$2:$K$1000,"Fail")+COUNTIF('Business Logic'!$K$2:$K$1000,"Fail") | E17: =COUNTIF(Checklist!$K$2:$K$1000,"Blocked")+COUNTIF('Business Logic'!$K$2:$K$1000,"Blocked") | F17: =COUNTIF(Checklist!$K$2:$K$1000,"N/A")+COUNTIF('Business Logic'!$K$2:$K$1000,"N/A") | G17: =COUNTIF(Checklist!$K$2:$K$1000,"Not Run")+COUNTIF('Business Logic'!$K$2:$K$1000,"Not Run") | H17: =IF(B17=0,0,(B17-G17)/B17) | I17: =IF(C17+D17=0,0,C17/(C17+D17))
A18: of which: Checklist sheet | B18: =COUNTA(Checklist!$A$2:$A$1000) | C18: =COUNTIF(Checklist!$K$2:$K$1000,"Pass") | D18: =COUNTIF(Checklist!$K$2:$K$1000,"Fail") | E18: =COUNTIF(Checklist!$K$2:$K$1000,"Blocked") | F18: =COUNTIF(Checklist!$K$2:$K$1000,"N/A") | G18: =COUNTIF(Checklist!$K$2:$K$1000,"Not Run") | H18: =IF(B18=0,0,(B18-G18)/B18) | I18: =IF(C18+D18=0,0,C18/(C18+D18))
A19: of which: Business Logic sheet | B19: =COUNTA('Business Logic'!$A$2:$A$1000) | C19: =COUNTIF('Business Logic'!$K$2:$K$1000,"Pass") | D19: =COUNTIF('Business Logic'!$K$2:$K$1000,"Fail") | E19: =COUNTIF('Business Logic'!$K$2:$K$1000,"Blocked") | F19: =COUNTIF('Business Logic'!$K$2:$K$1000,"N/A") | G19: =COUNTIF('Business Logic'!$K$2:$K$1000,"Not Run") | H19: =IF(B19=0,0,(B19-G19)/B19) | I19: =IF(C19+D19=0,0,C19/(C19+D19))
A21: Business logic — progress by module
A22: Module | B22: Total | C22: Pass | D22: Fail | E22: Blocked | F22: N/A | G22: Not Run | H22: % executed | I22: Pass rate
A23: Authentication & session | B23: =COUNTIF('Business Logic'!$B$2:$B$1000,$A23) | C23: =COUNTIFS('Business Logic'!$B$2:$B$1000,$A23,'Business Logic'!$K$2:$K$1000,"Pass") | D23: =COUNTIFS('Business Logic'!$B$2:$B$1000,$A23,'Business Logic'!$K$2:$K$1000,"Fail") | E23: =COUNTIFS('Business Logic'!$B$2:$B$1000,$A23,'Business Logic'!$K$2:$K$1000,"Blocked") | F23: =COUNTIFS('Business Logic'!$B$2:$B$1000,$A23,'Business Logic'!$K$2:$K$1000,"N/A") | G23: =COUNTIFS('Business Logic'!$B$2:$B$1000,$A23,'Business Logic'!$K$2:$K$1000,"Not Run") | H23: =IF(B23=0,0,(B23-G23)/B23) | I23: =IF(C23+D23=0,0,C23/(C23+D23))
A24: Booking | B24: =COUNTIF('Business Logic'!$B$2:$B$1000,$A24) | C24: =COUNTIFS('Business Logic'!$B$2:$B$1000,$A24,'Business Logic'!$K$2:$K$1000,"Pass") | D24: =COUNTIFS('Business Logic'!$B$2:$B$1000,$A24,'Business Logic'!$K$2:$K$1000,"Fail") | E24: =COUNTIFS('Business Logic'!$B$2:$B$1000,$A24,'Business Logic'!$K$2:$K$1000,"Blocked") | F24: =COUNTIFS('Business Logic'!$B$2:$B$1000,$A24,'Business Logic'!$K$2:$K$1000,"N/A") | G24: =COUNTIFS('Business Logic'!$B$2:$B$1000,$A24,'Business Logic'!$K$2:$K$1000,"Not Run") | H24: =IF(B24=0,0,(B24-G24)/B24) | I24: =IF(C24+D24=0,0,C24/(C24+D24))
A25: Payment | B25: =COUNTIF('Business Logic'!$B$2:$B$1000,$A25) | C25: =COUNTIFS('Business Logic'!$B$2:$B$1000,$A25,'Business Logic'!$K$2:$K$1000,"Pass") | D25: =COUNTIFS('Business Logic'!$B$2:$B$1000,$A25,'Business Logic'!$K$2:$K$1000,"Fail") | E25: =COUNTIFS('Business Logic'!$B$2:$B$1000,$A25,'Business Logic'!$K$2:$K$1000,"Blocked") | F25: =COUNTIFS('Business Logic'!$B$2:$B$1000,$A25,'Business Logic'!$K$2:$K$1000,"N/A") | G25: =COUNTIFS('Business Logic'!$B$2:$B$1000,$A25,'Business Logic'!$K$2:$K$1000,"Not Run") | H25: =IF(B25=0,0,(B25-G25)/B25) | I25: =IF(C25+D25=0,0,C25/(C25+D25))
A26: Appointments | B26: =COUNTIF('Business Logic'!$B$2:$B$1000,$A26) | C26: =COUNTIFS('Business Logic'!$B$2:$B$1000,$A26,'Business Logic'!$K$2:$K$1000,"Pass") | D26: =COUNTIFS('Business Logic'!$B$2:$B$1000,$A26,'Business Logic'!$K$2:$K$1000,"Fail") | E26: =COUNTIFS('Business Logic'!$B$2:$B$1000,$A26,'Business Logic'!$K$2:$K$1000,"Blocked") | F26: =COUNTIFS('Business Logic'!$B$2:$B$1000,$A26,'Business Logic'!$K$2:$K$1000,"N/A") | G26: =COUNTIFS('Business Logic'!$B$2:$B$1000,$A26,'Business Logic'!$K$2:$K$1000,"Not Run") | H26: =IF(B26=0,0,(B26-G26)/B26) | I26: =IF(C26+D26=0,0,C26/(C26+D26))
A27: Live queue | B27: =COUNTIF('Business Logic'!$B$2:$B$1000,$A27) | C27: =COUNTIFS('Business Logic'!$B$2:$B$1000,$A27,'Business Logic'!$K$2:$K$1000,"Pass") | D27: =COUNTIFS('Business Logic'!$B$2:$B$1000,$A27,'Business Logic'!$K$2:$K$1000,"Fail") | E27: =COUNTIFS('Business Logic'!$B$2:$B$1000,$A27,'Business Logic'!$K$2:$K$1000,"Blocked") | F27: =COUNTIFS('Business Logic'!$B$2:$B$1000,$A27,'Business Logic'!$K$2:$K$1000,"N/A") | G27: =COUNTIFS('Business Logic'!$B$2:$B$1000,$A27,'Business Logic'!$K$2:$K$1000,"Not Run") | H27: =IF(B27=0,0,(B27-G27)/B27) | I27: =IF(C27+D27=0,0,C27/(C27+D27))
A28: Home & search | B28: =COUNTIF('Business Logic'!$B$2:$B$1000,$A28) | C28: =COUNTIFS('Business Logic'!$B$2:$B$1000,$A28,'Business Logic'!$K$2:$K$1000,"Pass") | D28: =COUNTIFS('Business Logic'!$B$2:$B$1000,$A28,'Business Logic'!$K$2:$K$1000,"Fail") | E28: =COUNTIFS('Business Logic'!$B$2:$B$1000,$A28,'Business Logic'!$K$2:$K$1000,"Blocked") | F28: =COUNTIFS('Business Logic'!$B$2:$B$1000,$A28,'Business Logic'!$K$2:$K$1000,"N/A") | G28: =COUNTIFS('Business Logic'!$B$2:$B$1000,$A28,'Business Logic'!$K$2:$K$1000,"Not Run") | H28: =IF(B28=0,0,(B28-G28)/B28) | I28: =IF(C28+D28=0,0,C28/(C28+D28))
A29: Records & uploads | B29: =COUNTIF('Business Logic'!$B$2:$B$1000,$A29) | C29: =COUNTIFS('Business Logic'!$B$2:$B$1000,$A29,'Business Logic'!$K$2:$K$1000,"Pass") | D29: =COUNTIFS('Business Logic'!$B$2:$B$1000,$A29,'Business Logic'!$K$2:$K$1000,"Fail") | E29: =COUNTIFS('Business Logic'!$B$2:$B$1000,$A29,'Business Logic'!$K$2:$K$1000,"Blocked") | F29: =COUNTIFS('Business Logic'!$B$2:$B$1000,$A29,'Business Logic'!$K$2:$K$1000,"N/A") | G29: =COUNTIFS('Business Logic'!$B$2:$B$1000,$A29,'Business Logic'!$K$2:$K$1000,"Not Run") | H29: =IF(B29=0,0,(B29-G29)/B29) | I29: =IF(C29+D29=0,0,C29/(C29+D29))
A30: Cache, offline & pagination | B30: =COUNTIF('Business Logic'!$B$2:$B$1000,$A30) | C30: =COUNTIFS('Business Logic'!$B$2:$B$1000,$A30,'Business Logic'!$K$2:$K$1000,"Pass") | D30: =COUNTIFS('Business Logic'!$B$2:$B$1000,$A30,'Business Logic'!$K$2:$K$1000,"Fail") | E30: =COUNTIFS('Business Logic'!$B$2:$B$1000,$A30,'Business Logic'!$K$2:$K$1000,"Blocked") | F30: =COUNTIFS('Business Logic'!$B$2:$B$1000,$A30,'Business Logic'!$K$2:$K$1000,"N/A") | G30: =COUNTIFS('Business Logic'!$B$2:$B$1000,$A30,'Business Logic'!$K$2:$K$1000,"Not Run") | H30: =IF(B30=0,0,(B30-G30)/B30) | I30: =IF(C30+D30=0,0,C30/(C30+D30))
A31: Notifications | B31: =COUNTIF('Business Logic'!$B$2:$B$1000,$A31) | C31: =COUNTIFS('Business Logic'!$B$2:$B$1000,$A31,'Business Logic'!$K$2:$K$1000,"Pass") | D31: =COUNTIFS('Business Logic'!$B$2:$B$1000,$A31,'Business Logic'!$K$2:$K$1000,"Fail") | E31: =COUNTIFS('Business Logic'!$B$2:$B$1000,$A31,'Business Logic'!$K$2:$K$1000,"Blocked") | F31: =COUNTIFS('Business Logic'!$B$2:$B$1000,$A31,'Business Logic'!$K$2:$K$1000,"N/A") | G31: =COUNTIFS('Business Logic'!$B$2:$B$1000,$A31,'Business Logic'!$K$2:$K$1000,"Not Run") | H31: =IF(B31=0,0,(B31-G31)/B31) | I31: =IF(C31+D31=0,0,C31/(C31+D31))
A32: Profile & account | B32: =COUNTIF('Business Logic'!$B$2:$B$1000,$A32) | C32: =COUNTIFS('Business Logic'!$B$2:$B$1000,$A32,'Business Logic'!$K$2:$K$1000,"Pass") | D32: =COUNTIFS('Business Logic'!$B$2:$B$1000,$A32,'Business Logic'!$K$2:$K$1000,"Fail") | E32: =COUNTIFS('Business Logic'!$B$2:$B$1000,$A32,'Business Logic'!$K$2:$K$1000,"Blocked") | F32: =COUNTIFS('Business Logic'!$B$2:$B$1000,$A32,'Business Logic'!$K$2:$K$1000,"N/A") | G32: =COUNTIFS('Business Logic'!$B$2:$B$1000,$A32,'Business Logic'!$K$2:$K$1000,"Not Run") | H32: =IF(B32=0,0,(B32-G32)/B32) | I32: =IF(C32+D32=0,0,C32/(C32+D32))
A33: Family members | B33: =COUNTIF('Business Logic'!$B$2:$B$1000,$A33) | C33: =COUNTIFS('Business Logic'!$B$2:$B$1000,$A33,'Business Logic'!$K$2:$K$1000,"Pass") | D33: =COUNTIFS('Business Logic'!$B$2:$B$1000,$A33,'Business Logic'!$K$2:$K$1000,"Fail") | E33: =COUNTIFS('Business Logic'!$B$2:$B$1000,$A33,'Business Logic'!$K$2:$K$1000,"Blocked") | F33: =COUNTIFS('Business Logic'!$B$2:$B$1000,$A33,'Business Logic'!$K$2:$K$1000,"N/A") | G33: =COUNTIFS('Business Logic'!$B$2:$B$1000,$A33,'Business Logic'!$K$2:$K$1000,"Not Run") | H33: =IF(B33=0,0,(B33-G33)/B33) | I33: =IF(C33+D33=0,0,C33/(C33+D33))
A34: Insurance | B34: =COUNTIF('Business Logic'!$B$2:$B$1000,$A34) | C34: =COUNTIFS('Business Logic'!$B$2:$B$1000,$A34,'Business Logic'!$K$2:$K$1000,"Pass") | D34: =COUNTIFS('Business Logic'!$B$2:$B$1000,$A34,'Business Logic'!$K$2:$K$1000,"Fail") | E34: =COUNTIFS('Business Logic'!$B$2:$B$1000,$A34,'Business Logic'!$K$2:$K$1000,"Blocked") | F34: =COUNTIFS('Business Logic'!$B$2:$B$1000,$A34,'Business Logic'!$K$2:$K$1000,"N/A") | G34: =COUNTIFS('Business Logic'!$B$2:$B$1000,$A34,'Business Logic'!$K$2:$K$1000,"Not Run") | H34: =IF(B34=0,0,(B34-G34)/B34) | I34: =IF(C34+D34=0,0,C34/(C34+D34))
... A36: Shared rules: money & time | B36: =COUNTIF('Business Logic'!$B$2:$B$1000,$A36) | C36: =COUNTIFS('Business Logic'!$B$2:$B$1000,$A36,'Business Logic'!$K$2:$K$1000,"Pass") | D36: =COUNTIFS('Business Logic'!$B$2:$B$1000,$A36,'Business Logic'!$K$2:$K$1000,"Fail") | E36: =COUNTIFS('Business Logic'!$B$2:$B$1000,$A36,'Business Logic'!$K$2:$K$1000,"Blocked") | F36: =COUNTIFS('Business Logic'!$B$2:$B$1000,$A36,'Business Logic'!$K$2:$K$1000,"N/A") | G36: =COUNTIFS('Business Logic'!$B$2:$B$1000,$A36,'Business Logic'!$K$2:$K$1000,"Not Run") | H36: =IF(B36=0,0,(B36-G36)/B36) | I36: =IF(C36+D36=0,0,C36/(C36+D36))
A37: Total | B37: =SUM(B23:B36) | C37: =SUM(C23:C36) | D37: =SUM(D23:D36) | E37: =SUM(E23:E36) | F37: =SUM(F23:F36) | G37: =SUM(G23:G36) | H37: =IF(B37=0,0,(B37-G37)/B37) | I37: =IF(C37+D37=0,0,C37/(C37+D37)) | J37: =IF(B37=B19,"","Totals differ: a row on that sheet has a module name not listed here.")
A39: Functional, non-functional & release checklist — progress by module
A40: Module | B40: Total | C40: Pass | D40: Fail | E40: Blocked | F40: N/A | G40: Not Run | H40: % executed | I40: Pass rate
A41: 00 Test environment & prerequisites | B41: =COUNTIF(Checklist!$B$2:$B$1000,$A41) | C41: =COUNTIFS(Checklist!$B$2:$B$1000,$A41,Checklist!$K$2:$K$1000,"Pass") | D41: =COUNTIFS(Checklist!$B$2:$B$1000,$A41,Checklist!$K$2:$K$1000,"Fail") | E41: =COUNTIFS(Checklist!$B$2:$B$1000,$A41,Checklist!$K$2:$K$1000,"Blocked") | F41: =COUNTIFS(Checklist!$B$2:$B$1000,$A41,Checklist!$K$2:$K$1000,"N/A") | G41: =COUNTIFS(Checklist!$B$2:$B$1000,$A41,Checklist!$K$2:$K$1000,"Not Run") | H41: =IF(B41=0,0,(B41-G41)/B41) | I41: =IF(C41+D41=0,0,C41/(C41+D41))
A42: 01 End-to-end journeys (run first) | B42: =COUNTIF(Checklist!$B$2:$B$1000,$A42) | C42: =COUNTIFS(Checklist!$B$2:$B$1000,$A42,Checklist!$K$2:$K$1000,"Pass") | D42: =COUNTIFS(Checklist!$B$2:$B$1000,$A42,Checklist!$K$2:$K$1000,"Fail") | E42: =COUNTIFS(Checklist!$B$2:$B$1000,$A42,Checklist!$K$2:$K$1000,"Blocked") | F42: =COUNTIFS(Checklist!$B$2:$B$1000,$A42,Checklist!$K$2:$K$1000,"N/A") | G42: =COUNTIFS(Checklist!$B$2:$B$1000,$A42,Checklist!$K$2:$K$1000,"Not Run") | H42: =IF(B42=0,0,(B42-G42)/B42) | I42: =IF(C42+D42=0,0,C42/(C42+D42))
A43: 02 Install, launch & bootstrap | B43: =COUNTIF(Checklist!$B$2:$B$1000,$A43) | C43: =COUNTIFS(Checklist!$B$2:$B$1000,$A43,Checklist!$K$2:$K$1000,"Pass") | D43: =COUNTIFS(Checklist!$B$2:$B$1000,$A43,Checklist!$K$2:$K$1000,"Fail") | E43: =COUNTIFS(Checklist!$B$2:$B$1000,$A43,Checklist!$K$2:$K$1000,"Blocked") | F43: =COUNTIFS(Checklist!$B$2:$B$1000,$A43,Checklist!$K$2:$K$1000,"N/A") | G43: =COUNTIFS(Checklist!$B$2:$B$1000,$A43,Checklist!$K$2:$K$1000,"Not Run") | H43: =IF(B43=0,0,(B43-G43)/B43) | I43: =IF(C43+D43=0,0,C43/(C43+D43))
A44: 03 Onboarding & consent | B44: =COUNTIF(Checklist!$B$2:$B$1000,$A44) | C44: =COUNTIFS(Checklist!$B$2:$B$1000,$A44,Checklist!$K$2:$K$1000,"Pass") | D44: =COUNTIFS(Checklist!$B$2:$B$1000,$A44,Checklist!$K$2:$K$1000,"Fail") | E44: =COUNTIFS(Checklist!$B$2:$B$1000,$A44,Checklist!$K$2:$K$1000,"Blocked") | F44: =COUNTIFS(Checklist!$B$2:$B$1000,$A44,Checklist!$K$2:$K$1000,"N/A") | G44: =COUNTIFS(Checklist!$B$2:$B$1000,$A44,Checklist!$K$2:$K$1000,"Not Run") | H44: =IF(B44=0,0,(B44-G44)/B44) | I44: =IF(C44+D44=0,0,C44/(C44+D44))
A45: 04 Authentication & session | B45: =COUNTIF(Checklist!$B$2:$B$1000,$A45) | C45: =COUNTIFS(Checklist!$B$2:$B$1000,$A45,Checklist!$K$2:$K$1000,"Pass") | D45: =COUNTIFS(Checklist!$B$2:$B$1000,$A45,Checklist!$K$2:$K$1000,"Fail") | E45: =COUNTIFS(Checklist!$B$2:$B$1000,$A45,Checklist!$K$2:$K$1000,"Blocked") | F45: =COUNTIFS(Checklist!$B$2:$B$1000,$A45,Checklist!$K$2:$K$1000,"N/A") | G45: =COUNTIFS(Checklist!$B$2:$B$1000,$A45,Checklist!$K$2:$K$1000,"Not Run") | H45: =IF(B45=0,0,(B45-G45)/B45) | I45: =IF(C45+D45=0,0,C45/(C45+D45))
A46: 05 Home dashboard | B46: =COUNTIF(Checklist!$B$2:$B$1000,$A46) | C46: =COUNTIFS(Checklist!$B$2:$B$1000,$A46,Checklist!$K$2:$K$1000,"Pass") | D46: =COUNTIFS(Checklist!$B$2:$B$1000,$A46,Checklist!$K$2:$K$1000,"Fail") | E46: =COUNTIFS(Checklist!$B$2:$B$1000,$A46,Checklist!$K$2:$K$1000,"Blocked") | F46: =COUNTIFS(Checklist!$B$2:$B$1000,$A46,Checklist!$K$2:$K$1000,"N/A") | G46: =COUNTIFS(Checklist!$B$2:$B$1000,$A46,Checklist!$K$2:$K$1000,"Not Run") | H46: =IF(B46=0,0,(B46-G46)/B46) | I46: =IF(C46+D46=0,0,C46/(C46+D46))
A47: 06 Discovery: locations, hospitals, doctors, search | B47: =COUNTIF(Checklist!$B$2:$B$1000,$A47) | C47: =COUNTIFS(Checklist!$B$2:$B$1000,$A47,Checklist!$K$2:$K$1000,"Pass") | D47: =COUNTIFS(Checklist!$B$2:$B$1000,$A47,Checklist!$K$2:$K$1000,"Fail") | E47: =COUNTIFS(Checklist!$B$2:$B$1000,$A47,Checklist!$K$2:$K$1000,"Blocked") | F47: =COUNTIFS(Checklist!$B$2:$B$1000,$A47,Checklist!$K$2:$K$1000,"N/A") | G47: =COUNTIFS(Checklist!$B$2:$B$1000,$A47,Checklist!$K$2:$K$1000,"Not Run") | H47: =IF(B47=0,0,(B47-G47)/B47) | I47: =IF(C47+D47=0,0,C47/(C47+D47))
A48: 07 Booking flow | B48: =COUNTIF(Checklist!$B$2:$B$1000,$A48) | C48: =COUNTIFS(Checklist!$B$2:$B$1000,$A48,Checklist!$K$2:$K$1000,"Pass") | D48: =COUNTIFS(Checklist!$B$2:$B$1000,$A48,Checklist!$K$2:$K$1000,"Fail") | E48: =COUNTIFS(Checklist!$B$2:$B$1000,$A48,Checklist!$K$2:$K$1000,"Blocked") | F48: =COUNTIFS(Checklist!$B$2:$B$1000,$A48,Checklist!$K$2:$K$1000,"N/A") | G48: =COUNTIFS(Checklist!$B$2:$B$1000,$A48,Checklist!$K$2:$K$1000,"Not Run") | H48: =IF(B48=0,0,(B48-G48)/B48) | I48: =IF(C48+D48=0,0,C48/(C48+D48))
A49: 08 Payment (Razorpay) | B49: =COUNTIF(Checklist!$B$2:$B$1000,$A49) | C49: =COUNTIFS(Checklist!$B$2:$B$1000,$A49,Checklist!$K$2:$K$1000,"Pass") | D49: =COUNTIFS(Checklist!$B$2:$B$1000,$A49,Checklist!$K$2:$K$1000,"Fail") | E49: =COUNTIFS(Checklist!$B$2:$B$1000,$A49,Checklist!$K$2:$K$1000,"Blocked") | F49: =COUNTIFS(Checklist!$B$2:$B$1000,$A49,Checklist!$K$2:$K$1000,"N/A") | G49: =COUNTIFS(Checklist!$B$2:$B$1000,$A49,Checklist!$K$2:$K$1000,"Not Run") | H49: =IF(B49=0,0,(B49-G49)/B49) | I49: =IF(C49+D49=0,0,C49/(C49+D49))
A50: 09 Appointments | B50: =COUNTIF(Checklist!$B$2:$B$1000,$A50) | C50: =COUNTIFS(Checklist!$B$2:$B$1000,$A50,Checklist!$K$2:$K$1000,"Pass") | D50: =COUNTIFS(Checklist!$B$2:$B$1000,$A50,Checklist!$K$2:$K$1000,"Fail") | E50: =COUNTIFS(Checklist!$B$2:$B$1000,$A50,Checklist!$K$2:$K$1000,"Blocked") | F50: =COUNTIFS(Checklist!$B$2:$B$1000,$A50,Checklist!$K$2:$K$1000,"N/A") | G50: =COUNTIFS(Checklist!$B$2:$B$1000,$A50,Checklist!$K$2:$K$1000,"Not Run") | H50: =IF(B50=0,0,(B50-G50)/B50) | I50: =IF(C50+D50=0,0,C50/(C50+D50))
A51: 10 Live queue | B51: =COUNTIF(Checklist!$B$2:$B$1000,$A51) | C51: =COUNTIFS(Checklist!$B$2:$B$1000,$A51,Checklist!$K$2:$K$1000,"Pass") | D51: =COUNTIFS(Checklist!$B$2:$B$1000,$A51,Checklist!$K$2:$K$1000,"Fail") | E51: =COUNTIFS(Checklist!$B$2:$B$1000,$A51,Checklist!$K$2:$K$1000,"Blocked") | F51: =COUNTIFS(Checklist!$B$2:$B$1000,$A51,Checklist!$K$2:$K$1000,"N/A") | G51: =COUNTIFS(Checklist!$B$2:$B$1000,$A51,Checklist!$K$2:$K$1000,"Not Run") | H51: =IF(B51=0,0,(B51-G51)/B51) | I51: =IF(C51+D51=0,0,C51/(C51+D51))
A52: 11 Health records & documents | B52: =COUNTIF(Checklist!$B$2:$B$1000,$A52) | C52: =COUNTIFS(Checklist!$B$2:$B$1000,$A52,Checklist!$K$2:$K$1000,"Pass") | D52: =COUNTIFS(Checklist!$B$2:$B$1000,$A52,Checklist!$K$2:$K$1000,"Fail") | E52: =COUNTIFS(Checklist!$B$2:$B$1000,$A52,Checklist!$K$2:$K$1000,"Blocked") | F52: =COUNTIFS(Checklist!$B$2:$B$1000,$A52,Checklist!$K$2:$K$1000,"N/A") | G52: =COUNTIFS(Checklist!$B$2:$B$1000,$A52,Checklist!$K$2:$K$1000,"Not Run") | H52: =IF(B52=0,0,(B52-G52)/B52) | I52: =IF(C52+D52=0,0,C52/(C52+D52))
... A66: 25 Code quality gates | B66: =COUNTIF(Checklist!$B$2:$B$1000,$A66) | C66: =COUNTIFS(Checklist!$B$2:$B$1000,$A66,Checklist!$K$2:$K$1000,"Pass") | D66: =COUNTIFS(Checklist!$B$2:$B$1000,$A66,Checklist!$K$2:$K$1000,"Fail") | E66: =COUNTIFS(Checklist!$B$2:$B$1000,$A66,Checklist!$K$2:$K$1000,"Blocked") | F66: =COUNTIFS(Checklist!$B$2:$B$1000,$A66,Checklist!$K$2:$K$1000,"N/A") | G66: =COUNTIFS(Checklist!$B$2:$B$1000,$A66,Checklist!$K$2:$K$1000,"Not Run") | H66: =IF(B66=0,0,(B66-G66)/B66) | I66: =IF(C66+D66=0,0,C66/(C66+D66))
A67: Total | B67: =SUM(B41:B66) | C67: =SUM(C41:C66) | D67: =SUM(D41:D66) | E67: =SUM(E41:E66) | F67: =SUM(F41:F66) | G67: =SUM(G41:G66) | H67: =IF(B67=0,0,(B67-G67)/B67) | I67: =IF(C67+D67=0,0,C67/(C67+D67)) | J67: =IF(B67=B18,"","Totals differ: a row on that sheet has a module name not listed here.")

Sheet Business Logic
A1: ID | B1: Module | C1: Sub-module | D1: Business rule under test | E1: Steps | F1: Expected result | G1: Priority | H1: Check type | I1: Source in code | J1: Needs / Blocker | K1: Status | L1: Tester | M1: Date tested | N1: Build | O1: Device / OS | P1: Defect ID | Q1: Notes / Actual result
A2: BL-AUTH-001 | B2: Authentication & session | C2: Onboarding & consent | D2: Terms box is required; offers box is optional | E2: 1. On the consent screen tap 'Agree and Continue' with the terms box unticked 2. Tick it | F2: 'Please accept the terms to continue.' and no navigation; the note clears on tick and the user can proceed. | G2: P0 | H2: Rule | I2: lib/features/auth/presentation/controllers/consent_form_controller.dart:68 | K2: Pass | L2: Claude (adb) | M2: 46299 | N2: 1.0.0+1 debug | O2: emulator-5554 / Android 14 | Q2: Agree and Continue with the terms box unticked shows 'Please accept the terms to continue.' and stays; ticking clears the note; offers box is optional; proceeds to sign-in.
A3: BL-AUTH-002 | B3: Authentication & session | C3: Onboarding & consent | D3: Onboarding is recorded once and survives sign-out | E3: 1. Complete onboarding 2. Kill and relaunch 3. Sign in, then log out | F3: Relaunch goes to sign-in; after logout the intro is not shown again. | G3: P1 | H3: State | I3: lib/core/storage/hive/boxes.dart:83 | K3: Pass | L3: Claude (adb) | M3: 46299 | N3: 1.0.0+1 debug | O3: emulator-5554 / Android 14 | Q3: Relaunch after onboarding goes to sign-in; after signing in and logging out (several times, incl. forced sign-out) the app returns to sign-in and never shows the intro again.
A4: BL-AUTH-003 | B4: Authentication & session | C4: Onboarding & consent | D4: Consent can be accepted without the Terms having loaded | E4: 1. Go offline 2. Tick the terms box and accept | F4: Confirm intended: the code lets the user continue and records an empty accepted version. | G4: P2 | H4: Verify gap | I4: lib/features/auth/infrastructure/data_sources/local/onboarding_local_ds.dart:54 | K4: Pass | L4: Claude (adb) | M4: 46299 | N4: 1.0.0+1 debug (rebuilt with fix) | O4: emulator-5554 / Android 14 | P4: DEF-042 | Q4: FIXED AND RETESTED (4 Oct 2026, rebuilt debug build). Before: in airplane mode the terms box could be ticked and accepted although the Terms could not be loaded, and an empty Terms version was stored (owner decision: not acceptable, DEF-042). After the fix: fresh install in airplane mode -> tick the box -> 'Agree and Continue' stays on the consent screen with 'We could not load the Terms & Conditions and Privacy Policy. Check your connection, then tap Agree and Continue again.'; relaunch still shows the intro (nothing recorded). After reconnecting, the same button loads the documents and moves on to sign-in, and the stored accepted Terms version is '1'. The unticked-box note ('Please accept the terms to continue.') still works.
A5: BL-AUTH-004 | B5: Authentication & session | C5: Onboarding & consent | D5: Offers opt-in reaches the account | E5: 1. Tick the offers box in onboarding 2. Sign up 3. Inspect the sign-up request and the profile's marketing preference | F5: Marketing consent should reflect the choice. The code always sends marketing = false at sign-up. | G5: P1 | H5: Verify gap | I5: lib/features/auth/presentation/controllers/auth_flow_draft.dart:91 | J5: KB-05 | K5: Blocked | L5: Claude (adb) | M5: 46299 | N5: 1.0.0+1 debug | O5: emulator-5554 / Android 14 | Q5: Fixed 04-Oct-2026: sign-up now sends the onboarding offers choice (lib/features/auth/presentation/controllers/signup_form_controller.dart, startMobileVerification). Retest on the fixed build, offers box ticked in onboarding: the signup/start body captured on a local recording server (app pointed at http://10.0.2.2:8000) carries consents.marketing = true; unit tests cover ticked and unticked (test/features/auth/signup_server_errors_test.dart). Still blocked for the account half by KB-05: sign-up with +91 9746863592 on the integration server reached 'Verify Mobile' but no SMS arrived (resend tried once), so the account was not created and the profile's marketing preference could not be checked.
A6: BL-AUTH-005 | B6: Authentication & session | C6: Onboarding & consent | D6: Intro can be skipped by a deep link | E6: 1. Fresh install 2. Open medibook://login or medibook://signup | F6: Decide what is correct: the code opens sign-in / sign-up directly, skipping the intro and consent screen (sign-up has its own legal checkbox). | G6: P2 | H6: Verify gap | I6: lib/app/router/app_router.dart:466 | K6: Pass | L6: Claude (adb) | M6: 46299 | N6: 1.0.0+1 debug | O6: emulator-5554 / Android 14 | P6: DEF-043 | Q6: FIXED AND RETESTED (4 Oct 2026, rebuilt debug build). Owner decision (4 Oct 2026): links must never skip the intro (DEF-043). Before: with the app already open on the intro (not completed), medibook://signup and medibook://login opened Create Account / sign-in directly, skipping the intro and consent screen. After the fix, on a fresh install: with the app open on the intro, medibook://signup, medibook://login and https://medibook.app/login (sent straight to the app) all stay on the intro; opened from the consent screen they go back to the intro; a cold start with either medibook:// link shows the intro. After completing the intro, medibook://signup opens Create Account and medibook://login opens sign-in. The Terms link on the consent screen still opens the document. Routing tests added in test/app/sign_in_routing_test.dart.
A7: BL-AUTH-006 | B7: Authentication & session | C7: Sign-up | D7: First name rules | E7: Submit with first name empty, 'A', and 'An1ta' | F7: 'Enter your first name' / 'Name is too short' / 'Use letters only'. Names like D'Souza and Anne-Marie pass. | G7: P1 | H7: Boundary | I7: lib/features/auth/presentation/controllers/signup_form_controller.dart:58 | K7: Pass | L7: Claude (adb) | M7: 46299 | N7: 1.0.0+1 debug | O7: emulator-5554 / Android 14 | Q7: Empty: 'Enter your first name'; 'A': 'Name is too short'; 'An1ta': 'Use letters only'; D'Souza accepted.
A8: BL-AUTH-007 | B8: Authentication & session | C8: Sign-up | D8: Mobile number is an Indian mobile: 10 digits starting 6–9 | E8: Submit empty, 9 digits, and a number starting with 5 | F8: 'Enter your mobile number' / 'Mobile number must be 10 digits' / 'Mobile number must start with 6-9'. | G8: P0 | H8: Boundary | I8: lib/core/utils/validators.dart:54 | K8: Pass | L8: Claude (adb) | M8: 46299 | N8: 1.0.0+1 debug | O8: emulator-5554 / Android 14 | Q8: Empty: 'Enter your mobile number'; 9 digits: 'Mobile number must be 10 digits'; starting 5: 'Mobile number must start with 6-9' (same on sign-in Mobile tab).
A9: BL-AUTH-008 | B9: Authentication & session | C9: Sign-up | D9: Non-Indian country codes | E9: 1. Pick +971 in the country picker 2. Enter a valid 9-digit UAE number | F9: Decide what is correct: the picker offers other countries, but validation is always the Indian rule, so the number is rejected. | G9: P2 | H9: Verify gap | I9: lib/core/widgets/app_phone_field.dart:68 | K9: Pass | L9: Claude (adb) | M9: 46300 | N9: 1.0.0+1 debug | O9: emulator-5554 / Android 14 | P9: DEF-001 | Q9: FIXED AND RETESTED (5 Oct 2026, rebuilt debug build; DEF-001). The API takes only Indian mobiles for sign-in, sign-up, password reset, number change and family hand-over (§2: ^\+91[6-9]\d{9}$), so those screens are now fixed to +91: the country chip is not tappable and no picker opens (login_screen, signup_screen, forgot_password_screen, phone_change_screen, dependant_edit_screen release sheet). Emergency contacts, the alternate number and a family member's own phone keep the picker - the API accepts any E.164 there and those fields already validate foreign numbers. Emulator: signed out, Mobile tab shows 'Country code +91 India' (not clickable); tapping it opens nothing (+971 not shown). Test added (sign_in_routing_test.dart). First observed: Country picker offers +971 (and 8 other non-Indian codes); with +971 selected a valid 9-digit UAE mobile (501234567) is rejected with 'Mobile number must be 10 digits'. The non-Indian options can never be used.
A10: BL-AUTH-009 | B10: Authentication & session | C10: Sign-up | D10: Account holder must be 18 or older | E10: 1. Open the date picker and look for dates under 18 years ago 2. Force an under-age date via the server | F10: Picker stops at today minus 18 years; a server refusal shows the 18+ message under Date of birth. | G10: P0 | H10: Boundary | I10: lib/features/auth/presentation/controllers/signup_form_controller.dart:97 | K10: Pass | L10: Claude (adb) | M10: 46299 | N10: 1.0.0+1 debug | O10: emulator-5554 / Android 14 | Q10: Date picker opens on 4 Oct 2008 (today minus 18 years); 5 Oct 2008 onward is 'Out of range' and Next month/year are disabled. Server-side under-age refusal not exercised (cannot bypass the picker). Note: the Date of Birth label, placeholder and its error 'Select a date of birth' are drawn on screen but missing from the accessibility tree.
A11: BL-AUTH-010 | B11: Authentication & session | C11: Sign-up | D11: Password is optional; if given, at least 10 characters and confirmed | E11: 1. Leave both password fields empty 2. Enter 9 characters 3. Enter 10 with a different confirmation | F11: Empty is accepted (code-only account); 'At least 10 characters'; 'Passwords do not match'. | G11: P0 | H11: Boundary | I11: lib/features/auth/presentation/controllers/signup_form_controller.dart:71 | K11: Pass | L11: Claude (adb) | M11: 46299 | N11: 1.0.0+1 debug | O11: emulator-5554 / Android 14 | Q11: Both empty: no password error on submit. 9 chars: 'At least 10 characters'. 10 chars with different confirmation: 'Passwords do not match'.
A12: BL-AUTH-011 | B12: Authentication & session | C12: Sign-up | D12: Password containing personal details | E12: Use a 10+ character password containing your first name or phone number | F12: Server refuses it and the message appears under the password field (the app does not pre-check this). | G12: P2 | H12: Error handling | I12: lib/core/utils/validators.dart:30 | K12: Pass | L12: Claude (adb) | M12: 46299 | N12: 1.0.0+1 debug | O12: emulator-5554 / Android 14 | Q12: Password containing the phone number (9123456791ab) passes the app's checks; the server refuses and 'The password must not contain your name, email or phone number.' is shown under the password field.
A13: BL-AUTH-012 | B13: Authentication & session | C13: Sign-up | D13: Address is all-or-nothing | E13: 1. Fill only City and submit 2. Enter PIN 012345 3. Enter line 1 'abc' | F13: Once any of line 1 / city / state / PIN is filled all four are required; 'Enter a valid PIN code'; 'Address looks too short'. Label alone does not trigger it. | G13: P2 | H13: Rule | I13: lib/features/auth/presentation/controllers/signup_form_controller.dart:166 | K13: Pass | L13: Claude (adb) | M13: 46299 | N13: 1.0.0+1 debug | O13: emulator-5554 / Android 14 | Q13: With only City filled: 'Enter a street address', 'Enter a state', 'Enter a PIN code'. PIN 012345: 'Enter a valid PIN code'; 5 digits: 'PIN code must be 6 digits'; line 1 'abc': 'Address looks too short'. Label alone ('Home' prefilled) does not trigger it.
A14: BL-AUTH-013 | B14: Authentication & session | C14: Sign-up | D14: Legal checkbox is required | E14: Submit with the box unticked | F14: 'Accept the Terms, Privacy Policy and User Guidelines to continue'. | G14: P0 | H14: Rule | I14: lib/features/auth/presentation/controllers/signup_form_controller.dart:89 | K14: Pass | L14: Claude (adb) | M14: 46299 | N14: 1.0.0+1 debug | O14: emulator-5554 / Android 14 | Q14: Submitting with the legal box unticked shows 'Accept the Terms, Privacy Policy and User Guidelines to continue'.
A15: BL-AUTH-014 | B15: Authentication & session | C15: Sign-up | D15: No account exists until the code is verified | E15: 1. Submit a valid form 2. On the verify screen press Back 3. Try to sign in with those details | F15: Form is refilled except the password fields; sign-in fails because no account was created yet. | G15: P1 | H15: State | I15: lib/features/auth/presentation/controllers/signup_form_controller.dart:200 | J15: KB-05 | K15: Pass | L15: Claude (adb) | M15: 46299 | N15: 1.0.0+1 debug | O15: emulator-5554 / Android 14 | Q15: Valid form -> 'Verify Mobile … Verify & Create Account'. Back returns to the form with name, mobile, date of birth and address refilled and both password fields empty. API sign-in with those details: AUTH_INVALID_CREDENTIALS (no account created).
A16: BL-AUTH-015 | B16: Authentication & session | C16: Sign-up | D16: Server errors land on their fields | E16: 1. Use an already-registered number 2. Trigger server errors on email and address fields | F16: Each message under its own field (phone, email, date of birth, password, address lines, consents); anything else in the form banner. | G16: P1 | H16: Error handling | I16: lib/features/auth/presentation/controllers/signup_form_controller.dart:225 | K16: Pass | L16: Claude (adb) | M16: 46299 | N16: 1.0.0+1 debug | O16: emulator-5554 / Android 14 | Q16: Registered number: 'This mobile number is already registered. Log in instead.' under the mobile field. Server password refusal appears under the password field. (Email/address server errors not triggered.)
A17: BL-AUTH-016 | B17: Authentication & session | C17: Sign-up | D17: Successful sign-up signs the user in | E17: Enter the correct code | F17: 'Welcome to Medibook, <first name>!' and Home; booking 'for myself' works immediately. | G17: P0 | H17: State | I17: lib/features/auth/presentation/screen/verify_code_screen.dart:125 | J17: KB-05 | K17: Blocked | L17: Claude (adb) | M17: 46299 | N17: 1.0.0+1 debug | O17: emulator-5554 / Android 14 | Q17: KB-05: the server sends no SMS, so a correct sign-up code cannot be entered.
A18: BL-AUTH-017 | B18: Authentication & session | C18: OTP verification | D18: Local checks before any request | E18: Tap Verify with nothing entered and with fewer digits | F18: 'Enter the code' / 'Enter all N digits'; no request is sent. The number of boxes equals the server's code length. | G18: P1 | H18: Boundary | I18: lib/features/auth/presentation/controllers/verify_controller.dart:64 | K18: Pass | L18: Claude (adb) | M18: 46299 | N18: 1.0.0+1 debug | O18: emulator-5554 / Android 14 | Q18: Verify with nothing entered: 'Enter the code'; with 2 digits: 'Enter all 4 digits'. 4 boxes match the server's otp_length (4).
A19: BL-AUTH-018 | B19: Authentication & session | C19: OTP verification | D19: Wrong, expired and exhausted codes | E19: 1. Enter a wrong code 2. Wait over 180 s and enter the code 3. Enter 3 wrong codes | F19: 'That code is not right. Check it and try again. 2 attempts left.' / 'That code has expired. Request a new one.' / 'Too many wrong codes. Request a new code to continue.' | G19: P0 | H19: Error handling | I19: lib/core/network/network_exceptions.dart:478 | J19: KB-05 | K19: Pass | L19: Claude (adb) | M19: 46299 | N19: 1.0.0+1 debug | O19: emulator-5554 / Android 14 | Q19: Wrong codes: 'That code is not right. Check it and try again. 2 attempts left.' -> '1 attempt left.' -> 'Too many wrong codes. Request a new code to continue.' After 186 s: 'The code has expired.' (Minor: after 'Resend code' the old 'Too many wrong codes' error stays on screen.)
A20: BL-AUTH-019 | B20: Authentication & session | C20: OTP verification | D20: Resend replaces the challenge | E20: 1. Tap 'Resend Code' 2. Enter the old code, then the new one | F20: 'Code re-sent to your mobile number'; the old code fails, the new one works. | G20: P1 | H20: State | I20: lib/features/auth/presentation/controllers/verify_controller.dart:92 | J20: KB-05 | K20: Blocked | L20: Claude (adb) | M20: 46299 | N20: 1.0.0+1 debug | O20: emulator-5554 / Android 14 | Q20: KB-05: no SMS on this server, so old-vs-new code cannot be compared. Verified only that 'Resend code' shows the toast 'Code re-sent to your mobile number'.
A21: BL-AUTH-020 | B21: Authentication & session | C21: OTP verification | D21: Resend cooldown and code-expiry countdown | E21: Arrive on the verify screen and tap 'Resend Code' immediately, several times | F21: A 30 s cooldown / countdown is expected. The code leaves the button always tappable and relies on the server's 'too many attempts' answer. | G21: P1 | H21: Verify gap | I21: lib/features/auth/presentation/screen/verify_code_screen.dart:283 | J21: KB-05 | K21: Pass | L21: Claude (adb) | M21: 46300 | N21: 1.0.0+1 debug | O21: emulator-5554 / Android 14 | P21: DEF-002 | Q21: FIXED AND RETESTED (5 Oct 2026, rebuilt debug build; DEF-002). The code screen now counts down to the challenge's resend_after_seconds before Resend is offered ('Resend in 00:15', not tappable), and shows the code's own life from expires_at ('Code expires in 02:46'; after expiry 'This code has expired. Tap Resend Code for a new one.'). A resend restarts both. Emulator: mobile sign-in for Sanjay -> 'Code expires in 02:46' and 'Didn't get the code? Resend in 00:15'. Test added (sign_in_routing_test.dart). First observed: No resend cooldown or countdown on the verify screen: 'Resend code' is tappable immediately on arrival; tapping it at once gave the server banner 'Too many attempts. Please wait a moment and try again.' No expiry countdown for the 180 s code either.
A22: BL-AUTH-021 | B22: Authentication & session | C22: OTP verification | D22: Verify screen opened without a code request | E22: 1. Open the verify deep link with no parameters 2. Enter a code | F22: 'This code request has expired. Go back and ask for a new code.' | G22: P2 | H22: Error handling | I22: lib/features/auth/presentation/controllers/verify_controller.dart:53 | K22: Pass | L22: Claude (adb) | M22: 46300 | N22: 1.0.0+1 debug | O22: emulator-5554 / Android 14 | Q22: PASS (5 Oct 2026, debug build). Still not reachable from outside the app, which is intended: medibook://verify opens 'Page not found' and every in-app path passes a code request. The guard itself is covered by test/features/auth/verify_purpose_test.dart: opened with no code request, entering 1234 shows 'This code request has expired. Go back and ask for a new code.' and nothing is sent to the server. Earlier note: Not reachable by a user: medibook://verify (no parameters) opens 'Page not found', so the orphan verify screen cannot be opened from outside the app.
A23: BL-AUTH-022 | B23: Authentication & session | C23: OTP verification | D23: Phone-change purpose on the generic verify screen | E23: 1. While signed in open /verify?purpose=phone-change&ch=x&len=4 2. Enter any 4 digits | F23: Nothing should be 'verified'. The code accepts any well-formed code with no server call and opens Edit Profile (no number actually changes). | G23: P2 | H23: Verify gap | I23: lib/features/auth/presentation/controllers/verify_controller.dart:149 | K23: Pass | L23: Claude (adb) | M23: 46300 | N23: 1.0.0+1 debug | O23: emulator-5554 / Android 14 | P23: DEF-072 | Q23: PASS (5 Oct 2026, debug build). FIXED (DEF-072): the generic verify screen no longer has a phone-change purpose (the number change confirms both codes on its own /profile/phone screen, which nothing else used). A /verify?purpose=phone-change&ch=x&len=4 link is now checked by the server like any other code, so a made-up code is refused and nothing is 'verified'. Covered by test/features/auth/verify_purpose_test.dart; the route is still not open to external links. Earlier note: Not reachable by a user: the verify route is not exposed to external links (medibook://verify -> 'Page not found'); no in-app path opens /verify with purpose=phone-change.
A24: BL-AUTH-023 | B24: Authentication & session | C24: OTP verification | D24: What a correct code does depends on the flow | E24: Complete sign-up, mobile sign-in and password reset | F24: Buttons read 'Verify & Create Account' / 'Verify & Log In' / 'Verify'; destinations are Home, Home and the new-password screen. | G24: P1 | H24: Rule | I24: lib/features/auth/presentation/screen/verify_code_screen.dart:124 | J24: KB-05 | K24: Blocked | L24: Claude (adb) | M24: 46299 | N24: 1.0.0+1 debug | O24: emulator-5554 / Android 14 | Q24: KB-05: correct codes are not obtainable. Observed only the mobile sign-in label 'Verify & Log In' and title 'Verify Mobile'.
A25: BL-AUTH-024 | B25: Authentication & session | C25: Password sign-in | D25: Identifier must be an email or a full +91 number | E25: 1. Submit empty 2. Submit '9845658525' on the email/mobile field 3. Submit with an empty password | F25: 'Enter your email or mobile number' / 'Enter a valid email address or mobile number' / 'Enter your password'. Confirm a bare 10-digit number should be rejected here. | G25: P1 | H25: Boundary | I25: lib/features/auth/presentation/controllers/login_form_controller.dart:49 | K25: Pass | L25: Claude (adb) | M25: 46299 | N25: 1.0.0+1 debug | O25: emulator-5554 / Android 14 | Q25: Empty: 'Enter your email or mobile number' + 'Enter your password'. Bare 10-digit number: 'Enter a valid email address or mobile number' (a +91 prefix is required on this tab — confirm intended).
A26: BL-AUTH-025 | B26: Authentication & session | C26: Password sign-in | D26: Malformed input never spends a server attempt | E26: Submit a malformed identifier with a proxy attached | F26: No sign-in request is sent; attempts remaining is unchanged. | G26: P1 | H26: Rule | I26: lib/features/auth/application/usecases/login.dart:116 | K26: Pass | L26: Claude (adb) | M26: 46299 | N26: 1.0.0+1 debug | O26: emulator-5554 / Android 14 | Q26: No proxy available; verified indirectly: after two malformed submissions the first real wrong password still reported '4 attempts left', so no server attempt was spent.
A27: BL-AUTH-026 | B27: Authentication & session | C27: Password sign-in | D27: Wrong password shows attempts left | E27: Enter wrong passwords one at a time | F27: 'That email or number and password do not match an account. 4 attempts left.' counting down to '1 attempt left.' | G27: P0 | H27: Error handling | I27: lib/core/network/network_exceptions.dart:330 | K27: Pass | L27: Claude (adb) | M27: 46299 | N27: 1.0.0+1 debug | O27: emulator-5554 / Android 14 | Q27: Wrong passwords on a spare account: 'That email or number and password do not match an account. 3 attempts left.' -> '2 attempts left.' -> '1 attempt left.' (the count started at 4 on the first attempt earlier in the run).
A28: BL-AUTH-027 | B28: Authentication & session | C28: Password sign-in | D28: Blocked account | E28: Sign in to a blocked account | F28: 'This account has been blocked. Contact Medibook support.'; attempts counter unchanged. | G28: P1 | H28: Error handling | I28: lib/core/network/network_exceptions.dart:330 | K28: Blocked | L28: Claude (adb) | M28: 46299 | N28: 1.0.0+1 debug | O28: emulator-5554 / Android 14 | Q28: Seed data: every seeded patient account is active; no blocked account to sign in to.
A29: BL-AUTH-028 | B29: Authentication & session | C29: Password sign-in | D29: What is stored after sign-in | E29: 1. Sign in 2. Inspect secure storage and the Hive auth box on a debug build | F29: Tokens and session id only in secure storage; the Hive box holds id, name, phone and flags — no tokens. | G29: P0 | H29: Rule | I29: lib/features/auth/infrastructure/repositories/auth_repository_impl.dart:246 | K29: Pass | L29: Claude (adb) | M29: 46299 | N29: 1.0.0+1 debug | O29: emulator-5554 / Android 14 | Q29: On-device inspection (run-as): no JWT in any Hive file or plain prefs; tokens live only in FlutterSecureStorage (encrypted values). Hive auth box holds user id, first/last name, phone, has_password, version, last_login_at.
A30: BL-AUTH-029 | B30: Authentication & session | C30: OTP sign-in | D30: Unregistered number is indistinguishable at 'Send Code' | E30: 1. Request a code for a number with no account 2. Enter any code | F30: Verify screen opens normally; 'That code is not right. Check it and try again.' | G30: P1 | H30: Rule | I30: lib/features/auth/infrastructure/repositories/auth_repository_impl.dart:63 | K30: Pass | L30: Claude (adb) | M30: 46299 | N30: 1.0.0+1 debug | O30: emulator-5554 / Android 14 | Q30: Unregistered number 9123456781: 'Send Code' opens the normal verify screen ('We sent a 4-digit code to +919123456781.'); a code gives 'That code is not right. Check it and try again. 2 attempts left.' — no hint that the number has no account.
A31: BL-AUTH-030 | B31: Authentication & session | C31: OTP sign-in | D31: Switching Email / Mobile tab resets errors | E31: 1. Cause an error on one tab 2. Switch tabs | F31: Errors clear; button reads 'Log In' on Email and 'Send Code' on Mobile. | G31: P3 | H31: State | I31: lib/features/auth/presentation/screen/login_screen.dart:146 | K31: Pass | L31: Claude (adb) | M31: 46299 | N31: 1.0.0+1 debug | O31: emulator-5554 / Android 14 | Q31: Switching Email -> Mobile cleared the offline banner and field errors; button reads 'Log In' on Email and 'Send Code' on Mobile.
A32: BL-AUTH-031 | B32: Authentication & session | C32: Lockout | D32: Attempt warnings escalate | E32: Enter wrong passwords one by one | F32: Amber 'Sign-in attempts — N attempts left…' while more than one remains; red 'One attempt left' at one. | G32: P1 | H32: State | I32: lib/features/auth/presentation/components/lockout_notice.dart:91 | K32: Pass | L32: Claude (adb) | M32: 46299 | N32: 1.0.0+1 debug | O32: emulator-5554 / Android 14 | Q32: Amber 'Sign-in attempts — N attempts left before sign-in is paused for 60 seconds.' while more than one remains; red 'One attempt left — The next wrong password pauses sign-in for 60 seconds. Use "Forgot password?" if you are not sure.' at one.
A33: BL-AUTH-032 | B33: Authentication & session | C33: Lockout | D33: Warning text states the real pause length | E33: 1. Read the warning before lockout 2. Get locked out and read the countdown | F33: They should agree. The warning says 'paused for 60 seconds' while the server locks for about an hour. | G33: P1 | H33: Verify gap | I33: lib/app/config/constants.dart:50 | K33: Pass | L33: Claude (adb) | M33: 46300 | N33: 1.0.0+1 debug | O33: emulator-5554 / Android 14 | P33: DEF-003 | Q33: FIXED (5 Oct 2026; DEF-003); checked by automated test, not on the emulator (five wrong passwords would lock a shared seeded account for an hour). The warnings now name the server's real pause, one hour (API §4, 423 AUTH_LOCKED_OUT): '2 attempts left before sign-in is paused for 1 hour.' and 'The next wrong password pauses sign-in for 1 hour.' (AppConstants.loginLockoutCooldown = 1 hour; lockout_notice.dart words it). The countdown itself still runs to the server's locked_until. Test added (lockout_notice_test.dart). First observed: The warnings say sign-in will be 'paused for 60 seconds', but after the fifth failure the lockout countdown starts at 59:57 — about one hour. The warning understates the pause sixty-fold.
A34: BL-AUTH-033 | B34: Authentication & session | C34: Lockout | D34: Lockout disables sign-in with a live countdown | E34: Fail 5 times | F34: 'Too many failed attempts — Sign-in is paused for your security. Try again in mm:ss.'; fields and button disabled. | G34: P0 | H34: State | I34: lib/features/auth/application/usecases/login.dart:141 | K34: Pass | L34: Claude (adb) | M34: 46299 | N34: 1.0.0+1 debug | O34: emulator-5554 / Android 14 | Q34: After the fifth failure: 'Too many failed attempts — Sign-in is paused for your security. Try again in 59:57.' with a live countdown; the Log In button is disabled ('paused after too many failed attempts').
A35: BL-AUTH-034 | B35: Authentication & session | C35: Lockout | D35: Lockout survives a force-quit and lifts on its own | E35: 1. Get locked out 2. Kill and relaunch 3. Wait for 00:00 | F35: Countdown still showing after relaunch; at zero the form re-enables without restarting. | G35: P0 | H35: State | I35: lib/features/auth/application/providers/auth_provider.dart:292 | K35: Pass | L35: Claude (adb) | M35: 46299 | N35: 1.0.0+1 debug | O35: emulator-5554 / Android 14 | Q35: After force-stop and relaunch the lockout notice is still shown with the countdown continuing ('again in 59:36'). The automatic lift at 00:00 was not waited for (one hour).
A36: BL-AUTH-035 | B36: Authentication & session | C36: Lockout | D36: Lockout scope on a shared device | E36: 1. Lock account A 2. On the same device try to sign in as B, sign up, and use Forgot password | F36: Decide what is correct: the code blocks all of these locally while A's lock runs, although the warning itself suggests using 'Forgot password?'. | G36: P1 | H36: Verify gap | I36: lib/features/auth/application/providers/auth_provider.dart:268 | K36: Pass | L36: Claude (adb) | M36: 46300 | N36: 1.0.0+1 debug | O36: emulator-5554 / Android 14 | P36: DEF-004 | Q36: FIXED (5 Oct 2026; DEF-004); checked by automated test, not on the emulator (it needs a real one-hour lockout of a shared account). The lockout is now remembered with the account it belongs to (locked_identifier next to locked_until) and applies only to that account: another account on the same phone can sign in, ask for a code or reset a password; the locked account is still refused without a request. On the sign-in screen the warning and the disabled Log In follow the account typed, and the account field stays editable. A lockout remembered before this change (no account) still applies to all. Tests added (lockout_scope_test.dart). First observed: With the device locked out by one account's failed attempts, 'Forgot password?' for a DIFFERENT account's number is refused locally: 'Too many failed attempts. Try again in 60 minutes.' The lock is device-wide — nobody else can sign in, sign up or reset a password on this device for an hour, and it blocks the very 'Forgot password?' route the last-attempt warning recommends.
A37: BL-AUTH-036 | B37: Authentication & session | C37: Lockout | D37: Wrong OTP must not show a password-attempt warning | E37: 1. On mobile sign-in enter one wrong code 2. Go back to the sign-in screen | F37: No password warning. The code shows '2 attempts left before sign-in is paused…' although no password was tried. | G37: P2 | H37: Verify gap | I37: lib/features/auth/application/usecases/login.dart:144 | K37: Pass | L37: Claude (adb) | M37: 46300 | N37: 1.0.0+1 debug | O37: emulator-5554 / Android 14 | P37: DEF-005 | Q37: FIXED AND RETESTED (5 Oct 2026, rebuilt debug build; DEF-005). A wrong sign-in code no longer sets the password-attempt count: its attempts stay on the code screen. Emulator: mobile sign-in for Sanjay, code 0000 -> 'That code is not right. Check it and try again. 2 attempts left.'; Back -> the sign-in screen (Mobile and Email tabs) shows no 'Sign-in attempts' warning. Then signed in again by email. Test added (lockout_scope_test.dart). First observed: After one wrong OTP on mobile sign-in, going back to the sign-in screen shows the password warning 'Sign-in attempts — 2 attempts left before sign-in is paused for 60 seconds.' although no password was tried (OTP attempts are written into the password-attempt counter).
A38: BL-AUTH-037 | B38: Authentication & session | C38: Lockout | D38: A network failure clears the attempts notice | E38: 1. Enter a wrong password 2. Submit again in airplane mode | F38: Offline message; the attempts notice is gone (count unknown). | G38: P3 | H38: State | I38: lib/features/auth/application/providers/auth_provider.dart:250 | K38: Pass | L38: Claude (adb) | M38: 46299 | N38: 1.0.0+1 debug | O38: emulator-5554 / Android 14 | Q38: After a wrong password (attempts notice visible), submitting in airplane mode shows 'You appear to be offline. Check your connection and try again.' and the attempts notice is gone.
A39: BL-AUTH-038 | B39: Authentication & session | C39: Forgot / reset password | D39: Email identifier does not reveal the phone number | E39: Start a reset with a registered email | F39: 'We sent a 4-digit code to your mobile number.' — no digits shown. | G39: P1 | H39: Rule | I39: lib/features/auth/presentation/screen/forgot_password_screen.dart:81 | K39: Pass | L39: Claude (adb) | M39: 46299 | N39: 1.0.0+1 debug | O39: emulator-5554 / Android 14 | Q39: Bad email: 'Enter a valid email address'. Registered email: verify screen says 'We sent a 4-digit code to your mobile number.' — no digits revealed.
A40: BL-AUTH-039 | B40: Authentication & session | C40: Forgot / reset password | D40: Reset permission lives only in memory | E40: 1. Verify the reset code 2. Kill the app on the new-password screen 3. Reopen it and submit | F40: 'That reset link has expired. Request a new code to continue.'; no request is sent. | G40: P2 | H40: State | I40: lib/features/auth/presentation/controllers/reset_form_controller.dart:65 | J40: KB-05 | K40: Blocked | L40: Claude (adb) | M40: 46299 | N40: 1.0.0+1 debug | O40: emulator-5554 / Android 14 | Q40: KB-05: the reset code is never delivered on this server, so the flow cannot pass the verify step.
A41: BL-AUTH-040 | B41: Authentication & session | C41: Forgot / reset password | D41: Reset window of 15 minutes | E41: 1. Verify the code 2. Wait over 15 minutes 3. Submit a new password | F41: 'That reset code has expired. Request a new one to continue.' | G41: P2 | H41: Boundary | I41: lib/features/auth/presentation/controllers/reset_form_controller.dart:80 | J41: KB-05 | K41: Blocked | L41: Claude (adb) | M41: 46299 | N41: 1.0.0+1 debug | O41: emulator-5554 / Android 14 | Q41: KB-05: the reset code is never delivered on this server, so the flow cannot pass the verify step.
A42: BL-AUTH-041 | B42: Authentication & session | C42: Forgot / reset password | D42: Reset does not sign the user in | E42: Complete a reset | F42: 'Password reset — please log in'; sign-in screen; old password rejected; other devices signed out. | G42: P0 | H42: State | I42: lib/features/auth/presentation/screen/new_password_screen.dart:72 | J42: KB-05 | K42: Blocked | L42: Claude (adb) | M42: 46299 | N42: 1.0.0+1 debug | O42: emulator-5554 / Android 14 | Q42: KB-05: the reset code is never delivered on this server, so the flow cannot pass the verify step.
A43: BL-AUTH-042 | B43: Authentication & session | C43: Change password | D43: Menu row depends on whether a password exists | E43: Open Profile on a password account and on a code-only account | F43: 'Change password' vs 'Set a password'. | G43: P2 | H43: Rule | I43: lib/features/auth/presentation/controllers/change_password_form_controller.dart:126 | K43: Pass | L43: Claude (adb) | M43: 46299 | N43: 1.0.0+1 debug | O43: emulator-5554 / Android 14 | Q43: Password account: Profile row 'Change password — You will need your current password'. Code-only account not reachable (KB-05).
A44: BL-AUTH-043 | B44: Authentication & session | C44: Change password | D44: New password rules | E44: 1. Submit with current empty 2. 9-character new 3. New equal to current 4. Mismatched confirmation | F44: 'Enter your password' / 'At least 10 characters' / 'Choose a password you have not used before' / 'Passwords do not match'. | G44: P1 | H44: Boundary | I44: lib/features/auth/presentation/controllers/change_password_form_controller.dart:59 | K44: Pass | L44: Claude (adb) | M44: 46300 | N44: 1.0.0+1 debug | O44: emulator-5554 / Android 14 | P44: DEF-006 | Q44: FIXED AND RETESTED (5 Oct 2026, rebuilt debug build; DEF-006). The shared new-password fields took their hint from a hard-coded 'At least 6 characters'; they now use the enforced minimum (SignupFormController.passwordMinLength = 10, API §4 password rules), so Change password and the reset screen both say 'At least 10 characters'. Emulator: Profile > Change password shows 'At least 10 characters' under New Password. The rules themselves were already right. Test added (new_password_hint_test.dart). First observed: The rules themselves work: empty current 'Enter your password'; 9-character new 'At least 10 characters'; new = current 'Choose a password you have not used before'; mismatch 'Passwords do not match'. But the New Password placeholder and helper both read 'At least 6 characters' (KB-09), contradicting the enforced 10 — a user following the hint is always rejected.
A45: BL-AUTH-044 | B45: Authentication & session | C45: Change password | D45: Wrong current password is a field error, not a sign-out | E45: Enter a wrong current password | F45: 'That is not your current password' under the field; still signed in. | G45: P0 | H45: Error handling | I45: lib/features/auth/presentation/controllers/change_password_form_controller.dart:99 | K45: Pass | L45: Claude (adb) | M45: 46299 | N45: 1.0.0+1 debug | O45: emulator-5554 / Android 14 | Q45: Wrong current password: 'That is not your current password' under Current Password; the user stays on the screen, signed in.
A46: BL-AUTH-045 | B46: Authentication & session | C46: Change password | D46: Code-only account setting a password | E46: Open 'Set a password' on an account without one | F46: No current-password field should be asked for. The code still shows it (and ignores what is typed). | G46: P2 | H46: Verify gap | I46: lib/features/auth/presentation/screen/change_password_screen.dart:188 | K46: Blocked | L46: Claude (adb) | M46: 46299 | N46: 1.0.0+1 debug | O46: emulator-5554 / Android 14 | Q46: KB-05: a code-only account cannot be signed in to without a delivered code.
A47: BL-AUTH-046 | B47: Authentication & session | C47: Change password | D47: Success keeps this session | E47: Change the password | F47: 'Password updated'; still signed in here; other devices signed out; the Profile row now reads 'Change password'. | G47: P1 | H47: State | I47: lib/features/auth/presentation/screen/change_password_screen.dart:122 | K47: Blocked | L47: Claude (adb) | M47: 46299 | N47: 1.0.0+1 debug | O47: emulator-5554 / Android 14 | Q47: Not executed: changing the password would alter the shared seed password (seed_password_123) for this test account.
A48: BL-AUTH-047 | B48: Authentication & session | C48: Session & token refresh | D48: Relaunch after the access token expired | E48: 1. Sign in 2. Relaunch more than 15 minutes later | F48: Home opens with no sign-in flash; the first request refreshes silently. | G48: P0 | H48: State | I48: lib/features/auth/application/providers/auth_provider.dart:95 | K48: Pass | L48: Claude (adb) | M48: 46300 | N48: 1.0.0+1 debug | O48: emulator-5554 / Android 14 | P48: DEF-044 | Q48: FIXED AND RETESTED (5 Oct 2026, rebuilt debug build). Before (5 Oct): relaunching 16 min after sign-in landed on the sign-in screen with the session cleared, twice, because two refresh calls went out at once (DEF-044); an earlier run on 4 Oct had passed, so it depended on timing. After the fix: closed the app and relaunched after the 15-minute access token had expired - with the call recorder attached (exactly one refresh, Home loaded) and on the normal build without it (Home opened within 4 s, signed in, data loaded, no sign-in screen).
A49: BL-AUTH-048 | B49: Authentication & session | C49: Session & token refresh | D49: One refresh for many expired requests, each retried once | E49: 1. Let the access token expire 2. Open Home with a proxy attached | F49: Exactly one refresh call; all requests then succeed. | G49: P0 | H49: Rule | I49: lib/core/network/api_client.dart:570 | K49: Pass | L49: Claude (adb) | M49: 46300 | N49: 1.0.0+1 debug | O49: emulator-5554 / Android 14 | P49: DEF-044 | Q49: FIXED AND RETESTED (5 Oct 2026, rebuilt debug build). Calls watched through a pass-through recorder on the host (app pointed at http://10.0.2.2:8000, which forwards to the integration server). Before: opening the app after the access token expired sent TWO POST /patient/auth/token/refresh calls about 0.1 s apart - one from the API client after the 401s, one from the inbox socket after its handshake was refused (403). The server answered the second with 401 AUTH_SESSION_REVOKED and the app dropped to the sign-in screen. Seen with the recorder and on the normal build without it; reproduced on demand by having the recorder treat the token as expired (2 refreshes 2 ms apart) (DEF-044). After the fix (every refresh shares one call: auth_repository_impl.dart, api_client.dart, core/realtime/ws_session.dart): simulated expiry on cold start, 5 runs out of 5 - three 401s plus the socket 403, exactly ONE refresh, each request retried once, Home loaded; real expiry with the recorder (app closed 9 min past a 15-minute token) - three 401 AUTH_TOKEN_EXPIRED plus the socket 403, exactly ONE refresh (200), Home loaded; real expiry on the normal build with no recorder (app closed 15 min) - Home opened signed in with data, session intact. Also seen: with the app left open, the inbox socket alone refreshed once when the token expired. Unit tests added in test/features/auth/session_refresh_single_flight_test.dart and test/core/network/dio_api_client_test.dart.
A50: BL-AUTH-049 | B50: Authentication & session | C50: Session & token refresh | D50: Session-ending answers sign the user out once | E50: 1. Revoke the session from another device (or block the account) 2. Use the app | F50: User lands on sign-in once (no repeated redirects); local data cleared; relaunch stays signed out. | G50: P0 | H50: State | I50: lib/core/network/api_client.dart:577 | K50: Pass | L50: Claude (adb) | M50: 46299 | N50: 1.0.0+1 debug | O50: emulator-5554 / Android 14 | Q50: The emulator's session was revoked from another client; on the next authenticated screen (Appointments) the app went to the sign-in screen once, with no redirect loop. Local data was wiped: all cache boxes and the auth box are empty and secure storage keeps only the device fingerprint.
A51: BL-AUTH-050 | B51: Authentication & session | C51: Session & token refresh | D51: User is told why they were signed out | E51: 1. Have the session revoked 2. Look at the sign-in screen | F51: A reason should be visible ('Your session has expired. Please sign in again.'). The code stores the reason but the sign-in screen does not display it. | G51: P1 | H51: Verify gap | I51: lib/features/auth/presentation/screen/login_screen.dart:173 | K51: Pass | L51: Claude (adb) | M51: 46300 | N51: 1.0.0+1 debug | O51: emulator-5554 / Android 14 | P51: DEF-007 | Q51: FIXED AND RETESTED (5 Oct 2026, rebuilt debug build; DEF-007). The reason was already kept in the auth state; the sign-in screen now shows it. Emulator: the app's session was ended from the command line (DELETE /patient/auth/sessions/{id} from a second session, 204); on the next tab change the app went to sign-in with 'You were signed out because this session was ended - from another device, or after a password change. Sign in again to continue.' An expired session says 'Your session has expired. Sign in again to continue.'; a blocked account keeps its own message. The notice goes once the patient tries to sign in. Test added (sign_in_routing_test.dart). First observed: After the session was revoked remotely the user lands on the plain sign-in screen ('Hi, Welcome Back!') with no message at all — nothing says the session ended or why.
A52: BL-AUTH-051 | B52: Authentication & session | C52: Session & token refresh | D52: A network blip during refresh must not sign the user out | E52: 1. Let the access token expire 2. Cut the network (or return 429/500) exactly on the refresh call | F52: User should stay signed in and see an offline/retry message. The code treats any refresh failure as a lost session and wipes local data. | G52: P0 | H52: Verify gap | I52: lib/core/network/api_client.dart:605 | K52: Pass | L52: Claude (adb) | M52: 46300 | N52: 1.0.0+1 debug | O52: emulator-5554 / Android 14 | P52: DEF-045 | Q52: FIXED AND RETESTED (5 Oct 2026, rebuilt debug build). Calls watched through a pass-through recorder on the host (app pointed at http://10.0.2.2:8000, which forwards to the integration server). Before: cold start with the access token treated as expired and the refresh call answered 500 - one refresh attempt, then the app dropped to the sign-in screen and the stored session was wiped (DEF-045). After the fix (api_client.dart: only a refresh the server refuses ends the session): the same start with the refresh answered 500, with the connection cut, and answered 429 - each time one refresh attempt, the user stays signed in on Home with saved data, session file intact. While it keeps failing, Appointments shows 'Something went wrong - Too many attempts. Please wait a moment and try again.' with Try Again; once the refresh works, Try Again refreshes (200) and the list loads. A refresh the server refuses (401 AUTH_SESSION_REVOKED) still signs the user out, once. Unit tests added in test/core/network/dio_api_client_test.dart.
A53: BL-AUTH-052 | B53: Authentication & session | C53: Session & token refresh | D53: Credential errors never end the session | E53: While signed in, enter a wrong current password and a wrong phone-change code | F53: Field errors only; still signed in. | G53: P0 | H53: Rule | I53: lib/core/network/network_exceptions.dart:60 | K53: Pass | L53: Claude (adb) | M53: 46299 | N53: 1.0.0+1 debug | O53: emulator-5554 / Android 14 | Q53: A wrong current password (change password) and wrong phone-change codes produced field errors only; the session stayed signed in throughout.
A54: BL-AUTH-053 | B54: Authentication & session | C54: Session & token refresh | D54: Offline relaunch keeps the cached identity | E54: 1. Sign in 2. Relaunch in airplane mode | F54: Home shows the cached name; no error, no sign-out. | G54: P1 | H54: State | I54: lib/features/auth/application/providers/auth_provider.dart:119 | K54: Pass | L54: Claude (adb) | M54: 46299 | N54: 1.0.0+1 debug | O54: emulator-5554 / Android 14 | Q54: Cold start in airplane mode: Home opens with 'Welcome back, Sanjay!' and cached services; no error and no sign-out.
A55: BL-AUTH-054 | B55: Authentication & session | C55: Sign-in guard & routing | D55: Public vs protected screens | E55: Signed out, open Home, Help & Support, FAQ, a legal page, and My requests | F55: Help, FAQ and legal pages open; Home and My requests redirect to sign-in (or the intro on a fresh install). | G55: P0 | H55: Rule | I55: lib/app/router/app_router.dart:440 | K55: Pass | L55: Claude (adb) | M55: 46299 | N55: 1.0.0+1 debug | O55: emulator-5554 / Android 14 | Q55: Signed out: Help & Support, FAQs and Terms open; medibook://home, /appointments and /support/tickets redirect to sign-in.
A56: BL-AUTH-055 | B56: Authentication & session | C56: Sign-in guard & routing | D56: Signed-in users cannot reach sign-in screens | E56: Signed in, open the login, sign-up and forgot-password links | F56: Home is shown. | G56: P2 | H56: Rule | I56: lib/app/router/app_router.dart:473 | K56: Pass | L56: Claude (adb) | M56: 46299 | N56: 1.0.0+1 debug | O56: emulator-5554 / Android 14 | Q56: Signed in, medibook://login and medibook://signup both land on Home.
A57: BL-AUTH-056 | B57: Authentication & session | C57: Sign-in guard & routing | D57: Failed attempt does not bounce the screen | E57: Fail a sign-in and watch the screen | F57: Stays on sign-in with the typed values; no reload. | G57: P3 | H57: State | I57: lib/app/router/app_router.dart:495 | K57: Pass | L57: Claude (adb) | M57: 46299 | N57: 1.0.0+1 debug | O57: emulator-5554 / Android 14 | Q57: After a wrong password the user stays on the sign-in screen with the identifier and password still filled in; only the banner and attempts notice change.
A58: BL-AUTH-057 | B58: Authentication & session | C58: Logout | D58: Order: unregister push, end session, go to sign-in | E58: Log out with a proxy attached | F58: Device unregister (when one is registered) precedes the logout call. | G58: P2 | H58: Rule | I58: lib/features/profile/presentation/screen/profile_screen.dart:305 | J58: KB-04 | K58: Blocked | L58: Claude (adb) | M58: 46300 | N58: 1.0.0+1 debug | O58: emulator-5554 / Android 14 | Q58: KB-04: this build never registers the device for push (no /devices call in any recorded session), so there is no unregister call to order. Calls watched through a pass-through recorder on the host (app pointed at http://10.0.2.2:8000, which forwards to the integration server). Observed on Log Out: one call, POST /patient/auth/logout (204), then the sign-in screen. Re-run once a push provider is in the app.
A59: BL-AUTH-058 | B59: Authentication & session | C59: Logout | D59: Logout works offline | E59: 1. Log out in airplane mode 2. Relaunch | F59: Signed out locally; relaunch stays on sign-in. | G59: P0 | H59: Rule | I59: lib/features/auth/infrastructure/repositories/auth_repository_impl.dart:160 | K59: Pass | L59: Claude (adb) | M59: 46299 | N59: 1.0.0+1 debug | O59: emulator-5554 / Android 14 | Q59: Logged out in airplane mode: confirm dialog 'Log out of Medibook? …', then the sign-in screen; Back leaves the app rather than returning to signed-in screens; relaunch stays on sign-in. Note: the server-side session ('Medibook/1.0') remained listed afterwards because the logout call could not be sent — the local tokens are gone, but the session lives until it expires.
A60: BL-AUTH-059 | B60: Authentication & session | C60: Logout | D60: What is cleared and what is kept | E60: 1. Log out 2. Sign in as a different user 3. Compare the device fingerprint header before and after | F60: No data from the previous user; onboarding not repeated; device fingerprint unchanged. | G60: P0 | H60: State | I60: lib/core/storage/secure_store.dart:46 | K60: Pass | L60: Claude (adb) | M60: 46299 | N60: 1.0.0+1 debug | O60: emulator-5554 / Android 14 | Q60: After logout: every cache box and the auth box are 0 bytes, secure storage holds only the device fingerprint (same value as before logout), and the settings box (onboarding flag) is kept. Signing in as another user afterwards shows none of the previous user's data.
A61: BL-AUTH-060 | B61: Authentication & session | C61: Device identity | D61: Fingerprint is sent only on code-based calls and matches between start and verify | E61: Inspect headers on sign-up, code sign-in, resend and forgot-password calls, and on password sign-in | F61: X-Device-Fingerprint present and identical on the code calls; absent on password sign-in and token refresh. | G61: P1 | H61: Rule | I61: lib/features/auth/infrastructure/data_sources/remote/auth_api.dart:113 | K61: Pass | L61: Claude (adb) | M61: 46300 | N61: 1.0.0+1 debug | O61: emulator-5554 / Android 14 | Q61: Calls watched through a pass-through recorder on the host (app pointed at http://10.0.2.2:8000, which forwards to the integration server). X-Device-Fingerprint was present with the same value (hash d747e6) on: code sign-in start, otp/resend, password/forgot/start, signup/start and signup/verify (wrong code 0000 -> 401 AUTH_OTP_INVALID, '2 attempts left'). It was absent on password sign-in and on every token refresh. Not exercised: the verify calls for code sign-in and forgot password, to avoid failed attempts on a seeded account (and KB-05 for a correct code).
A62: BL-AUTH-061 | B62: Authentication & session | C62: App update | D62: Below the minimum version forces an update | E62: 1. Set the backend minimum Android version above the installed Play build 2. Launch 3. Back out of the Play update screen | F62: Play's full-screen update, then a blocking 'Update required' screen with 'Update now'. | G62: P0 | H62: Rule | I62: lib/features/app_update/domain/policies/app_update_policy.dart:16 | K62: Blocked | L62: Claude (adb) | M62: 46299 | N62: 1.0.0+1 debug | O62: emulator-5554 / Android 14 | Q62: Needs a Google Play-distributed build and a changed minimum version in backend app-config (currently min 1.0.0 = installed 1.0.0); the emulator build is a sideloaded debug build.
A63: BL-AUTH-062 | B63: Authentication & session | C63: App update | D63: Version comparison is numeric | E63: Minimum 1.10.0 with 1.9.3 installed; minimum 1.9.3 with 1.9.3+7 installed | F63: 1.9.3 is forced to update; 1.9.3+7 is not. | G63: P1 | H63: Calculation | I63: lib/features/app_update/domain/policies/app_update_policy.dart:31 | K63: Blocked | L63: Claude (adb) | M63: 46299 | N63: 1.0.0+1 debug | O63: emulator-5554 / Android 14 | Q63: Needs a Google Play-distributed build and a changed minimum version in backend app-config (currently min 1.0.0 = installed 1.0.0); the emulator build is a sideloaded debug build.
A64: BL-AUTH-063 | B64: Authentication & session | C64: App update | D64: Optional update downloads in the background | E64: 1. Publish a newer build that is above the minimum 2. Let it download 3. Tap Later 4. Resume the app | F64: 'Update ready' dialog with Restart / Later; after Later it does not reappear until the next launch. | G64: P2 | H64: State | I64: lib/features/app_update/application/providers/app_update_provider.dart:83 | K64: Blocked | L64: Claude (adb) | M64: 46299 | N64: 1.0.0+1 debug | O64: emulator-5554 / Android 14 | Q64: Needs a Google Play-distributed build and a changed minimum version in backend app-config (currently min 1.0.0 = installed 1.0.0); the emulator build is a sideloaded debug build.
A65: BL-AUTH-064 | B65: Authentication & session | C65: App update | D65: Minimum version on iOS and non-Play installs | E65: Run a below-minimum build on iOS and on a sideloaded Android build | F65: Old versions should be blocked. The code enforces the minimum only on Android installs from Google Play. | G65: P1 | H65: Verify gap | I65: lib/features/app_update/infrastructure/repositories/app_update_repository_impl.dart:18 | K65: Blocked | L65: Claude (adb) | M65: 46299 | N65: 1.0.0+1 debug | O65: emulator-5554 / Android 14 | Q65: Needs a Google Play-distributed build and a changed minimum version in backend app-config (currently min 1.0.0 = installed 1.0.0); the emulator build is a sideloaded debug build.
A66: BL-AUTH-065 | B66: Authentication & session | C66: App update | D66: Demo build cannot be used to test lockout | E66: On a demo build enter wrong passwords repeatedly | F66: Always '4 attempts left', never locked — run lockout checks only on a build pointed at the real backend. | G66: P3 | H66: Rule | I66: lib/features/auth/infrastructure/data_sources/remote/demo_auth_api.dart:27 | K66: Pass | L66: Claude (adb) | M66: 46300 | N66: 1.0.0+1 debug | O66: emulator-5554 / Android 14 | Q66: PASS (5 Oct 2026, demo build: flutter run --dart-define=MEDIBOOK_DEMO=true, app data wiped). Sign-in prefilled ('Demo login is prefilled — just tap Log In.'); with a wrong password, Log In tapped 6 times: every time 'That email and password do not match an account.' and '4 attempts left before sign-in is paused for 1 hour.' — never locked. So lockout checks must run on the normal build, as the rule says. Emulator put back on the normal build afterwards. Earlier note: The installed build is not a demo build (no prefilled credentials; real server answers with attempts counting down).
A67: BL-BOOK-001 | B67: Booking | C67: Discovery | D67: Browsing hospitals and doctors needs a signed-in session | E67: Signed out, open links to the hospitals list, a doctor and the booking flow | F67: Redirected to sign-in (or the intro on a fresh install). Confirm intended — the API allows these lists without sign-in. | G67: P2 | H67: Rule | I67: lib/app/router/app_router.dart:395 | K67: Pass | L67: Claude (adb) | M67: 46300 | N67: 1.0.0+1 debug | O67: emulator-5554 / Android 14 | Q67: OWNER DECISION (5 Oct 2026): intended - keep hospitals, doctors, search, booking, availability and the ambulance screen behind sign-in in the app, even though the API serves them without a token. No code change. Re-checked signed out on the 5 Oct build: medibook://hospitals, medibook://booking, medibook://ambulance, medibook://search and medibook://doctor/<id> all land on the sign-in screen. First observed 4 Oct 2026: medibook://hospitals and medibook://booking redirect to sign-in although the API serves these lists publicly; medibook://ambulance (emergency numbers) also requires sign-in.
A68: BL-BOOK-002 | B68: Booking | C68: Discovery | D68: Hospital list sorting | E68: 1. Open Hospitals 2. Use each sort option | F68: 'Name A–Z' (default), 'Highest rated', 'Soonest slot'; no distance option; list reloads each time. | G68: P2 | H68: Rule | I68: lib/features/booking/presentation/screen/hospitals_screen.dart:78 | J68: KB-10 | K68: Pass | L68: Claude (adb) | M68: 46299 | N68: 1.0.0+1 debug | O68: emulator-5554 / Android 14 | Q68: Sort menu offers 'Name A–Z' (default), 'Highest rated', 'Soonest slot' — no distance option; 'Highest rated' puts Sahyadri (4.5) above Lakeshore (3.9).
A69: BL-BOOK-003 | B69: Booking | C69: Discovery | D69: Hospital search and department tab combine | E69: 1. Type a name quickly 2. Pick a department tab 3. Search something with no match | F69: One request per typing pause; 'No hospital matches these filters' with 'Clear filters' clearing both. | G69: P2 | H69: Rule | I69: lib/features/booking/presentation/screen/hospitals_screen.dart:94 | K69: Pass | L69: Claude (adb) | M69: 46299 | N69: 1.0.0+1 debug | O69: emulator-5554 / Android 14 | Q69: 'sahy' shows only Sahyadri City Hospital; adding the Cardiology tab gives '0 hospitals — No hospital matches these filters' with 'Clear filters', which clears both the text and the tab (back to 2 hospitals).
A70: BL-BOOK-004 | B70: Booking | C70: Discovery | D70: Hospital card availability line | E70: Compare a hospital with online booking off, one with no published slot and one with a slot today | F70: 'Online booking not available' / 'No free slot published' / 'Next free <time> today'. | G70: P1 | H70: Data mapping | I70: lib/features/booking/presentation/components/hospital_card.dart:98 | K70: Blocked | L70: Claude (adb) | M70: 46299 | N70: 1.0.0+1 debug | O70: emulator-5554 / Android 14 | Q70: Seed data: the server lists only 2 hospitals (both online-bookable, India time) and 10 doctors (all active and bookable), so this state cannot be produced. Observed for the normal case: cards show 'Next free 9:00 AM tomorrow'.
A71: BL-BOOK-005 | B71: Booking | C71: Discovery | D71: 'Next free' time uses the hospital's zone | E71: 1. Use a hospital outside India time (e.g. Dubai) 2. Read the card | F71: Time should be the hospital's local time. The list card always renders India time. | G71: P3 | H71: Verify gap | I71: lib/features/booking/domain/hospital_clock.dart:25 | J71: BB-09 (docs/BACKEND_BLOCKERS.md) | K71: Blocked | L71: Claude (adb) | M71: 46299 | N71: 1.0.0+1 debug | O71: emulator-5554 / Android 14 | Q71: Seed data: the server lists only 2 hospitals (both online-bookable, India time) and 10 doctors (all active and bookable), so this state cannot be produced. Observed for the normal case: cards show 'Next free 9:00 AM tomorrow'.
A72: BL-BOOK-006 | B72: Booking | C72: Discovery | D72: More than one page of hospitals or doctors | E72: Use a location with 51+ hospitals, or a hospital department with 51+ doctors | F72: All should be reachable. The code loads a single page of 50 with no 'load more'. | G72: P2 | H72: Verify gap | I72: lib/features/booking/presentation/screen/booking_screen.dart:604 | J72: BB-10 (docs/BACKEND_BLOCKERS.md) | K72: Blocked | L72: Claude (adb) | M72: 46299 | N72: 1.0.0+1 debug | O72: emulator-5554 / Android 14 | Q72: Seed data: the server lists only 2 hospitals (both online-bookable, India time) and 10 doctors (all active and bookable), so this state cannot be produced. Observed for the normal case: cards show 'Next free 9:00 AM tomorrow'.
A73: BL-BOOK-007 | B73: Booking | C73: Discovery | D73: A doctor can be booked only when active and bookable online | E73: Open a doctor on leave and one marked not bookable online | F73: 'On leave — not taking bookings right now.' / 'Not bookable online. Call the hospital to book.'; no Book button; Doctor Details footer 'Not bookable online'. | G73: P0 | H73: Rule | I73: lib/features/booking/presentation/components/booking_doctor_card.dart:160 | J73: BB-08 (docs/BACKEND_BLOCKERS.md) | K73: Blocked | L73: Claude (adb) | M73: 46299 | N73: 1.0.0+1 debug | O73: emulator-5554 / Android 14 | Q73: Seed data: the server lists only 2 hospitals (both online-bookable, India time) and 10 doctors (all active and bookable), so this state cannot be produced. Observed for the normal case: cards show 'Next free 9:00 AM tomorrow'.
A74: BL-BOOK-008 | B74: Booking | C74: Discovery | D74: Department list depends on where the flow started | E74: Start a booking from Home and from a hospital page | F74: Home: all departments with 'N hospitals'; hospital: only that hospital's departments. | G74: P2 | H74: Rule | I74: lib/features/booking/presentation/screen/booking_screen.dart:455 | K74: Pass | L74: Claude (adb) | M74: 46299 | N74: 1.0.0+1 debug | O74: emulator-5554 / Android 14 | Q74: Started from Home/deep link: step 1 lists '7 departments' with hospital counts ('Cardiology, 1 hospital'). Once a hospital is in the draft, step 1 lists that hospital's '4 departments'.
A75: BL-BOOK-009 | B75: Booking | C75: Step gating | D75: Each step needs its choice before Continue | E75: Try Continue on step 1 without a department, step 2 without a doctor, step 3 without a slot or patient, step 4 before the fee loads | F75: Button disabled at each point. | G75: P0 | H75: Rule | I75: lib/features/booking/presentation/screen/booking_screen.dart:346 | K75: Pass | L75: Claude (adb) | M75: 46299 | N75: 1.0.0+1 debug | O75: emulator-5554 / Android 14 | Q75: Continue is disabled on step 1 with no department, on step 2 with no doctor, and on step 3 with no time; step 4 with nothing chosen shows 'Nothing to confirm yet'.
A76: BL-BOOK-010 | B76: Booking | C76: Step gating | D76: Continue on step 2 opens the time picker when no time is chosen | E76: 1. Select a doctor without a time 2. Tap Continue 3. Confirm a time | F76: 'Select Time' sheet opens; after confirming, the flow is on step 3. | G76: P1 | H76: State | I76: lib/features/booking/presentation/screen/booking_screen.dart:243 | K76: Pass | L76: Claude (adb) | M76: 46299 | N76: 1.0.0+1 debug | O76: emulator-5554 / Android 14 | Q76: On step 2 with the doctor still selected and no time, Continue opened the 'Select Time' sheet; confirming a time moved to step 3.
A77: BL-BOOK-011 | B77: Booking | C77: Step gating | D77: Changing the department clears doctor and time | E77: 1. Choose a slot 2. Go back to step 1 and pick another department | F77: No doctor selected on step 2; patient, coupon and notes are kept. | G77: P0 | H77: State | I77: lib/features/booking/application/providers/booking_draft_provider.dart:67 | K77: Pass | L77: Claude (adb) | M77: 46299 | N77: 1.0.0+1 debug | O77: emulator-5554 / Android 14 | Q77: With a slot chosen for Dr. Meera Varghese (General Medicine), going back and picking Cardiology shows Cardiology's doctors with none selected and Continue disabled.
A78: BL-BOOK-012 | B78: Booking | C78: Step gating | D78: Changing the hospital clears doctor and time | E78: 1. Choose a slot 2. Tap 'Change' next to the hospital | F78: Step 2 returns to 'Choose a hospital'; the earlier slot is gone. | G78: P0 | H78: State | I78: lib/features/booking/application/providers/booking_draft_provider.dart:39 | K78: Pass | L78: Claude (adb) | M78: 46299 | N78: 1.0.0+1 debug | O78: emulator-5554 / Android 14 | Q78: Tapping 'Change' on the hospital strip returns to 'Choose a hospital' ('Hospitals with a Cardiology department.'); the earlier doctor and time are gone and Continue is disabled until a doctor is picked again.
A79: BL-BOOK-013 | B79: Booking | C79: Step gating | D79: Changing the doctor clears the time and adopts the doctor's hospital and department | E79: 1. Choose a slot with doctor A 2. Select doctor B | F79: Doctor B selected, no slot; summary shows B's hospital and department. | G79: P0 | H79: State | I79: lib/features/booking/application/providers/booking_draft_provider.dart:82 | K79: Pass | L79: Claude (adb) | M79: 46299 | N79: 1.0.0+1 debug | O79: emulator-5554 / Android 14 | Q79: With a time chosen for Dr. Meera Varghese: opening Dr. Suresh Pillai's time sheet and closing it keeps Dr. Varghese and her time; confirming a time for Dr. Pillai replaces both (step 3 shows 'Tomorrow · 5 Oct 2026 · 9:00 AM · Morning OPD · Dr. Suresh Pillai').
A80: BL-BOOK-014 | B80: Booking | C80: Step gating | D80: Stepper allows going back only | E80: On step 3 tap 'Department', then try a later step label | F80: Jumps back to step 1; later labels do nothing. | G80: P2 | H80: Rule | I80: lib/features/booking/presentation/components/booking_stepper.dart:50 | K80: Pass | L80: Claude (adb) | M80: 46299 | N80: 1.0.0+1 debug | O80: emulator-5554 / Android 14 | Q80: On step 3, tapping the later 'Payment' label does nothing; tapping 'Back to Department' jumps to step 1.
A81: BL-BOOK-015 | B81: Booking | C81: Step gating | D81: Deep link step is clamped and incomplete steps show guidance | E81: Open /booking?step=9, /booking?step=abc and /booking?step=4 with nothing chosen | F81: Step 4 / step 1 / 'Nothing to confirm yet — Pick a doctor, a time and who the visit is for first.' with a button back to step 3. | G81: P2 | H81: Boundary | I81: lib/features/booking/application/providers/booking_draft_provider.dart:20 | K81: Pass | L81: Claude (adb) | M81: 46299 | N81: 1.0.0+1 debug | O81: emulator-5554 / Android 14 | Q81: medibook://booking?step=9 opens step 4 with 'Nothing to confirm yet — Pick a doctor, a time and who the visit is for first.' and 'Back to time and patient'; step=abc opens step 1 ('7 departments').
A82: BL-BOOK-016 | B82: Booking | C82: Step gating | D82: Leaving the flow | E82: 1. Tap X on step 1 2. Tap X on step 3 3. Tap X after tapping Pay | F82: Step 1 leaves at once; later: 'Leave this booking? … Nothing has been booked or charged.'; after Pay: 'Leave without paying? Booking <ref> is held for you…'. | G82: P1 | H82: State | I82: lib/features/booking/presentation/screen/booking_screen.dart:185 | K82: Pass | L82: Claude (adb) | M82: 46299 | N82: 1.0.0+1 debug | O82: emulator-5554 / Android 14 | Q82: X on step 3: 'Leave this booking? Your choices so far will not be saved. Nothing has been booked or charged.' (Keep booking / Leave). After a booking exists the step-4 button reads 'Complete payment'. Step-1 immediate leave and the 'Leave without paying?' wording were not separately captured.
A83: BL-BOOK-017 | B83: Booking | C83: Date & availability | D83: Date strip shows exactly the days the server publishes | E83: 1. Open the time picker for a doctor 2. Compare with the availability API | F83: One chip per returned day; 'This doctor has no sessions in the booking window.' when none. | G83: P1 | H83: Rule | I83: lib/features/booking/application/providers/availability_providers.dart:13 | K83: Pass | L83: Claude (adb) | M83: 46299 | N83: 1.0.0+1 debug | O83: emulator-5554 / Android 14 | Q83: Date strip for Dr. Meera Varghese matches GET availability day for day (4 Oct, 8 Oct, 11 Oct 'not available'; others bookable).
A84: BL-BOOK-018 | B84: Booking | C84: Date & availability | D84: First bookable day is preselected | E84: Open the picker for a doctor whose first two days are full | F84: The first day with a free session is selected. | G84: P2 | H84: Rule | I84: lib/features/booking/presentation/components/slot_sheet.dart:182 | K84: Pass | L84: Claude (adb) | M84: 46299 | N84: 1.0.0+1 debug | O84: emulator-5554 / Android 14 | Q84: Today (4 Oct) has no session; the picker opened with Mon 5 selected.
A85: BL-BOOK-019 | B85: Booking | C85: Date & availability | D85: Day states | E85: 1. Tap a day with no sessions 2. Tap a fully booked day | F85: First cannot be tapped; second is struck through and says 'Every slot on this day is taken. Pick another day.' | G85: P1 | H85: State | I85: lib/features/booking/presentation/components/date_strip.dart:51 | K85: Pass | L85: Claude (adb) | M85: 46299 | N85: 1.0.0+1 debug | O85: emulator-5554 / Android 14 | Q85: Tapping 'Sun 11, not available' does nothing (selection unchanged). A fully-booked day does not exist in the seed data, so the 'Every slot on this day is taken' text was not seen.
... A89: BL-BOOK-023 | B89: Booking | C89: Slot selection | D89: Changing the day resets the chosen time | E89: 1. Pick 10:00 on Monday 2. Tap Tuesday | F89: Selection moves to Tuesday's first free slot. | G89: P1 | H89: State | I89: lib/features/booking/presentation/components/slot_sheet.dart:202 | K89: Pass | L89: Claude (adb) | M89: 46299 | N89: 1.0.0+1 debug | O89: emulator-5554 / Android 14 | Q89: Chose 9:40 AM on Mon 5, tapped Tue 13: selection moved to Tue 13 9:00 AM ('Continue with 9:00 AM').
A90: BL-BOOK-024 | B90: Booking | C90: Slot selection | D90: Slots in a paused session | E90: 1. Have the desk pause a session that still has free slots 2. Open the picker | F90: Decide what is correct: the heading shows '· paused' but its free slots remain selectable. | G90: P2 | H90: Verify gap | I90: lib/features/booking/presentation/components/slot_grid.dart:101 | J90: KB-08 | K90: Blocked | L90: Claude (adb) | M90: 46299 | N90: 1.0.0+1 debug | O90: emulator-5554 / Android 14 | Q90: KB-08: no desk user to pause a session.
A91: BL-BOOK-025 | B91: Booking | C91: Slot selection | D91: Previously chosen slot that was taken meanwhile | E91: 1. Choose a slot 2. Have another user book it 3. On step 3 tap 'Change' | F91: The taken slot must not be confirmable. The code keeps it preselected with 'Continue with <time>' enabled, so booking fails later. | G91: P1 | H91: Verify gap | I91: lib/features/booking/presentation/components/slot_sheet.dart:276 | K91: Pass | L91: Claude (adb) | M91: 46300 | N91: 1.0.0+1 debug | O91: emulator-5554 / Android 14 | P91: DEF-073 | Q91: PASS (5 Oct 2026, debug build). FIXED (DEF-073): the slot sheet kept the earlier pick whenever it still existed that day, even if taken; now it keeps it only while it is free, otherwise moves to the first free slot with a toast ('The <time> slot has just been taken. Pick another.'), or turns Continue off when nothing is free. Retest: Dr. Meera Varghese, Wed 7 Oct 9:30 AM chosen, reached step 3; Asha Rao booked the same slot via the API (slot now 'held'); 'Change the slot' showed '9:30 AM, taken' and 'Continue with 9:00 AM'. Asha's test hold lapses on its own. Tests: test/features/booking/slot_sheet_taken_test.dart.
A92: BL-BOOK-026 | B92: Booking | C92: Slot selection | D92: Booking from Doctor Details carries the slot | E92: 1. Open a doctor from Search 2. Pick a time 3. Tap 'Book <time>' 4. Repeat after another user takes that slot | F92: Step 3 shows the chosen time; if it was taken, step 3 asks to pick a time again. | G92: P1 | H92: State | I92: lib/features/booking/presentation/screen/booking_screen.dart:137 | K92: Pass | L92: Claude (adb) | M92: 46300 | N92: 1.0.0+1 debug | O92: emulator-5554 / Android 14 | P92: DEF-008 | Q92: FIXED AND RETESTED (5 Oct 2026, rebuilt debug build; DEF-008). Cause: when the doctor's details were already loaded, the booking screen applied the doctor and slot from the link first, and its own set-up ('configure', which replaces the whole draft) ran just after and wiped them. The screen now applies them only after set-up (booking_screen.dart). Emulator: Search > Dr. Meera Varghese > 9:40 AM > 'Book 9:40 AM tomorrow' -> the flow opens on step 3 (Patient) with 'Tomorrow - 6 Oct 2026 - 9:40 AM - Morning OPD - Dr. Meera Varghese'. First observed: From a clean start: Search -> Dr. Meera Varghese -> picked 9:40 AM -> footer 'Book 9:40 AM tomorrow' -> tapped. The booking opens on step 3 with 'Pick a doctor and a time first.' / 'Choose a doctor' — the chosen time (and the doctor) is not carried over, and step 2 shows the hospital as 'This hospital' with no doctor selected. Reproduced twice (the slot was still free). Doctor Details footer states work: 'Pick a time to continue' disabled until a time is tapped.
A93: BL-BOOK-027 | B93: Booking | C93: Slot selection | D93: The slot is not held until Pay | E93: 1. Reach step 4 on device A 2. Book the same slot on device B 3. Tap Pay on A | F93: Step 4 note explains the hold starts at Pay; device A is told the slot was taken. | G93: P0 | H93: Rule | I93: lib/features/booking/presentation/screen/booking_screen.dart:1008 | K93: Pass | L93: Claude (adb) | M93: 46299 | N93: 1.0.0+1 debug | O93: emulator-5554 / Android 14 | Q93: The slot was not held while on step 4: another account booked it and Pay was refused. Step 4 note reads 'Your booking reference and token are issued when you tap Pay. The slot is then held for a few minutes while you pay…'.
A94: BL-BOOK-028 | B94: Booking | C94: Patient selection | D94: Default patient | E94: Open step 3 on an account with self + family, and one with only two family members | F94: Self preselected / nobody preselected and Continue disabled. | G94: P1 | H94: Rule | I94: lib/features/booking/presentation/screen/booking_screen.dart:793 | K94: Pass | L94: Claude (adb) | M94: 46299 | N94: 1.0.0+1 debug | O94: emulator-5554 / Android 14 | Q94: Step 3 on Sanjay's account (self + spouse + child): 'Sanjay Varma, You' is preselected. Account with only family members not available.
A95: BL-BOOK-029 | B95: Booking | C95: Patient selection | D95: Account with no patient record | E95: Use an account with no persons | F95: 'Your account has no patient record yet, so we cannot book "for myself"…' with 'Add a family member'. | G95: P2 | H95: Error handling | I95: lib/features/booking/presentation/screen/booking_screen.dart:841 | J95: BB-13 (docs/BACKEND_BLOCKERS.md) | K95: Blocked | L95: Claude (adb) | M95: 46299 | N95: 1.0.0+1 debug | O95: emulator-5554 / Android 14 | Q95: Seed data: no account without a patient record.
A96: BL-BOOK-030 | B96: Booking | C96: Patient selection | D96: Notes are optional and limited | E96: 1. Enter only spaces 2. Paste 2001 characters | F96: Spaces-only notes are not sent; input stops at 2000. | G96: P3 | H96: Boundary | I96: lib/features/booking/application/providers/booking_draft_provider.dart:125 | K96: Pass | L96: Claude (adb) | M96: 46300 | N96: 1.0.0+1 debug | O96: emulator-5554 / Android 14 | P96: DEF-046 | Q96: FIXED AND RETESTED (5 Oct 2026, rebuilt debug build). The earlier 'tooling limit' was an app defect (DEF-046). Before: typing 'chest pain' into Notes for the doctor in one go left only 'c' - the box was rebuilt after the first character and lost the keyboard; typing on after re-tapping, 'chest' + space + 'pain' became 'chestpain' because the space was removed as soon as it was typed. The booking doctor search did the same ('harish' left 'h'), and the department search is built the same way. After the fix (new booking component draft_text.dart, used by the notes box and both search boxes): 'chest pain since Monday' typed in one go is kept as typed; the department search takes 'cardio' and the doctor search 'harish menon' in one go and filter the list. Limit: with 2000 characters in the box, 3 more were not accepted (still 2000). Spaces only: the box accepts them, Continue goes to step 4, and no booking was made on the shared account; that spaces-only notes are stored as none and patient_notes is left out of the request is covered by new tests (booking_draft_test.dart, booking_api_body_test.dart, draft_text_test.dart).
A97: BL-BOOK-031 | B97: Booking | C97: Fee quote | D97: Quote is re-requested when the patient or coupon changes | E97: 1. Reach step 4 2. Change the patient 3. Return to step 4 | F97: A fresh breakdown loads (follow-up pricing is per patient). | G97: P0 | H97: Rule | I97: lib/features/booking/application/providers/booking_providers.dart:52 | K97: Pass | L97: Claude (adb) | M97: 46299 | N97: 1.0.0+1 debug | O97: emulator-5554 / Android 14 | Q97: Changing the patient to Tara and returning to step 4 reloaded the summary and fee for Tara (₹424; no follow-up pricing in seed data).
A98: BL-BOOK-032 | B98: Booking | C98: Fee quote | D98: Breakdown is the server's, line by line | E98: Compare every row, tax note and 'Total Payable' with the fee-quote response | F98: Identical; e.g. 'GST 18% · ₹5 added' (or 'included'); a Taxes row only when tax is above zero. | G98: P0 | H98: Calculation | I98: lib/features/booking/presentation/components/fee_breakdown_card.dart:27 | K98: Pass | L98: Claude (adb) | M98: 46299 | N98: 1.0.0+1 debug | O98: emulator-5554 / Android 14 | Q98: Step 4 shows Consultation ₹400, Convenience fee ₹20, Taxes ₹4, Total payable ₹424 — identical to GET fee-quotes (40000 + 2000 + 400 = 42400 paise). Pay button reads 'Pay ₹424'.
A99: BL-BOOK-033 | B99: Booking | C99: Fee quote | D99: Follow-up visit | E99: Book the same doctor again for a follow-up-eligible patient | F99: 'Visit: Follow-up (reduced fee)' and the reduced total. | G99: P1 | H99: Rule | I99: lib/features/booking/presentation/screen/booking_screen.dart:959 | J99: BB-11 (docs/BACKEND_BLOCKERS.md) | K99: Blocked | L99: Claude (adb) | M99: 46299 | N99: 1.0.0+1 debug | O99: emulator-5554 / Android 14 | Q99: Seed data: fee quotes return is_follow_up=false for the combinations tried; no follow-up pricing configured.
A100: BL-BOOK-034 | B100: Booking | C100: Fee quote | D100: Pay stays disabled without a quote | E100: Cut the network on step 4 | F100: Inline error with Retry; 'Pay ₹…' disabled. | G100: P1 | H100: Error handling | I100: lib/features/booking/presentation/screen/booking_screen.dart:400 | K100: Pass | L100: Claude (adb) | M100: 46300 | N100: 1.0.0+1 debug | O100: emulator-5554 / Android 14 | P100: DEF-009 | Q100: FIXED AND RETESTED (5 Oct 2026, rebuilt debug build; DEF-009). Cause: the step-4 footer read the fee quote with AsyncValue.value, which re-throws a failed quote and crashed the whole app; it now uses valueOrNull (booking_screen.dart). No other such read in the app. Emulator: Dr. Meera Varghese, 9:40 AM, Sanjay, airplane mode, Continue -> 'Confirm appointment' with 'You appear to be offline. Check your connection and try again.' and Try Again; Pay shows as unavailable. Back online, Try Again loaded the quote (GET /patient/fee-quotes 200 seen through the recorder) and Pay became available. First observed: On booking step 3 with a doctor, time and patient chosen, the device was put in airplane mode and Continue tapped: instead of an inline error with Retry, the ENTIRE app is replaced by a red Flutter error screen reading 'NetworkFailure(network): The connection errored … DioException [connection error] … SocketException: Connection failed (OS Error: Network is unreachable, errno = 101), address = 62.171.151.149, port = 8443 — See also: https://docs.flutter.dev/testing/errors'. Reproduced twice. System Back then exits the app. (In a release build this would be a blank grey screen.) Screenshot: docs/emulator-run-redscreen-booking-offline.png.
A101: BL-BOOK-035 | B101: Booking | C101: Fee quote | D101: Amount charged vs amount quoted | E101: 1. Book a slot on a date priced differently from today (if the hospital has date-based pricing) 2. Compare step 4 total with the payment screen total | F101: Confirm intended: the payment screen charges the booking's own fee snapshot, which can differ from the step-4 quote. | G101: P1 | H101: Verify gap | I101: lib/features/payment/presentation/screen/payment_screen.dart:300 | J101: BB-11 (docs/BACKEND_BLOCKERS.md) | K101: Pass | L101: Claude (adb) | M101: 46300 | N101: 1.0.0+1 debug | O101: emulator-5554 / Android 14 | P101: DEF-047 | Q101: OWNER DECISION (5 Oct 2026): not acceptable - the app must make a changed price clear before the patient pays (DEF-047). FIXED AND RETESTED (5 Oct 2026, rebuilt debug build). The payment screen now compares the total shown at confirmation with the booking's own total. When they differ it shows a warning above the order summary and, on Pay, asks 'The price has changed' with 'Not now' / 'Pay <amount>' before any payment starts. Retest: no date-based pricing exists on the server (docs/BACKEND_BLOCKERS.md BB-11), so the quote was lowered by Rs 100 in a pass-through recorder on the host. Step 4 showed 'Total payable Rs 824' and 'Pay Rs 824'; the booking (LKSB-2610-00194, left unpaid to expire) cost Rs 924. The payment screen showed: 'The price has changed. You were shown Rs 824 when you confirmed. The hospital's price for this appointment is Rs 924. Nothing has been charged yet.' and the button 'Pay Rs 924'. Tapping Pay opened the confirmation; 'Not now' made no call and stayed on the screen; tapping Pay again asked again; 'Pay Rs 924' went on to the payment (which fails on this server, KB-02). Unit tests added (price_change_test.dart, booking_submit_test.dart). Still to do when BB-11 is delivered: repeat with a real date-priced slot. Earlier (4 Oct): quote and charged amount were equal (Rs 424, Rs 824, Rs 524); payment screen notes 'Priced for <date> by the hospital.'
A102: BL-BOOK-036 | B102: Booking | C102: Coupon | D102: Code input rules | E102: Type ' welcome-10 ' | F102: Only letters and digits accepted (max 64); sent as 'WELCOME10'. | G102: P2 | H102: Boundary | I102: lib/features/booking/presentation/components/coupon_field.dart:128 | K102: Pass | L102: Claude (adb) | M102: 46299 | N102: 1.0.0+1 debug | O102: emulator-5554 / Android 14 | Q102: Typing ' welcome-10 ' leaves 'welcome10' in the field: spaces and the hyphen are rejected.
A103: BL-BOOK-037 | B103: Booking | C103: Coupon | D103: Valid coupon | E103: 1. Apply a valid code 2. Remove it | F103: '<CODE> applied', '₹X off', a green '− ₹X' row and reduced total; Remove restores the price. | G103: P0 | H103: Calculation | I103: lib/features/booking/presentation/components/coupon_field.dart:173 | J103: BB-07 (docs/BACKEND_BLOCKERS.md) | K103: Blocked | L103: Claude (adb) | M103: 46299 | N103: 1.0.0+1 debug | O103: emulator-5554 / Android 14 | Q103: Seed data: no valid coupon code is known for this server (13 guesses via the fee-quote API all returned COUPON_INVALID).
...

Sheet Checklist
A1: ID | B1: Module | C1: Screen / Area | D1: Test case | E1: Steps | F1: Expected result | G1: Priority | H1: Type | I1: Platform | J1: Needs / Blocker | K1: Status | L1: Tester | M1: Date tested | N1: Build | O1: Device / OS | P1: Defect ID | Q1: Notes / Actual result
A2: ENV-001 | B2: 00 Test environment & prerequisites | C2: Backend | D2: API reachable over HTTPS with a CA-signed certificate | E2: 1. Run curl against <host>/api/v1/shared/health without -k 2. Open the same URL in a device browser | F2: 200 response, no certificate warning. A self-signed certificate is not acceptable for a production run. | G2: P0 | H2: Release | I2: Both | J2: KB-03 | K2: Blocked | L2: Claude (adb) | M2: 46300 | N2: 1.0.0+1 debug | O2: emulator-5554 / Android 14 | Q2: 5 Oct 2026: curl without -k to https://62.171.151.149:8443/api/v1/shared/health fails (HTTP 000): the certificate is self-signed (subject and issuer 'CN=localhost', valid to 1 Jan 2029). Backend blocker BB-23 (KB-03): a CA-signed certificate on a real host name.
A3: ENV-002 | B3: 00 Test environment & prerequisites | C3: Build | D3: Build under test is a release build with production defines | E3: 1. Build with --release and MEDIBOOK_ENV=prod, MEDIBOOK_API_BASE_URL=<prod host>, MEDIBOOK_DEMO=false, MEDIBOOK_ALLOW_BAD_CERT=false 2. Install on a device 3. Record the build number in the Read Me sheet | F3: App starts and talks to the production/pre-prod host. No debug banner. The integration-server IP is not used. | G3: P0 | H3: Release | I3: Both | J3: KB-07 | K3: Blocked | L3: Claude (adb) | M3: 46300 | N3: 1.0.0+1 debug | O3: emulator-5554 / Android 14 | Q3: 5 Oct 2026: No production or pre-production host has been provided, so a --release build with MEDIBOOK_ENV=prod and MEDIBOOK_API_BASE_URL=<prod host> cannot be pointed anywhere. App side is ready: in a prod build the config check refuses demo mode and certificate bypass (see INS-007). Backend blocker BB-24 (KB-07).
A4: ENV-003 | B4: 00 Test environment & prerequisites | C4: Payments | D4: Razorpay keys are configured on the backend | E4: 1. Create a booking 2. Inspect the payment_order in the response (proxy) | F4: payment_order.key_id is a real rzp_test_/rzp_live_ key and gateway_order_id is a real Razorpay order (not order_fake...). | G4: P0 | H4: Release | I4: Both | J4: KB-02 | K4: Blocked | L4: Claude (adb) | M4: 46300 | N4: 1.0.0+1 debug | O4: emulator-5554 / Android 14 | Q4: 5 Oct 2026: A booking's payment_order has key_id '' and gateway_order_id 'order_fake9b2dc0c9fa7447'. Razorpay is still the in-process fake. Backend blocker BB-16 (KB-02).
A5: ENV-004 | B5: 00 Test environment & prerequisites | C5: Storage | D5: File storage host resolves and accepts uploads | E5: 1. POST /shared/files/uploads 2. PUT a file to the returned upload_url | F5: upload_url points at a resolvable host; PUT returns 2xx; the file reaches status 'clean'. | G5: P0 | H5: Release | I5: Both | J5: KB-01 | K5: Blocked | L5: Claude (adb) | M5: 46300 | N5: 1.0.0+1 debug | O5: emulator-5554 / Android 14 | Q5: 5 Oct 2026: POST /shared/files/uploads returns 201, but upload_url points at storage.fake.local, which does not resolve (PUT fails: 'nodename nor servname provided'). Backend blocker BB-17 (KB-01).
A6: ENV-005 | B6: 00 Test environment & prerequisites | C6: SMS | D6: OTP SMS is delivered to real test numbers | E6: 1. Start an OTP login for a test number 2. Wait for the SMS | F6: SMS arrives within 30 s with a 4-digit code. (India: DLT sender ID and template are registered.) | G6: P0 | H6: Release | I6: Both | J6: KB-05 | K6: Blocked | L6: Claude (adb) | M6: 46300 | N6: 1.0.0+1 debug | O6: emulator-5554 / Android 14 | Q6: 5 Oct 2026: No SMS is sent on the integration server and the code is not exposed. Backend blocker BB-01 (KB-05).
A7: ENV-006 | B7: 00 Test environment & prerequisites | C7: Push | D7: Push provider configured for Android and iOS | E7: Confirm FCM project, APNs key and app registration exist for the release bundle IDs | F7: A test push sent from the console reaches both platforms. | G7: P0 | H7: Release | I7: Both | J7: KB-04 | K7: Blocked | L7: Claude (adb) | M7: 46300 | N7: 1.0.0+1 debug | O7: emulator-5554 / Android 14 | Q7: 5 Oct 2026: The app has no push SDK (no Firebase/FCM in pubspec.yaml; KB-04), and there is no FCM project or APNs key for the release bundle ids. Needs the owner's decision to add Firebase Messaging plus the project's config files (same as BL-NOTIF-017).
A8: ENV-007 | B8: 00 Test environment & prerequisites | C8: Test data | D8: Test accounts are prepared | E8: Prepare: (a) unregistered mobile number, (b) account with password, (c) OTP-only account, (d) account with 2+ family members, (e) blocked account, (f) account with a completed paid visit, (g) account with a pending deletion request | F8: All seven accounts exist and their credentials are recorded outside this workbook. | G8: P0 | H8: Release | I8: Both | K8: Blocked | L8: Claude (adb) | M8: 46300 | N8: 1.0.0+1 debug | O8: emulator-5554 / Android 14 | Q8: 5 Oct 2026: Available: (b) password account (Sanjay Varma), (d) 2+ family members (Sanjay: Tara, Ishaan), (f) completed visits (Sanjay: 5 completed). Missing: (a) a usable unregistered number (sign-up needs an OTP, BB-01), (c) OTP-only account (BB-01), (e) blocked account (BB-02), (g) account with a pending deletion request (BB-03, a throwaway account is needed).
A9: ENV-008 | B9: 00 Test environment & prerequisites | C9: Test data | D9: Hospital seed data covers every booking state | E9: Prepare: hospital with online booking on, hospital with manual approval, hospital with booking off, doctor with free slots today and next 7 days, doctor on leave, a full session, department with no doctors, coupons (valid, expired, minimum-order, usage-capped) | F9: Every state can be reached from the app without database edits during the run. | G9: P0 | H9: Release | I9: Both | K9: Blocked | L9: Claude (adb) | M9: 46300 | N9: 1.0.0+1 debug | O9: emulator-5554 / Android 14 | Q9: 5 Oct 2026: Seed data lacks several states: hospital with booking off / no free slots (BB-06), doctor on leave or not bookable online (BB-08), known coupons (BB-07), follow-up/date pricing (BB-11). Online booking and free slots for the next days do exist (Dr. Meera Varghese).
A10: ENV-009 | B10: 00 Test environment & prerequisites | C10: Test data | D10: Hospital desk user available to run a live session | E10: Arrange a staff login that can open a session, call tokens, pause, complete and mark no-show | F10: A tester can drive the queue while a second tester watches the patient app. | G10: P1 | H10: Release | I10: Both | J10: KB-08 | K10: Blocked | L10: Claude (adb) | M10: 46300 | N10: 1.0.0+1 debug | O10: emulator-5554 / Android 14 | Q10: 5 Oct 2026: No hospital desk user yet (KB-08). Left until the hospital web app is ready, per the owner's instruction.
A11: ENV-010 | B11: 00 Test environment & prerequisites | C11: Tools | D11: Test devices and tooling ready | E11: 1. Collect the devices in the Device Matrix sheet 2. Install a proxy (Charles/Proxyman/mitmproxy) and a network throttler 3. Enable adb / Xcode console access | F11: All devices charged and enrolled; proxy can observe traffic on a debug/profile build for the NET and SEC cases. | G11: P1 | H11: Release | I11: Both | K11: Blocked | L11: Claude (adb) | M11: 46300 | N11: 1.0.0+1 debug | O11: emulator-5554 / Android 14 | Q11: 5 Oct 2026: Tooling is ready on the test machine: adb on emulator-5554 (rooted), a pass-through recording proxy for the NET/SEC cases, airplane mode and iptables for network faults. Missing: the physical devices in the Device Matrix sheet; only the Android 14 emulator is available for this run.
A12: E2E-001 | B12: 01 End-to-end journeys (run first) | C12: Journey 1 | D12: New patient: install to Home | E12: 1. Fresh install 2. Swipe through onboarding 3. Accept terms on the consent screen 4. Sign up with a new mobile number 5. Enter the OTP | F12: User lands on Home, greeted by first name. Profile shows the entered details. Relaunch goes straight to Home. | G12: P0 | H12: Functional | I12: Both | J12: KB-05 | K12: Blocked | L12: Claude (adb) | M12: 46300 | N12: 1.0.0+1 debug | O12: emulator-5554 / Android 14 | Q12: 5 Oct 2026: Sign-up needs the OTP sent to the new number; no SMS is sent and the code is not exposed on the integration server. BB-01 (KB-05). Onboarding and consent steps work (see ONB rows).
A13: E2E-002 | B13: 01 End-to-end journeys (run first) | C13: Journey 2 | D13: Book and pay for myself | E13: 1. Home > pick a department 2. Choose hospital, doctor, date and slot 3. Select yourself as patient 4. Review the fee 5. Confirm and pay with a Razorpay test method | F13: Success screen shows the server booking reference and token. Appointment appears under Upcoming as confirmed and paid. A confirmation notification arrives. | G13: P0 | H13: Functional | I13: Both | J13: KB-02 | K13: Blocked | L13: Claude (adb) | M13: 46300 | N13: 1.0.0+1 debug | O13: emulator-5554 / Android 14 | Q13: 5 Oct 2026: Booking up to the payment step works (Dr. Meera Varghese, 7 Oct, Sanjay, total ₹424), but payment cannot be made: Razorpay is the in-process fake (key_id empty). BB-16 (KB-02).
A14: E2E-003 | B14: 01 End-to-end journeys (run first) | C14: Journey 3 | D14: Book for a family member with a coupon | E14: 1. Add a family member 2. Start a booking and choose that member 3. Apply a valid coupon 4. Pay | F14: Discount line appears and the amount charged equals the discounted total. Appointment shows the family member as patient. | G14: P0 | H14: Functional | I14: Both | J14: KB-02 | K14: Blocked | L14: Claude (adb) | M14: 46300 | N14: 1.0.0+1 debug | O14: emulator-5554 / Android 14 | Q14: 5 Oct 2026: Needs a real payment (BB-16, KB-02) and a known coupon code (BB-07).
A15: E2E-004 | B15: 01 End-to-end journeys (run first) | C15: Journey 4 | D15: Visit day: queue to receipt to review | E15: 1. With a booking for today, open Live queue 2. Desk user opens the session and calls tokens up to yours 3. Desk completes the consultation 4. Open the receipt 5. Rate the visit | F15: Queue updates live; 'your turn' alert appears when the token is called; appointment moves to Completed; receipt shows correct lines and GST; rating is saved and the Rate button disappears. | G15: P0 | H15: Functional | I15: Both | J15: KB-02, KB-08 | K15: Blocked | L15: Claude (adb) | M15: 46300 | N15: 1.0.0+1 debug | O15: emulator-5554 / Android 14 | Q15: 5 Oct 2026: Needs a paid booking for today (BB-16, KB-02) and a desk user to run the queue (KB-08, left until the hospital web app is ready).
A16: E2E-005 | B16: 01 End-to-end journeys (run first) | C16: Journey 5 | D16: Cancel a paid appointment and receive a refund | E16: 1. Open an upcoming paid appointment 2. Tap Cancel 3. Read the refund preview 4. Confirm | F16: Refund amount in the preview matches the hospital policy; appointment moves to Cancelled; refund record shows with a status; the slot is bookable again. | G16: P0 | H16: Functional | I16: Both | J16: KB-02 | K16: Blocked | L16: Claude (adb) | M16: 46300 | N16: 1.0.0+1 debug | O16: emulator-5554 / Android 14 | Q16: 5 Oct 2026: No paid appointment can be made to cancel and refund (BB-16, KB-02).
A17: E2E-006 | B17: 01 End-to-end journeys (run first) | C17: Journey 6 | D17: Health record lifecycle | E17: 1. Records > Add record 2. Attach a PDF, fill title, type, date and person 3. Save 4. Open it 5. Download 6. Edit the title 7. Delete | F17: Upload completes after the virus scan, document opens and downloads, edit is saved, delete removes it from the list. | G17: P0 | H17: Functional | I17: Both | J17: KB-01 | K17: Blocked | L17: Claude (adb) | M17: 46300 | N17: 1.0.0+1 debug | O17: emulator-5554 / Android 14 | Q17: 5 Oct 2026: Upload links point at storage.fake.local, which does not resolve. BB-17 (KB-01).
A18: E2E-007 | B18: 01 End-to-end journeys (run first) | C18: Journey 7 | D18: Returning user after app kill | E18: 1. Sign in 2. Use the app 3. Force-stop the app 4. Relaunch | F18: Splash then Home with no flash of the sign-in screen. Cached content appears immediately and refreshes in the background. | G18: P0 | H18: Functional | I18: Both | K18: Pass | L18: Claude (adb) | M18: 46300 | N18: 1.0.0+1 debug | O18: emulator-5554 / Android 14 | Q18: 5 Oct 2026: Signed in as Sanjay, force-stopped, relaunched: sampled the screen every ~1 s; Home ('Welcome back, Sanjay!') from the first sample, never the sign-in screen. Cached Home content shown at once.
A19: E2E-008 | B19: 01 End-to-end journeys (run first) | C19: Journey 8 | D19: Forgot password | E19: 1. Login > Forgot password 2. Enter the mobile number 3. Enter the OTP 4. Set a new password 5. Sign in | F19: Reset succeeds, user is sent to sign-in, the new password works and the old one does not. Other signed-in devices are signed out. | G19: P0 | H19: Functional | I19: Both | J19: KB-05 | K19: Blocked | L19: Claude (adb) | M19: 46300 | N19: 1.0.0+1 debug | O19: emulator-5554 / Android 14 | Q19: 5 Oct 2026: The reset needs the OTP sent by SMS; not obtainable on the integration server. BB-01 (KB-05).
A20: E2E-009 | B20: 01 End-to-end journeys (run first) | C20: Journey 9 | D20: Offline and back | E20: 1. Load Home, Appointments and Records online 2. Turn on airplane mode 3. Browse the same screens 4. Try to book 5. Turn airplane mode off | F20: Saved data is shown with an offline indication; booking is refused with a clear message (no crash, no duplicate); everything refreshes when the connection returns. | G20: P0 | H20: Offline | I20: Both | K20: Pass | L20: Claude (adb) | M20: 46300 | N20: 1.0.0+1 debug | O20: emulator-5554 / Android 14 | P20: DEF-075 | Q20: 5 Oct 2026: FIXED two issues (DEF-075, DEF-076). Home, Appointments, Records loaded online; airplane mode on: Home shows saved data, Records shows the Offline mark, Canceled tab shows "You're offline. Showing data from 6 minutes ago." with its cards. Found: the Upcoming tab (empty online) showed an error screen offline -> now 'Nothing here yet' under the offline line (DEF-075). Found: Pay offline spun 3 s then said 'This is taking longer than usual' -> now at once 'You appear to be offline. Check your connection and try again.' (DEF-076). Appointment count on the server stayed 34 (no booking, no duplicate). Back online the screens refresh.
A21: E2E-010 | B21: 01 End-to-end journeys (run first) | C21: Journey 10 | D21: Support ticket | E21: 1. Profile > Help & Support 2. Raise a request with category, subject and description 3. Open the ticket 4. Send a reply | F21: Ticket is created with a ticket number, appears in the list, and the reply shows in the thread. | G21: P1 | H21: Functional | I21: Both | K21: Pass | L21: Claude (adb) | M21: 46300 | N21: 1.0.0+1 debug | O21: emulator-5554 / Android 14 | Q21: 5 Oct 2026: Help & Support > Raise a request: category 'App or technical problem', subject and description > Send Request -> TKT-2026-0023 opened (Open, Normal priority); reply 'Test reply from the app.' shows in the thread; My requests lists TKT-2026-0023 at the top.
A22: E2E-011 | B22: 01 End-to-end journeys (run first) | C22: Journey 11 | D22: Account deletion and reactivation | E22: 1. Profile > Delete account 2. Give a reason and confirm 3. Observe the pending state 4. Reactivate | F22: Request number and the cooling-off end date are shown; account shows as pending deletion; Reactivate restores it to active. | G22: P0 | H22: Functional | I22: Both | K22: Blocked | L22: Claude (adb) | M22: 46300 | N22: 1.0.0+1 debug | O22: emulator-5554 / Android 14 | Q22: 5 Oct 2026: Would put the shared test account (Sanjay) into pending deletion. Needs a throwaway patient account that is ours to change. BB-03.
A23: E2E-012 | B23: 01 End-to-end journeys (run first) | C23: Journey 12 | D23: Sign out and sign back in with OTP | E23: 1. Profile > Log out 2. Confirm 3. Sign in with mobile + OTP | F23: Logout returns to sign-in and Back does not reveal signed-in screens. OTP sign-in lands on Home with the same data. | G23: P0 | H23: Functional | I23: Both | J23: KB-05 | K23: Blocked | L23: Claude (adb) | M23: 46300 | N23: 1.0.0+1 debug | O23: emulator-5554 / Android 14 | Q23: 5 Oct 2026: Logout part passes: Profile > Logout > Log Out -> sign-in screen; Back leaves the app; relaunch and the medibook://appointments link both land on sign-in. OTP sign-in cannot be done: no OTP on the integration server, BB-01 (KB-05). Signed back in with the password.
A24: INS-001 | B24: 02 Install, launch & bootstrap | C24: Install | D24: Fresh install of the release build launches | E24: 1. Install the signed release build (Play internal track / TestFlight) 2. Tap the icon | F24: App opens without a crash or ANR. | G24: P0 | H24: Functional | I24: Both | K24: Blocked | L24: Claude (adb) | M24: 46300 | N24: 1.0.0+1 debug | O24: emulator-5554 / Android 14 | Q24: 5 Oct 2026: A local release APK (flutter build apk --release, 69.9 MB) installs and opens on the emulator with no crash or ANR. Not done: the signed Play internal-track / TestFlight build. The Android release build is still signed with the debug key (KB-06), and no iOS device is available.
A25: INS-002 | B25: 02 Install, launch & bootstrap | C25: Splash | D25: Splash sequence has no flash | E25: 1. Launch on a light-mode device 2. Launch on a dark-mode device | F25: Light: white splash with the brand mark. Dark: navy splash. No white/black flash before the first screen. | G25: P2 | H25: UI | I25: Both | K25: Pass | L25: Claude (adb) | M25: 46300 | N25: 1.0.0+1 debug | O25: emulator-5554 / Android 14 | Q25: 5 Oct 2026: Launch frames captured: light mode shows a white splash with the round navy brand mark; dark mode shows a navy splash with the white mark. No white/black flash between splash and first screen (Android 14 emulator; iOS not run).
A26: INS-003 | B26: 02 Install, launch & bootstrap | C26: Launcher | D26: App name and icon are correct | E26: 1. Look at the launcher / home screen 2. On Android 13+, enable themed icons | F26: Label reads 'Medibook'. Icon is the brand mark; adaptive and monochrome icons render correctly. | G26: P2 | H26: UI | I26: Both | K26: Pass | L26: Claude (adb) | M26: 46300 | N26: 1.0.0+1 debug | O26: emulator-5554 / Android 14 | Q26: 5 Oct 2026: Launcher label 'Medibook' with the brand mark on a navy adaptive icon. The adaptive icon defines a monochrome layer, which Android 13+ themed icons use (themed-icon toggle not switched on in this run).
A27: INS-004 | B27: 02 Install, launch & bootstrap | C27: First run | D27: Onboarding shows only on first run | E27: 1. Fresh install > launch 2. Finish onboarding 3. Kill and relaunch | F27: Onboarding appears the first time only; later launches go to sign-in or Home. | G27: P1 | H27: Functional | I27: Both | K27: Pass | L27: Claude (adb) | M27: 46300 | N27: 1.0.0+1 debug | O27: emulator-5554 / Android 14 | Q27: 5 Oct 2026: App data wiped: intro shown, finished (consent accepted) -> sign-in. Force-stop and relaunch twice: sign-in both times, intro not shown again.
A28: INS-005 | B28: 02 Install, launch & bootstrap | C28: Splash | D28: Session is resolved before any screen is shown | E28: 1. Sign in 2. Kill the app 3. Relaunch on a slow device | F28: Splash stays until the session is known; a signed-in user never sees the sign-in screen flash. | G28: P1 | H28: Functional | I28: Both | K28: Pass | L28: Claude (adb) | M28: 46300 | N28: 1.0.0+1 debug | O28: emulator-5554 / Android 14 | Q28: 5 Oct 2026: Signed in, force-stopped, relaunched: screen sampled about every second from launch; Home from the first sample, sign-in never shown (same run as E2E-007). Slow physical device not available.
A29: INS-006 | B29: 02 Install, launch & bootstrap | C29: Release | D29: No demo affordances in the release build | E29: Open sign-in, sign-up and OTP screens | F29: No prefilled credentials, no 'Demo login is prefilled' text, no 'Demo code: 1234' hint, no reviewer screen-jump menu. | G29: P0 | H29: Security | I29: Both | K29: Pass | L29: Claude (adb) | M29: 46300 | N29: 1.0.0+1 debug | O29: emulator-5554 / Android 14 | Q29: 5 Oct 2026: Release APK: sign-in has empty fields and no 'Demo login is prefilled' text; Mobile tab shows only 'We'll text you a 4-digit code.'; sign-up has no prefilled values; the code screen ('Verify Mobile') has no 'Demo code' hint. No screen-jump menu anywhere.
A30: INS-007 | B30: 02 Install, launch & bootstrap | C30: Release | D30: Production build refuses unsafe configuration | E30: 1. Build with MEDIBOOK_ENV=prod and MEDIBOOK_DEMO=true (then again with MEDIBOOK_ALLOW_BAD_CERT=true) 2. Launch | F30: The app refuses to start and logs a clear configuration error for each case. | G30: P1 | H30: Release | I30: Both | K30: Pass | L30: Claude (adb) | M30: 46300 | N30: 1.0.0+1 debug | O30: emulator-5554 / Android 14 | P30: DEF-078 | Q30: 5 Oct 2026: FIXED (DEF-078). Debug run with MEDIBOOK_ENV=prod: (1) MEDIBOOK_DEMO=true -> refused; (2) MEDIBOOK_ALLOW_BAD_CERT=true -> refused. Found: the app stayed on its splash with nothing in the device log (the error went to DevTools only), and a prod build accepted the integration server's IP as its API. Now it prints 'Medibook cannot start: EnvConfigError: ...' to the device log, shows a 'This build of Medibook is misconfigured and cannot start' screen listing each error, and also refuses an IP-address API host in production.
A31: INS-008 | B31: 02 Install, launch & bootstrap | C31: Upgrade | D31: Upgrade over an older build keeps the user signed in | E31: 1. Install the previous build and sign in 2. Install the new build over it 3. Launch | F31: No crash; session and settings survive; cached data is migrated or rebuilt cleanly. | G31: P1 | H31: Compatibility | I31: Both | K31: Pass | L31: Claude (adb) | M31: 46300 | N31: 1.0.0+1 debug | O31: emulator-5554 / Android 14 | Q31: 5 Oct 2026: Release APK installed over the signed-in debug build (adb install -r): no crash, still signed in as Sanjay, cached appointments shown and refreshed. (No older store build exists to upgrade from; this is the closest check.)
A32: INS-009 | B32: 02 Install, launch & bootstrap | C32: Bootstrap | D32: Launch with no network | E32: 1. Fresh install 2. Enable airplane mode 3. Launch | F32: App opens to onboarding/sign-in with an offline message where data is needed; no infinite spinner and no crash. | G32: P1 | H32: Offline | I32: Both | K32: Pass | L32: Claude (adb) | M32: 46300 | N32: 1.0.0+1 debug | O32: emulator-5554 / Android 14 | Q32: 5 Oct 2026: App data wiped, airplane mode on, launched: intro shown, then consent; no crash, no endless spinner. Agree without the policies loaded shows the 'could not load' note; a policy link shows 'We could not load this document / You appear to be offline' with Try Again.
A33: INS-010 | B33: 02 Install, launch & bootstrap | C33: Bootstrap | D33: Launch succeeds when local storage is damaged | E33: 1. On a debug build, corrupt or delete a Hive box file in the app data directory 2. Launch | F33: App starts, rebuilds the cache from the network and does not crash. | G33: P1 | H33: Negative | I33: Both | K33: Pass | L33: Claude (adb) | M33: 46300 | N33: 1.0.0+1 debug | O33: emulator-5554 / Android 14 | Q33: 5 Oct 2026: Debug build, signed in: http_cache.hive overwritten with 14 KB of random bytes, then launched. Log: 'Recovering corrupted box.' Home opened signed in, Appointments loaded from the server; no crash.
A34: ONB-001 | B34: 03 Onboarding & consent | C34: Onboarding | D34: Intro slides navigate correctly | E34: 1. Swipe between the two slides 2. Use the Next/Skip controls | F34: Slides and carousel dots stay in sync; the final action leads to the consent screen. | G34: P2 | H34: Functional | I34: Both | K34: Pass | L34: Claude (adb) | M34: 46300 | N34: 1.0.0+1 debug | O34: emulator-5554 / Android 14 | Q34: 5 Oct 2026: Swipe left/right moves between slide 1 and 2, the 'Slide n of 2' indicator follows; Continue on slide 1 goes to slide 2; 'Get Started' on slide 2 opens the consent screen; Back on consent returns to the intro.
A35: ONB-002 | B35: 03 Onboarding & consent | C35: Consent | D35: Cannot continue without accepting the policies | E35: 1. Leave the acceptance box unticked 2. Tap Continue | F35: Continue is disabled or an inline message explains that acceptance is required. | G35: P0 | H35: Negative | I35: Both | K35: Pass | L35: Claude (adb) | M35: 46300 | N35: 1.0.0+1 debug | O35: emulator-5554 / Android 14 | Q35: 5 Oct 2026: Box unticked, 'Agree and Continue' -> stays on the screen with 'Please accept the terms to continue.'
A36: ONB-003 | B36: 03 Onboarding & consent | C36: Consent | D36: Marketing opt-in is optional | E36: 1. Accept the policies but leave offers/marketing unticked 2. Continue | F36: User proceeds; marketing_opt_in is false on the account. | G36: P2 | H36: Functional | I36: Both | K36: Blocked | L36: Claude (adb) | M36: 46300 | N36: 1.0.0+1 debug | O36: emulator-5554 / Android 14 | Q36: 5 Oct 2026: Ticking only the terms lets the user continue (checked). The opt-in is sent to the server with sign-up (consents.marketing), and sign-up needs an OTP, so marketing_opt_in on a new account cannot be checked: BB-01 (KB-05).
A37: ONB-004 | B37: 03 Onboarding & consent | C37: Legal | D37: Policy links open the right documents | E37: From the consent screen tap Terms & Conditions, Privacy Policy and User Guidelines in turn | F37: Each opens its own document loaded from the server, with a way back to where the user came from. | G37: P1 | H37: Functional | I37: Both | K37: Pass | L37: Claude (adb) | M37: 46300 | N37: 1.0.0+1 debug | O37: emulator-5554 / Android 14 | P37: DEF-077 | Q37: 5 Oct 2026: FIXED (DEF-077). Terms & Conditions and Privacy Policy each open their own document from the server ('Version 1 · published 31 July 2026'); 'Back to sign up' and system Back return to the consent screen. Found: after opening them offline and reconnecting, both kept showing 'You appear to be offline' until Try Again; they now load again on reconnect. Note: the consent screen links only these two; Community Guidelines is linked from Help & Support and Profile, not from consent.
A38: ONB-005 | B38: 03 Onboarding & consent | C38: Legal | D38: Policy document fails to load | E38: Open a policy with the network off | F38: Error state with a retry (or the cached copy), never a blank page. | G38: P2 | H38: Negative | I38: Both | K38: Pass | L38: Claude (adb) | M38: 46300 | N38: 1.0.0+1 debug | O38: emulator-5554 / Android 14 | Q38: 5 Oct 2026: Airplane mode, Terms opened from consent: 'We could not load this document / You appear to be offline. Check your connection and try again.' with Try Again; never blank.
A39: ONB-006 | B39: 03 Onboarding & consent | C39: Consent | D39: Policy version change triggers re-consent | E39: 1. Publish a new terms version on the backend 2. Open the app as an existing user | F39: 'Our policies have changed' prompt appears; accepting records the consent and the prompt does not return. | G39: P1 | H39: Functional | I39: Both | K39: Blocked | L39: Claude (adb) | M39: 46300 | N39: 1.0.0+1 debug | O39: emulator-5554 / Android 14 | Q39: 5 Oct 2026: Needs a newer policy version published on the server for a short window. BB-20.
A40: AUTH-001 | B40: 04 Authentication & session | C40: Sign up | D40: Sign up with valid details | E40: 1. Enter first name, mobile, date of birth, password 2. Accept the policies 3. Submit 4. Enter the OTP | F40: Account is created, user lands on Home, and a 'self' person exists for booking. | G40: P0 | H40: Functional | I40: Both | J40: KB-05 | K40: Blocked | L40: Claude (adb) | M40: 46300 | N40: 1.0.0+1 debug | O40: emulator-5554 / Android 14 | Q40: 5–6 Oct 2026: The form, validation and 'Verify Mobile' step work (see AUTH-002 to -010); the account is only created after the SMS code is entered. No OTP can be obtained on the integration server: BB-01 (KB-05).
A41: AUTH-002 | B41: 04 Authentication & session | C41: Sign up | D41: Required fields are enforced | E41: Submit with first name, mobile and date of birth empty, one at a time | F41: Each missing field shows its own inline message; no request is sent. | G41: P1 | H41: Negative | I41: Both | K41: Pass | L41: Claude (adb) | M41: 46300 | N41: 1.0.0+1 debug | O41: emulator-5554 / Android 14 | Q41: 5–6 Oct 2026: Create Account with everything empty: 'Enter your first name', 'Enter your mobile number', 'Select a date of birth' under their own fields, plus the terms message; nothing sent. (Note for module 22: these field errors are not in the accessibility tree.)
A42: AUTH-003 | B42: 04 Authentication & session | C42: Sign up | D42: Mobile number validation | E42: Try: empty, letters, 9 digits, 11 digits, a number starting with 0-5, a valid number typed with spaces/dashes | F42: All invalid inputs are rejected inline; the valid number with spaces/dashes is accepted. | G42: P1 | H42: Negative | I42: Both | K42: Pass | L42: Claude (adb) | M42: 46300 | N42: 1.0.0+1 debug | O42: emulator-5554 / Android 14 | Q42: 5–6 Oct 2026: Device: the mobile box only accepts digits ('98a08-b6832c57' typed -> '9808683257'). Rules in test/core/utils/validators_test.dart: empty 'Enter your mobile number', 9 and 11 digits 'Mobile number must be 10 digits', starts 0-5 'Mobile number must start with 6-9', '98086 83257' and '980-868-3257' accepted. Same as BL-AUTH-007.
A43: AUTH-004 | B43: 04 Authentication & session | C43: Sign up | D43: Already-registered mobile number | E43: Sign up with a number that already has an account | F43: Inline error on the mobile field saying it is already registered; no OTP screen. | G43: P1 | H43: Negative | I43: Both | K43: Pass | L43: Claude (adb) | M43: 46300 | N43: 1.0.0+1 debug | O43: emulator-5554 / Android 14 | Q43: 5–6 Oct 2026: Sign-up with 9808683257 (Sanjay's number): 'This mobile number is already registered. Log in instead.' under Mobile Number; no code screen.
A44: AUTH-005 | B44: 04 Authentication & session | C44: Sign up | D44: Account holder under 18 | E44: 1. Enter a date of birth less than 18 years ago 2. Submit | F44: Sign-up is refused with a clear age message (UNDER_AGE). | G44: P1 | H44: Negative | I44: Both | K44: Pass | L44: Claude (adb) | M44: 46300 | N44: 1.0.0+1 debug | O44: emulator-5554 / Android 14 | Q44: 5–6 Oct 2026: The date picker opens on Oct 2008; 6 Oct 2008 onward is 'Out of range' and cannot be picked; hint 'You must be 18 or older to open an account.' Server: signup/start with date_of_birth 2010-01-01 -> 409 UNDER_AGE 'Account holders must be 18 or older…'; the app maps UNDER_AGE onto the date-of-birth field (signup_form_controller).
A45: AUTH-006 | B45: 04 Authentication & session | C45: Sign up | D45: Email is optional and validated | E45: 1. Submit without an email 2. Submit with 'abc', 'a@b', 'a b@c.com' | F45: Blank is accepted; malformed emails are rejected inline. | G45: P2 | H45: Negative | I45: Both | K45: Pass | L45: Claude (adb) | M45: 46300 | N45: 1.0.0+1 debug | O45: emulator-5554 / Android 14 | Q45: 5–6 Oct 2026: Blank email accepted (submit went on to server checks). 'a b@c.com' -> 'Enter a valid email address' inline. 'abc' and 'a@b' rejected by the same rule (validators_test).
A46: AUTH-007 | B46: 04 Authentication & session | C46: Sign up | D46: Password rule matches the server (10+ characters) | E46: 1. Try a 6-character password, a 9-character password, one containing your name/phone, and a valid 10+ character one 2. Compare the on-screen hint with the rule | F46: Short and personal-data passwords are rejected with a clear message; the hint reads 'At least 10 characters'. | G46: P1 | H46: Negative | I46: Both | K46: Pass | L46: Claude (adb) | M46: 46300 | N46: 1.0.0+1 debug | O46: emulator-5554 / Android 14 | Q46: 5–6 Oct 2026: Hint reads 'At least 10 characters' / 'If set, at least 10 characters.' 6 and 9 characters -> 'At least 10 characters' (validators_test; BL-AUTH-010). Password with the first name ('Qachecker123') -> 'The password must not contain your name, email or phone number.'; a common one -> 'This password has appeared in a data breach. Choose another.' Both under the password field.
A47: AUTH-008 | B47: 04 Authentication & session | C47: Sign up | D47: Confirm password mismatch | E47: Enter different values in Password and Confirm Password | F47: Inline mismatch error; submit blocked. | G47: P2 | H47: Negative | I47: Both | K47: Pass | L47: Claude (adb) | M47: 46300 | N47: 1.0.0+1 debug | O47: emulator-5554 / Android 14 | Q47: 5–6 Oct 2026: Different Password and Confirm Password -> 'Passwords do not match' under Confirm Password; submit blocked.
A48: AUTH-009 | B48: 04 Authentication & session | C48: Sign up | D48: Server field errors land on the right fields | E48: Trigger server-side errors for phone, email and password (proxy or real data) | F48: Each server message is shown under its field, not as a generic toast. | G48: P1 | H48: Negative | I48: Both | K48: Pass | L48: Claude (adb) | M48: 46300 | N48: 1.0.0+1 debug | O48: emulator-5554 / Android 14 | Q48: 5–6 Oct 2026: Real server errors, each under its field: mobile 'This mobile number is already registered. Log in instead.', email 'This email is already registered.', password 'must not contain your name…' / 'appeared in a data breach'. No generic toast.
A49: AUTH-010 | B49: 04 Authentication & session | C49: Sign up | D49: Optional address validation | E49: Add an address with a 5-digit PIN, then a PIN starting with 0, then a valid 6-digit PIN | F49: Invalid PINs rejected inline; valid address becomes the default address in Profile. | G49: P2 | H49: Functional | I49: Both | K49: Blocked | L49: Claude (adb) | M49: 46300 | N49: 1.0.0+1 debug | O49: emulator-5554 / Android 14 | Q49: 5–6 Oct 2026: Validation passes: PIN '68202' -> 'PIN code must be 6 digits', '082020' -> 'Enter a valid PIN code'; a partly filled address asks for street, city, state and PIN (BL-AUTH-012). Not checkable: the address becoming the default in Profile, which needs a created account. No OTP can be obtained on the integration server: BB-01 (KB-05).
A50: AUTH-011 | B50: 04 Authentication & session | C50: OTP | D50: OTP entry behaviour | E50: 1. Type the 4 digits 2. Use backspace 3. Paste a 4-digit code 4. On iOS use the keyboard's one-time-code suggestion | F50: Focus advances and retreats correctly, paste fills all boxes, numeric keyboard is shown. | G50: P1 | H50: Functional | I50: Both | K50: Blocked | L50: Claude (adb) | M50: 46300 | N50: 1.0.0+1 debug | O50: emulator-5554 / Android 14 | Q50: 5–6 Oct 2026: The code screen shows a 4-digit numeric box ('Verification code, 4 digits'); local checks pass (BL-AUTH-017). Typing, backspace and paste of a real code, and the iOS one-time-code suggestion, need a delivered code. No OTP can be obtained on the integration server: BB-01 (KB-05).
A51: AUTH-012 | B51: 04 Authentication & session | C51: OTP | D51: Masked destination is displayed | E51: Reach the verify screen | F51: Text shows the masked number (e.g. +91******10), never another user's number. | G51: P2 | H51: Functional | I51: Both | K51: Pass | L51: Claude (adb) | M51: 46300 | N51: 1.0.0+1 debug | O51: emulator-5554 / Android 14 | Q51: 5–6 Oct 2026: Code screens show the masked destination: '+91******57' for Sanjay's number, '+91******83' for an unregistered one; never another user's number.
A52: AUTH-013 | B52: 04 Authentication & session | C52: OTP | D52: Wrong code | E52: Enter an incorrect code once, then twice, then a third time | F52: Each failure shows the attempts remaining; after the third the user is told to request a new code. | G52: P0 | H52: Negative | I52: Both | J52: KB-05 | K52: Pass | L52: Claude (adb) | M52: 46300 | N52: 1.0.0+1 debug | O52: emulator-5554 / Android 14 | Q52: 5–6 Oct 2026: Wrong codes: 'That code is not right. Check it and try again. 2 attempts left.' then '1 attempt left'; after the third the user is told to ask for a new code (BL-AUTH-018, and seen again 5 Oct on the phone-change code). A wrong code can be tested without SMS.
A53: AUTH-014 | B53: 04 Authentication & session | C53: OTP | D53: Expired code | E53: 1. Wait more than 180 s after the SMS 2. Enter the code | F53: Clear 'code expired' message with a resend option. | G53: P1 | H53: Negative | I53: Both | J53: KB-05 | K53: Blocked | L53: Claude (adb) | M53: 46300 | N53: 1.0.0+1 debug | O53: emulator-5554 / Android 14 | Q53: 5–6 Oct 2026: The code screen shows 'Code expires in' / 'mm:ss remaining' (BL-AUTH-020) and the expired-code handling is covered by BL-AUTH-018; entering the real code after 180 s needs a delivered SMS. No OTP can be obtained on the integration server: BB-01 (KB-05).
A54: AUTH-015 | B54: 04 Authentication & session | C54: OTP | D54: Resend cooldown and limit | E54: 1. Check the resend control immediately 2. Wait 30 s and resend 3. Use the old code 4. Resend more than 3 times | F54: Resend is disabled with a countdown for 30 s; the new code works and the old one fails; exceeding the limit shows a wait time. | G54: P1 | H54: Functional | I54: Both | J54: KB-05 | K54: Blocked | L54: Claude (adb) | M54: 46300 | N54: 1.0.0+1 debug | O54: emulator-5554 / Android 14 | Q54: 5–6 Oct 2026: Resend is disabled with a 30 s countdown ('00:25 remaining') and unlocks after it (BL-AUTH-020). New-code-works / old-code-fails needs delivered codes. No OTP can be obtained on the integration server: BB-01 (KB-05).
A55: AUTH-016 | B55: 04 Authentication & session | C55: OTP | D55: Verify screen survives backgrounding | E55: On the verify screen, switch to the SMS app and return | F55: The same challenge is still active and the code can be entered. | G55: P1 | H55: Functional | I55: Both | J55: KB-05 | K55: Blocked | L55: Claude (adb) | M55: 46300 | N55: 1.0.0+1 debug | O55: emulator-5554 / Android 14 | Q55: 5–6 Oct 2026: Needs a delivered code to enter after returning from the SMS app. No OTP can be obtained on the integration server: BB-01 (KB-05).
A56: AUTH-017 | B56: 04 Authentication & session | C56: Login | D56: Sign in with mobile + password | E56: 1. Enter a registered mobile and the correct password 2. Log In | F56: User lands on Home. | G56: P0 | H56: Functional | I56: Both | K56: Pass | L56: Claude (adb) | M56: 46300 | N56: 1.0.0+1 debug | O56: emulator-5554 / Android 14 | Q56: 5–6 Oct 2026: Signed in with '+919808683257' and the password -> Home ('Welcome back, Sanjay!').
A57: AUTH-018 | B57: 04 Authentication & session | C57: Login | D57: Sign in with email + password | E57: 1. Enter a registered email and the correct password 2. Log In | F57: User lands on Home. | G57: P1 | H57: Functional | I57: Both | K57: Pass | L57: Claude (adb) | M57: 46300 | N57: 1.0.0+1 debug | O57: emulator-5554 / Android 14 | Q57: 5–6 Oct 2026: Signed in with sanjay.varma@patients.medibook.example.com and the password -> Home (several times today).
A58: AUTH-019 | B58: 04 Authentication & session | C58: Login | D58: Wrong password | E58: Enter a wrong password | F58: Error is shown on the form with attempts remaining; the fields stay filled; the user is not logged out or redirected. | G58: P0 | H58: Negative | I58: Both | K58: Pass | L58: Claude (adb) | M58: 46300 | N58: 1.0.0+1 debug | O58: emulator-5554 / Android 14 | Q58: 5–6 Oct 2026: Wrong password: 'That email or number and password do not match an account. 4 attempts left.' on the form plus the amber attempts notice; fields stay filled; no redirect or sign-out.
A59: AUTH-020 | B59: 04 Authentication & session | C59: Login | D59: Lockout after 5 failed attempts | E59: 1. Fail 4 times and note the 'One attempt left' warning 2. Fail a 5th time 3. Kill and relaunch 4. Try OTP login for the same account | F59: Lockout screen with a countdown to the server's locked_until time; countdown survives relaunch; the lock cannot be bypassed via the other sign-in method. | G59: P0 | H59: Security | I59: Both | K59: Pass | L59: Claude (adb) | M59: 46300 | N59: 1.0.0+1 debug | O59: emulator-5554 / Android 14 | Q59: 5–6 Oct 2026: 5th failure: 'Too many failed attempts — Sign-in is paused for your security. Try again in 59:58 remaining'; Log In disabled. Survives force-stop and relaunch (BL-AUTH-033, -034). The pause is per account (BL-AUTH-035). Signing in by code for the same locked account cannot be completed here (BB-01), so the bypass check is on the server's side only.
A60: AUTH-021 | B60: 04 Authentication & session | C60: Login | D60: Sign-in works after the lockout ends | E60: 1. Wait for the lockout to expire 2. Sign in with correct credentials | F60: Sign-in succeeds. | G60: P1 | H60: Functional | I60: Both | K60: Pass | L60: Claude (adb) | M60: 46301 | N60: 1.0.0+1 debug | O60: emulator-5554 / Android 14 | Q60: 6 Oct 2026: The spare account Jacob Mathew was locked with five wrong passwords at 19:47:42 UTC (5th answer 423 AUTH_LOCKED_OUT); during the lock even the correct password was refused (423). At 20:47:44 the server answered a wrong password with 401 again (lock lifted after an hour), and signing in on the emulator with the correct password opened Home. Signed back in as Sanjay.
A61: AUTH-022 | B61: 04 Authentication & session | C61: Login | D61: Sign in with OTP | E61: 1. Choose mobile sign-in 2. Send Code 3. Enter the OTP | F61: User lands on Home. | G61: P0 | H61: Functional | I61: Both | J61: KB-05 | K61: Blocked | L61: Claude (adb) | M61: 46300 | N61: 1.0.0+1 debug | O61: emulator-5554 / Android 14 | Q61: 5–6 Oct 2026: Send Code opens 'Verify Mobile — We sent a 4-digit code to +919808683257'; the code itself never arrives. No OTP can be obtained on the integration server: BB-01 (KB-05).
A62: AUTH-023 | B62: 04 Authentication & session | C62: Login | D62: OTP sign-in for an unregistered number does not reveal account existence | E62: Request a code for an unregistered number | F62: Same screen and wording as for a registered number; verification simply fails. No 'number not registered' message. | G62: P1 | H62: Security | I62: Both | K62: Pass | L62: Claude (adb) | M62: 46300 | N62: 1.0.0+1 debug | O62: emulator-5554 / Android 14 | Q62: 5–6 Oct 2026: Unregistered 9123456781 at Send Code opens the same verify screen and wording as a registered number (BL-AUTH-029); the same holds for Forgot password (AUTH-030).
A63: AUTH-024 | B63: 04 Authentication & session | C63: Login | D63: OTP-only account tries password sign-in | E63: 1. Use an account that has no password 2. Sign in with any password | F63: Generic invalid-credentials message; guidance to use a code or 'Forgot password?'. | G63: P2 | H63: Negative | I63: Both | K63: Blocked | L63: Claude (adb) | M63: 46300 | N63: 1.0.0+1 debug | O63: emulator-5554 / Android 14 | Q63: 5–6 Oct 2026: No code-only (password-less) account exists to test with, and one cannot be created without an OTP. No OTP can be obtained on the integration server: BB-01 (KB-05).
A64: AUTH-025 | B64: 04 Authentication & session | C64: Login | D64: Blocked account | E64: Sign in with the blocked test account | F64: 'Account blocked' message with a support route; no session is created. | G64: P1 | H64: Negative | I64: Both | K64: Blocked | L64: Claude (adb) | M64: 46300 | N64: 1.0.0+1 debug | O64: emulator-5554 / Android 14 | Q64: 5–6 Oct 2026: No blocked patient account exists. BB-02.
A65: AUTH-026 | B65: 04 Authentication & session | C65: Login | D65: Too many requests | E65: Submit sign-in rapidly more than 5 times in a minute | F65: A 'please wait N seconds' message based on the server's Retry-After; no crash. | G65: P2 | H65: Negative | I65: Both | K65: Pass | L65: Claude (adb) | M65: 46300 | N65: 1.0.0+1 debug | O65: emulator-5554 / Android 14 | P65: DEF-079 | Q65: 5–6 Oct 2026: FIXED (DEF-079). The server answers 429 RATE_LIMITED with only a Retry-After header (meta empty). The app said 'Too many attempts. Please wait a moment and try again.' Now: 'Too many attempts. Please wait 40 seconds and try again.' (seconds from Retry-After). No crash. Rapid wrong passwords for one identifier reach the 5-try pause first.
A66: AUTH-027 | B66: 04 Authentication & session | C66: Login | D66: Form usability | E66: 1. Toggle password visibility 2. Move between fields with the keyboard Next key 3. Submit with the keyboard Done key 4. Double-tap Log In | F66: Visibility toggles; focus order is logical; only one request is sent on double-tap; the button shows progress. | G66: P2 | H66: UI | I66: Both | K66: Pass | L66: Claude (adb) | M66: 46300 | N66: 1.0.0+1 debug | O66: emulator-5554 / Android 14 | Q66: 5–6 Oct 2026: Show/Hide password toggles the text; keyboard Next moves from the identifier to the password; Done signs in; a second submit while one is in flight is ignored (the form returns early while busy) and the button shows progress.
A67: AUTH-028 | B67: 04 Authentication & session | C67: Forgot password | D67: Reset by mobile number | E67: 1. Forgot password > enter mobile 2. Enter OTP 3. Enter a new valid password | F67: User is returned to sign-in; the new password works; the old one is rejected. | G67: P0 | H67: Functional | I67: Both | J67: KB-05 | K67: Blocked | L67: Claude (adb) | M67: 46300 | N67: 1.0.0+1 debug | O67: emulator-5554 / Android 14 | Q67: 5–6 Oct 2026: Forgot password > mobile opens 'Verify Code — We sent a 4-digit code to +91******57'; the code never arrives. No OTP can be obtained on the integration server: BB-01 (KB-05).
A68: AUTH-029 | B68: 04 Authentication & session | C68: Forgot password | D68: Reset by email identifier | E68: Enter a registered email as the identifier | F68: Flow proceeds; the destination number is not revealed. | G68: P2 | H68: Security | I68: Both | J68: KB-05 | K68: Blocked | L68: Claude (adb) | M68: 46300 | N68: 1.0.0+1 debug | O68: emulator-5554 / Android 14 | Q68: 5–6 Oct 2026: With the registered email the flow continues to the code screen without showing the number (BL-AUTH-038); finishing needs the code. No OTP can be obtained on the integration server: BB-01 (KB-05).
A69: AUTH-030 | B69: 04 Authentication & session | C69: Forgot password | D69: Unknown identifier | E69: Enter an unregistered number | F69: Same response as for a known account (no enumeration). | G69: P1 | H69: Security | I69: Both | K69: Pass | L69: Claude (adb) | M69: 46300 | N69: 1.0.0+1 debug | O69: emulator-5554 / Android 14 | Q69: 5–6 Oct 2026: Forgot password with unregistered 9123456783: 'Verify Code — We sent a 4-digit code to +91******83.' — the same screen and wording as for registered 9808683257 ('+91******57'). No 'not registered' message.
A70: AUTH-031 | B70: 04 Authentication & session | C70: Forgot password | D70: Reset token expired | E70: 1. Verify the OTP 2. Wait more than 15 minutes 3. Submit a new password | F70: Clear message that the link/session expired, with a way to restart. | G70: P2 | H70: Negative | I70: Both | J70: KB-05 | K70: Blocked | L70: Claude (adb) | M70: 46300 | N70: 1.0.0+1 debug | O70: emulator-5554 / Android 14 | Q70: 5–6 Oct 2026: Needs a delivered reset code to get the reset token. No OTP can be obtained on the integration server: BB-01 (KB-05).
A71: AUTH-032 | B71: 04 Authentication & session | C71: Forgot password | D71: New-password hint matches the rule on reset and change-password | E71: 1. Open the new-password form in Forgot password and in Profile > Change password 2. Read the hint 3. Try a 6-character and a 9-character password | F71: Hint states the real rule (at least 10 characters) and both short passwords are rejected inline. | G71: P1 | H71: Negative | I71: Both | J71: KB-09 | K71: Pass | L71: Claude (adb) | M71: 46300 | N71: 1.0.0+1 debug | O71: emulator-5554 / Android 14 | Q71: 5–6 Oct 2026: Both new-password forms (reset and Profile > Change password) state the 10-character rule and reject 6 and 9 characters (BL-AUTH-043, DEF-006 fixed 5 Oct).
A72: AUTH-033 | B72: 04 Authentication & session | C72: Session | D72: Access token refresh is silent | E72: 1. Sign in 2. Leave the app idle for 16+ minutes 3. Pull to refresh on any screen | F72: Data loads; the user is not logged out and sees no error. | G72: P0 | H72: Functional | I72: Both | K72: Pass | L72: Claude (adb) | M72: 46300 | N72: 1.0.0+1 debug | O72: emulator-5554 / Android 14 | Q72: 5–6 Oct 2026: Expired access token refreshed silently; data loads, no sign-out or error (BL-AUTH-047, -051 retested 5 Oct with the calls watched).
A73: AUTH-034 | B73: 04 Authentication & session | C73: Session | D73: Refresh is single-flight | E73: 1. With a proxy attached, let the access token expire 2. Open Home (several requests fire together) | F73: Exactly one token/refresh call is made; every original request then succeeds. The session is not revoked. | G73: P0 | H73: Security | I73: Both | K73: Pass | L73: Claude (adb) | M73: 46300 | N73: 1.0.0+1 debug | O73: emulator-5554 / Android 14 | Q73: 5–6 Oct 2026: Several requests failing with an expired token trigger exactly one refresh; each retried once and succeeds (BL-AUTH-048, calls watched through the recorder on 5 Oct).
A74: AUTH-035 | B74: 04 Authentication & session | C74: Session | D74: Rotated refresh token is persisted | E74: 1. Trigger a refresh 2. Force-stop the app 3. Relaunch | F74: User is still signed in (the new refresh token was stored). | G74: P0 | H74: Functional | I74: Both | K74: Pass | L74: Claude (adb) | M74: 46300 | N74: 1.0.0+1 debug | O74: emulator-5554 / Android 14 | Q74: 5–6 Oct 2026: After a refresh, force-stop and relaunch: still signed in (BL-AUTH-047). Also survived a full emulator reboot today (AUTH-037).
A75: AUTH-036 | B75: 04 Authentication & session | C75: Session | D75: Session revoked from another device | E75: 1. Sign in on devices A and B 2. On A, end B's session from Signed-in devices 3. Use B | F75: B is returned to sign-in with an explanatory message; its tokens and cached data are cleared. | G75: P0 | H75: Security | I75: Both | K75: Pass | L75: Claude (adb) | M75: 46300 | N75: 1.0.0+1 debug | O75: emulator-5554 / Android 14 | Q75: 5–6 Oct 2026: Session ended from another client: on its next call the emulator returned to sign-in with the reason shown, and its cache was cleared (BL-AUTH-049, -050, -059).
A76: AUTH-037 | B76: 04 Authentication & session | C76: Session | D76: Stay signed in across restart and reboot | E76: 1. Sign in 2. Reboot the device 3. Open the app | F76: User is still signed in. | G76: P1 | H76: Functional | I76: Both | K76: Pass | L76: Claude (adb) | M76: 46300 | N76: 1.0.0+1 debug | O76: emulator-5554 / Android 14 | Q76: 5–6 Oct 2026: Signed in, emulator rebooted (adb reboot), app opened: 'Welcome back, Sanjay!' — still signed in.
A77: AUTH-038 | B77: 04 Authentication & session | C77: Session | D77: Expired session (7 days idle / 30 days absolute) | E77: 1. Use a session expired on the backend (or wait) 2. Open the app | F77: User is taken to sign-in with a 'session expired' message; no error loop. | G77: P1 | H77: Functional | I77: Both | K77: Pass | L77: Claude (adb) | M77: 46300 | N77: 1.0.0+1 debug | O77: emulator-5554 / Android 14 | Q77: 5–6 Oct 2026: A session the server no longer accepts sends the user to sign-in once with the 'session ended' message, no loop (BL-AUTH-049, -050). The 7-day / 30-day expiry itself was not waited out.
A78: AUTH-039 | B78: 04 Authentication & session | C78: Logout | D78: Log out | E78: 1. Profile > Log out 2. Confirm 3. Press Back | F78: Sign-in screen is shown; Back does not return to signed-in screens; relaunch stays signed out; the push device is unregistered. | G78: P0 | H78: Security | I78: Both | K78: Pass | L78: Claude (adb) | M78: 46300 | N78: 1.0.0+1 debug | O78: emulator-5554 / Android 14 | Q78: 5–6 Oct 2026: Profile > Logout > Log Out -> sign-in; Back leaves the app; relaunch stays signed out (E2E-012). Push device unregistering does not apply: the app has no push registration yet (KB-04).
A79: AUTH-040 | B79: 04 Authentication & session | C79: Logout | D79: Cancel the logout dialog | E79: 1. Profile > Log out 2. Dismiss the dialog | F79: User stays signed in. | G79: P3 | H79: Functional | I79: Both | K79: Pass | L79: Claude (adb) | M79: 46300 | N79: 1.0.0+1 debug | O79: emulator-5554 / Android 14 | Q79: 5–6 Oct 2026: Logout dialog: Cancel and tapping outside both keep the user signed in; relaunch still shows Home.
A80: AUTH-041 | B80: 04 Authentication & session | C80: Guard | D80: Signed-out user cannot reach protected screens | E80: While signed out, open deep links to /appointments, /profile/edit and /records | F80: User is redirected to sign-in, and after signing in continues to the requested screen (or Home). | G80: P0 | H80: Security | I80: Both | K80: Pass | L80: Claude (adb) | M80: 46300 | N80: 1.0.0+1 debug | O80: emulator-5554 / Android 14 | Q80: 5–6 Oct 2026: Signed out, medibook://appointments, /profile/edit and /records land on sign-in (BL-AUTH-054, and today's link check). After signing in the user lands on Home.
A81: AUTH-042 | B81: 04 Authentication & session | C81: Change password | D81: Change password with the correct current password | E81: 1. Profile > Change password 2. Enter current and a new valid password 3. Save | F81: Success message; this device stays signed in; other devices are signed out. | G81: P1 | H81: Functional | I81: Both | K81: Blocked | L81: Claude (adb) | M81: 46300 | N81: 1.0.0+1 debug | O81: emulator-5554 / Android 14 | Q81: 5–6 Oct 2026: Would change the shared seed account's password; changing it back may be refused by the breach/old-password rules. Needs a throwaway account (BB-03).
A82: AUTH-043 | B82: 04 Authentication & session | C82: Change password | D82: Wrong current password does not log the user out | E82: 1. Enter a wrong current password 2. Save | F82: Inline error on the current-password field. The user stays signed in. | G82: P0 | H82: Negative | I82: Both | K82: Pass | L82: Claude (adb) | M82: 46300 | N82: 1.0.0+1 debug | O82: emulator-5554 / Android 14 | Q82: 5–6 Oct 2026: Wrong current password: 'That is not your current password' under Current password; the user stays signed in (BL-AUTH-044, -052).
A83: AUTH-044 | B83: 04 Authentication & session | C83: Change password | D83: OTP-only account sets a password | E83: 1. On an account without a password, open 'Set a password' 2. Save a valid password | F83: No current password is asked; afterwards password sign-in works. | G83: P2 | H83: Functional | I83: Both | K83: Blocked | L83: Claude (adb) | M83: 46300 | N83: 1.0.0+1 debug | O83: emulator-5554 / Android 14 | Q83: 5–6 Oct 2026: No code-only account can be signed in to without an OTP. No OTP can be obtained on the integration server: BB-01 (KB-05).
... A88: HOME-005 | B88: 05 Home dashboard | C88: Home | D88: Hospitals list and View all | E88: 1. Tap a hospital card 2. Tap 'View all hospitals' | F88: Card opens that hospital's detail; View all opens the hospitals list. | G88: P1 | H88: Functional | I88: Both | K88: Pass | L88: Claude (adb) | M88: 46301 | N88: 1.0.0+1 debug | O88: emulator-5554 / Android 14 | Q88: 6 Oct 2026: Hospital card (Sahyadri City Hospital) opens Hospital Details for it; 'View all hospitals' opens the Hospitals list.
A89: HOME-006 | B89: 05 Home dashboard | C89: Home | D89: Promo banners | E89: 1. Watch the banner for 10 s 2. Swipe manually 3. Turn on Reduce Motion and reopen Home | F89: Banner rotates about every 4 s with dots in sync; no rotation when Reduce Motion is on. | G89: P2 | H89: UI | I89: Both | K89: Pass | L89: Claude (adb) | M89: 46301 | N89: 1.0.0+1 debug | O89: emulator-5554 / Android 14 | P89: DEF-098 | Q89: 6 Oct 2026: OWNER DECISION: auto-rotate. FIXED (DEF-098): the offers strip moves to the next card every 4 s and wraps to the first; it stays still when the phone's 'Remove animations' is on (reduced motion), while a finger is on it (and one interval after), when another screen covers Home, and with a single card. Emulator: card x-position sampled every 2 s went 986 -> 138 -> 986 (rotating, 2 banners); with Remove animations on it stayed at 986 for 12 s. Tests: promo_banner_rotation_test.dart (rotate + wrap, reduced motion, held).
A90: HOME-007 | B90: 05 Home dashboard | C90: Home | D90: Notification bell badge | E90: 1. Compare the badge with the unread notifications 2. Trigger a new notification | F90: Badge matches the unread count and updates without a manual refresh. | G90: P1 | H90: Functional | I90: Both | K90: Pass | L90: Claude (adb) | M90: 46301 | N90: 1.0.0+1 debug | O90: emulator-5554 / Android 14 | Q90: 6 Oct 2026: Badge 'Notifications, 19 unread' = server unread_count 19. One notification marked read through the API: the badge showed 18 within 5 s with no refresh (live inbox socket). Put back to unread afterwards (19).
A91: HOME-008 | B91: 05 Home dashboard | C91: Home | D91: Pull to refresh | E91: Pull down on Home | F91: Sections reload; indicator disappears; no duplicate content. | G91: P2 | H91: Functional | I91: Both | K91: Pass | L91: Claude (adb) | M91: 46301 | N91: 1.0.0+1 debug | O91: emulator-5554 / Android 14 | Q91: 6 Oct 2026: Pulled down on Home: sections reload, indicator goes away, still exactly two hospital cards (no duplicates).
A92: HOME-009 | B92: 05 Home dashboard | C92: Home | D92: Empty states | E92: Use a location with no live hospitals / no departments | F92: 'No hospital is live…' and 'No departments are taking bookings…' messages appear instead of blank areas. | G92: P2 | H92: Negative | I92: Both | K92: Blocked | L92: Claude (adb) | M92: 46301 | N92: 1.0.0+1 debug | O92: emulator-5554 / Android 14 | Q92: 6 Oct 2026: No location or data set with zero live hospitals or departments on the integration server (BB-06). The empty texts exist in code ('No hospital is live and accepting patients right now.', 'No departments are taking bookings right now.').
A93: HOME-010 | B93: 05 Home dashboard | C93: Home | D93: Section failure does not blank the whole screen | E93: With a proxy, fail one Home request (e.g. hospitals) with a 500 | F93: Other sections still render; the failed section shows an error with retry. | G93: P1 | H93: Negative | I93: Both | K93: Pass | L93: Claude (adb) | M93: 46301 | N93: 1.0.0+1 debug | O93: emulator-5554 / Android 14 | P93: DEF-081 | Q93: 6 Oct 2026: FIXED (DEF-081). Widget test (test/features/dashboard/home_section_failure_test.dart): hospitals request fails, the rest of Home renders and the section shows an error with Try Again. Found: Try Again (and the section's refresh) reloaded a different provider, so it did nothing. Now it reloads the hospitals section.
A94: HOME-011 | B94: 05 Home dashboard | C94: Bottom nav | D94: Tab bar navigation and state | E94: 1. Scroll within Appointments 2. Switch to Records and back 3. Re-tap the active tab | F94: Each tab keeps its scroll position and stack; the active tab is highlighted. | G94: P1 | H94: Functional | I94: Both | K94: Pass | L94: Claude (adb) | M94: 46301 | N94: 1.0.0+1 debug | O94: emulator-5554 / Android 14 | Q94: 6 Oct 2026: Appointments scrolled (Canceled tab), switched to Records and back: same scroll position; re-tapping the tab keeps it. Active tab highlighted (bold navy, filled icon) and marked selected for accessibility.
A95: HOME-012 | B95: 05 Home dashboard | C95: Home | D95: Search entry | E95: Tap the Home search bar | F95: Search screen opens with the keyboard focused. | G95: P2 | H95: Functional | I95: Both | K95: Pass | L95: Claude (adb) | M95: 46301 | N95: 1.0.0+1 debug | O95: emulator-5554 / Android 14 | P95: DEF-082 | Q95: 6 Oct 2026: FIXED (DEF-082). The Home search bar opens Search; the box was not focused and no keyboard appeared. Now the box is focused and the keyboard is up on arrival.
A96: DISC-001 | B96: 06 Discovery: locations, hospitals, doctors, search | C96: Locations | D96: Choose a location | E96: 1. Open Locations 2. Pick a city/area 3. Return Home | F96: Home and hospital lists reflect the chosen location; the choice survives relaunch. | G96: P1 | H96: Functional | I96: Both | K96: Pass | L96: Claude (adb) | M96: 46301 | N96: 1.0.0+1 debug | O96: emulator-5554 / Android 14 | P96: DEF-099 | Q96: 6 Oct 2026: OWNER DECISION: save the location and scope Home to it. FIXED (DEF-099): choosing an area saves it (settings box, per device, kept across relaunch and sign-out); Home's 'Hospitals Near You' (and so the offers strip) and the Hospitals list then ask the server for that city/area, with 'In <area>, <city> · Change' under the heading. 'Show hospitals in every area' / 'See every hospital' clears it. Emulator: chose Kadavanthra, Kochi -> list '1 hospital'; Home 'In Kadavanthra, Kochi', Lakeshore only; after force-stop + relaunch still scoped; cleared -> Home lists Lakeshore and Sahyadri. Works with the distance order (DISC-015). Tests: location_scope_test.dart.
A97: DISC-002 | B97: 06 Discovery: locations, hospitals, doctors, search | C97: Hospitals | D97: Hospital list loads and paginates | E97: 1. Open Hospitals 2. Scroll to the end | F97: More results load; no duplicates; end of list handled. | G97: P1 | H97: Functional | I97: Both | K97: Blocked | L97: Claude (adb) | M97: 46301 | N97: 1.0.0+1 debug | O97: emulator-5554 / Android 14 | Q97: 6 Oct 2026: Only 2 live hospitals exist, so there is no second page to load. BB-10.
A98: DISC-003 | B98: 06 Discovery: locations, hospitals, doctors, search | C98: Hospitals | D98: Rating display | E98: Find a rated and an unrated hospital | F98: Rated shows the value (e.g. 4.6); unrated shows 'Unrated' — never 'null' or 0.0. | G98: P2 | H98: UI | I98: Both | K98: Pass | L98: Claude (adb) | M98: 46301 | N98: 1.0.0+1 debug | O98: emulator-5554 / Android 14 | Q98: 6 Oct 2026: Rated hospitals show their value (Lakeshore 3.9, Sahyadri 4.5, doctors 3.6 / 4.4); no 'null' or 0.0 anywhere. No unrated hospital or doctor exists on the server to see 'Unrated' / 'Not yet rated'.
A99: DISC-004 | B99: 06 Discovery: locations, hospitals, doctors, search | C99: Hospital detail | D99: Hospital detail content | E99: Open a hospital | F99: Name, address, departments, doctors and banners load; images resolve; phone and directions actions are present. | G99: P1 | H99: Functional | I99: Both | K99: Pass | L99: Claude (adb) | M99: 46301 | N99: 1.0.0+1 debug | O99: emulator-5554 / Android 14 | P99: DEF-080 | Q99: 6 Oct 2026: FIXED (DEF-080). Lakeshore: name, address, next free slot, departments (4), rating, reviews, booking window, doctors by department, opening hours, policies and Contact load; images fall back to the placeholder (fake storage). Found: no call or directions actions (phone, email and website were plain text). Now the Contact card has tappable Phone, Directions ('Open in Maps'), Email and Website rows.
A100: DISC-005 | B100: 06 Discovery: locations, hospitals, doctors, search | C100: Hospital detail | D100: Call and directions hand off to the OS | E100: 1. Tap the phone action 2. Tap directions/map | F100: Dialer opens with the number; maps opens at the location; returning to the app keeps state. | G100: P2 | H100: Functional | I100: Both | K100: Pass | L100: Claude (adb) | M100: 46301 | N100: 1.0.0+1 debug | O100: emulator-5554 / Android 14 | Q100: 6 Oct 2026: After the DEF-080 fix: Phone opens the dialler with '+91 484 270 1000'; Directions opens Google Maps at the hospital's pin (9.9312, 76.2673); returning to Medibook keeps the hospital page.
A101: DISC-006 | B101: 06 Discovery: locations, hospitals, doctors, search | C101: Hospital detail | D101: Hospital not taking online bookings | E101: Open a hospital with online booking off | F101: 'Not bookable online. Call the hospital to book.' is shown; no path leads to payment. | G101: P1 | H101: Negative | I101: Both | K101: Blocked | L101: Claude (adb) | M101: 46301 | N101: 1.0.0+1 debug | O101: emulator-5554 / Android 14 | Q101: 6 Oct 2026: No hospital with online booking off exists. BB-06.
A102: DISC-007 | B102: 06 Discovery: locations, hospitals, doctors, search | C102: Doctor detail | D102: Doctor detail content | E102: Open a doctor from search, from a hospital and from booking | F102: Name, speciality, fee, rating ('Not yet rated' when none) and availability are shown; Back returns to the originating screen each time. | G102: P1 | H102: Functional | I102: Both | K102: Pass | L102: Claude (adb) | M102: 46301 | N102: 1.0.0+1 debug | O102: emulator-5554 / Android 14 | Q102: 6 Oct 2026: Dr. Meera Varghese from search, from a hospital's booking list ('View details for…') and from booking: name, 'MBBS · Family Medicine', hospital and room, experience, rating 4.4, fee ₹400 ('Consultation ₹400 · Follow-up ₹200 · 10-minute slots'). Back returns to search (query kept) and to the booking step. On the hospital page a doctor card selects the doctor for booking rather than opening details. 'Not yet rated' not seen: every doctor is rated.
A103: DISC-008 | B103: 06 Discovery: locations, hospitals, doctors, search | C103: Doctor detail | D103: Doctor on leave | E103: Open a doctor whose status is on leave | F103: 'On leave — not taking bookings right now.' and no bookable slots. | G103: P1 | H103: Negative | I103: Both | K103: Blocked | L103: Claude (adb) | M103: 46301 | N103: 1.0.0+1 debug | O103: emulator-5554 / Android 14 | Q103: 6 Oct 2026: No doctor on leave exists. BB-08.
A104: DISC-009 | B104: 06 Discovery: locations, hospitals, doctors, search | C104: Search | D104: Search returns doctors, hospitals and departments | E104: Type a 2+ character query matching each kind | F104: Grouped results appear; tapping each opens the right screen. | G104: P0 | H104: Functional | I104: Both | K104: Pass | L104: Claude (adb) | M104: 46301 | N104: 1.0.0+1 debug | O104: emulator-5554 / Android 14 | Q104: 6 Oct 2026: 'Lake' -> HOSPITALS group (Lakeshore); 'Cardio' -> SPECIALITIES group (Cardiology, 1 hospital); 'Meera' -> DOCTORS group. Tapping opens Hospital Details, booking for that speciality, and Doctor Details respectively.
...

Sheet Known Blockers
A1: Known blockers found in the repository — resolve or accept before the production run | H1: Open: | I1: =COUNTIF($H$4:$H$200,"Open")
A2: Each item was read from the code or project docs on 04-Oct-2026 and may already be fixed elsewhere — re-verify, then set Status. Checklist rows name these ids in the 'Needs / Blocker' column.
A3: ID | B3: Blocker | C3: What was found | D3: Test areas affected | E3: Evidence (file / doc) | F3: Owner | G3: What is needed | H3: Status | I3: Date resolved | J3: Notes
A4: KB-01 | B4: File storage host does not resolve on the integration server | C4: Presigned upload/download URLs point at storage.fake.local, so every upload and download fails. | D4: Record upload/download, insurance files, ticket attachments, receipt PDF, data-export file | E4: docs/FLUTTER_INTEGRATION_GAPS_ROUND_2.md §2 R-1 | F4: Backend / DevOps | G4: Point the server at real object storage. | H4: Open | J4: What is needed from the backend is written up in docs/BACKEND_BLOCKERS.md (BB-17). 15 Business Logic rows and 14 Checklist rows wait on it.
A5: KB-02 | B5: Razorpay runs as an in-process fake | C5: payment_order.key_id is empty and order ids are order_fake…; the app correctly refuses to open the SDK. | D5: Everything after 'Confirm appointment': pay, success, receipt, refund | E5: docs/FLUTTER_INTEGRATION_GAPS_ROUND_2.md §2 R-2 | F5: Backend / DevOps | G5: Configure Razorpay test keys on pre-prod and live keys on production. | H5: Open | J5: Re-checked 05-Oct-2026: bookings LKSB-2610-00194 and -00195 still get an empty Razorpay key; the app shows 'Online payment is not set up for this hospital yet…'. What is needed from the backend is written up in docs/BACKEND_BLOCKERS.md (BB-16).
A6: KB-03 | B6: Self-signed TLS certificate; bad-cert acceptance defaults to on | C6: The integration server presents a self-signed certificate. MEDIBOOK_ALLOW_BAD_CERT defaults to true outside prod. | D6: Any external tester build; SEC transport cases | E6: GAPS_ROUND_2 §2 R-3; lib/app/config/env.dart | F6: DevOps | G6: CA-signed certificate; build with MEDIBOOK_ALLOW_BAD_CERT=false. | H6: Open
A7: KB-04 | B7: No push provider in the app | C7: No Firebase/FCM SDK in pubspec.yaml. Device registration is wired but nothing calls it. | D7: All push-notification cases | E7: GAPS_ROUND_2 §2 R-4 and §5 D-1; pubspec.yaml | F7: Product owner / Mobile | G7: Decide the push provider, add the SDK and platform config. | H7: Open
A8: KB-05 | B8: OTP codes cannot be obtained on the integration server | C8: No SMS is sent in fake mode and the code is not exposed. | D8: Sign-up, OTP sign-in, forgot password, phone change, releasing a family member | E8: GAPS_ROUND_2 §4 | F8: Backend | G8: Real SMS provider (or a controlled test hook) on pre-prod. | H8: Open | J8: Re-checked 04-Oct-2026 with a real phone (+91 9746863592): signup/start accepted, no SMS arrived. What is needed from the backend is written up in docs/BACKEND_BLOCKERS.md (BB-01).
A9: KB-06 | B9: Android release build is signed with the debug key | C9: buildTypes.release uses signingConfigs.getByName("debug") with a TODO. | D9: Play upload, App Links verification, release-build payment test | E9: android/app/build.gradle.kts (release block) | F9: Mobile | G9: Create the upload keystore and a release signingConfig. | H9: Open
A10: KB-07 | B10: Default API URL is the integration server's IP | C10: Env.apiBaseUrl defaults to https://62.171.151.149:8443 when no define is passed. | D10: A release built without the define would talk to the wrong server | E10: lib/app/config/env.dart | F10: Mobile / CI | G10: Release pipeline must pass MEDIBOOK_API_BASE_URL and MEDIBOOK_ENV=prod. | H10: Open
A11: KB-08 | B11: Live queue needs a desk user running a session | C11: Seeded accounts have no booking in an open session, so queue movement was never observed. | D11: Live queue real-time cases; visit-day journey | E11: GAPS_ROUND_2 §4 | F11: QA / Hospital ops | G11: Provide a staff login and a session to run during testing. | H11: Open | J11: 5 Oct 2026 (project owner): the hospital web app is not integrated with the backend yet, so nobody can play the desk role from it. 19 Business Logic rows wait on this. The only other route is driving the hospital API directly with a seeded front-desk account - not tried.
A12: KB-09 | B12: New-password hint says 6 characters; the rule is 10 | C12: NewPasswordFields (reset and change password) defaults its hint to 'At least 6 characters' and no caller overrides it, while the form controllers enforce 10. Sign-up already says 10. | D12: Forgot-password and change-password forms (misleading hint, not a security gap) | E12: lib/features/auth/presentation/components/new_password_fields.dart:36; reset_form_controller.dart:36; change_password_form_controller.dart:42; API doc §4.1 | F12: Mobile | G12: Change the default hint to 'At least 10 characters'. | H12: Open
A13: KB-10 | B13: Features intentionally not available yet | C13: No QR on the token card and no 'Save token card' (D-6). No geolocation: 'Hospitals Near You' is name-ordered (D-3). | D13: Token card, hospital ordering | E13: GAPS_ROUND_2 §5 D-3, D-6 | F13: Product owner | G13: Accept for launch or schedule. | H13: Open
A14: KB-11 | B14: Golden-test failure images are present | C14: test/goldens/failures contains diff images for components and screens. | D14: Golden test gate | E14: test/goldens/failures/ | F14: Mobile | G14: Re-run goldens; update or fix, then clear the folder. | H14: Open
A15: KB-12 | B15: Design base size differs between docs and code | C15: CLAUDE.md / responsiveness guide say 390 x 835; AppConstants.designSize is 390 x 844. | D15: Responsive sizing audit | E15: CLAUDE.md; lib/app/config/constants.dart:15 | F15: Design / Mobile | G15: Confirm the Figma frame size and make both agree. | H15: Open
A16: KB-13 | B16: Tooling deviations from the spec | C16: naming_conventions_lints is not set up (D-7); SDK and package versions differ from Technical_stack.md (noted in pubspec.yaml). | D16: Code quality gates | E16: GAPS_ROUND_2 §5 D-7; pubspec.yaml | F16: Tech lead | G16: Approve the deviations or bring the project in line. | H16: Open

Sheet Screen Coverage
A1: Screen coverage — tick each state once it has been seen on the release build
A2: Use Pass / Fail / N/A in the yellow cells. N/A where a state cannot occur (e.g. no empty state on Login).
A3: # | B3: Feature | C3: Screen | D3: Route | E3: Loaded with data | F3: Loading state | G3: Empty state | H3: Error + retry | I3: Offline | J3: Small phone | K3: Large font | L3: Screen reader | M3: Notes
A4: 1 | B4: Auth | C4: Onboarding | D4: /onboarding | E4: Pass | F4: N/A | G4: N/A | H4: N/A | I4: Pass | J4: Pass | K4: Pass | L4: Pass | M4: Slides seen (ONB-001/002); they are built in, so they show offline too (7 Oct).
A5: 2 | B5: Auth | C5: Consent | D5: /onboarding/consent | E5: Pass | F5: N/A | G5: N/A | H5: Pass | I5: Pass | J5: Pass | K5: Pass | L5: Pass | M5: Text is built in; the policy version loads in the background, so there is no loading state. Offline (7 Oct) 'Agree and Continue' used the version already loaded and went on to sign-in; stays put while policies cannot load and reloads on reconnect (NET-012, DEF-077).
A6: 3 | B6: Auth | C6: Login | D6: /login | E6: Pass | F6: N/A | G6: N/A | H6: Pass | I6: Pass | J6: Pass | K6: Pass | L6: Pass | M6: Field and server errors shown; offline sign-in: 'You appear to be offline…' on the form (6 Oct).
A7: 4 | B7: Auth | C7: Sign up | D7: /signup | E7: Pass | F7: N/A | G7: N/A | H7: Pass | I7: Pass | J7: Pass | K7: Pass | L7: Pass | M7: Form and validation seen (AUTH-002..009). Offline 'Create Account' -> 'You appear to be offline…' at the top of the form (7 Oct). Finishing sign-up needs an OTP (BB-01).
A8: 5 | B8: Auth | C8: Forgot password | D8: /forgot | E8: Pass | F8: N/A | G8: N/A | H8: Pass | I8: Pass | J8: Pass | K8: Pass | L8: Pass | M8: Request form seen (AUTH-023/030). Offline 'Send Code' -> 'You appear to be offline…' on the form (7 Oct). Code delivery blocked (BB-01).
A9: 6 | B9: Auth | C9: Verify code (OTP) | D9: /verify | E9: Pass | F9: N/A | G9: N/A | H9: Pass | I9: Pass | J9: Pass | K9: Pass | L9: Pass | M9: Screen and resend timer seen (AUTH-012). Offline 'Verify & Create Account' -> 'You appear to be offline…' (7 Oct). Real codes blocked (BB-01).
A10: 7 | B10: Auth | C10: New password | D10: /reset | E10: Backend fix | F10: N/A | G10: N/A | H10: Backend fix | I10: Backend fix | J10: Backend fix | K10: Backend fix | L10: Backend fix | M10: Reached only with a reset code, which cannot be delivered on this server (BB-01).
A11: 8 | B11: Auth | C11: Lockout | D11: /lockout | E11: Pass | F11: N/A | G11: N/A | H11: N/A | I11: N/A | J11: Pass | K11: Pass | L11: Pass | M11: Pause with countdown, survives restart (AUTH-020/021). The pause comes from the server's answer; offline the sign-in says it is offline instead (7 Oct).
A12: 9 | B12: Auth | C12: Change password | D12: /change-password, /profile/password | E12: Pass | F12: N/A | G12: N/A | H12: Pass | I12: Pass | J12: Pass | K12: Pass | L12: Pass | M12: Offline 'Update Password' -> 'You appear to be offline…' on the form; no up-front offline note (6 Oct).
A13: 10 | B13: Dashboard | C13: Home | D13: /home | E13: Pass | F13: Pass | G13: Pass | H13: Pass | I13: Pass | J13: Pass | K13: Pass | L13: Pass | M13: App-wide offline bar on every screen (6 Oct fix, DEF-121): 'You're offline - showing what was saved on this phone.'; pull-to-refresh offline now says so (DEF-124). Skeletons then data (NET-001). Empty state needs data (HOME-009, BB-06).
A14: 11 | B14: Dashboard | C14: Ambulance | D14: /ambulance | E14: Pass | F14: Pass | G14: Backend fix | H14: Pass | I14: Pass | J14: Pass | K14: Pass | L14: Pass | M14: The directory loads when the app starts, so the screen opens with it (fresh install, 2G-like speed, 7 Oct). Error view on directory failure (ERR-001); offline shows the saved list under the offline bar. Empty directory needs test data (BB-44).
A15: 12 | B15: Search | C15: Search | D15: /search | E15: Pass | F15: Pass | G15: Pass | H15: Pass | I15: Pass | J15: Pass | K15: Pass | L15: Pass | M15: App-wide offline bar on every screen (6 Oct fix, DEF-121): 'You're offline - showing what was saved on this phone.'. No-match advice; offline new term -> clear offline + Try Again.
... A54: 51 | B54: App | C54: Not found | D54: /notfound | E54: Pass | F54: N/A | G54: N/A | H54: N/A | I54: N/A | J54: Pass | K54: Pass | L54: Pass | M54: Unknown link -> 'Page not found' with Go to Home (NAV-004).
C55: Checked (of screens × 8) | D55: =COUNTA(E4:L54)&" of "&ROWS(E4:L54)*COLUMNS(E4:L54)
C56: Failures | D56: =COUNTIF(E4:L54,"Fail")

Sheet Device Matrix
A1: Device matrix — run the E2E journeys on every row; run the full checklist on at least one Android and one iOS row
A2: Device classes are a recommendation for an India launch; replace the examples with the handsets you actually have.
A3: Platform | B3: Device class (example) | C3: OS version | D3: Screen | E3: Why it is in the matrix | F3: Actual device used | G3: E2E journeys | H3: Full checklist | I3: Tester | J3: Date | K3: Notes
A4: Android | B4: Small / low-end phone (e.g. Redmi A-series, Galaxy A0x) | C4: Lowest supported Android | D4: ~360 x 640 dp, 2–3 GB RAM | E4: Minimum OS, small layout, low memory
A5: Android | B5: Mid-range phone (e.g. Redmi Note, Galaxy A/M series) | C5: Android 12–13 | D5: ~393 x 873 dp | E5: Most common device class in India
A6: Android | B6: Samsung flagship (One UI) | C6: Android 14–15 | D6: ~412 x 915 dp | E6: One UI behaviour, edge-to-edge
A7: Android | B7: Pixel | C7: Latest Android | D7: ~412 x 915 dp | E7: Reference Android, predictive back, 16 KB pages
A8: Android | B8: Oppo / Vivo / Realme | C8: Android 13–14 | D8: ~360–412 dp wide | E8: Aggressive battery managers, push delivery
A9: Android | B9: Tablet (only if distributed to tablets) | C9: Android 13+ | D9: ~800 x 1280 dp | E9: Large layout
A10: iOS | B10: iPhone SE (2nd/3rd gen) | C10: Lowest supported iOS | D10: 375 x 667 pt | E10: Smallest iOS layout, home button
A11: iOS | B11: iPhone 13 / 14 | C11: iOS 17–18 | D11: 390 x 844 pt | E11: Matches the design base size
A12: iOS | B12: iPhone 15/16 Pro Max | C12: Latest iOS | D12: 430 x 932 pt | E12: Largest phone, Dynamic Island
A13: iOS | B13: iPad (only if distributed to iPad) | C13: Latest iPadOS | D13: 820 x 1180 pt | E13: Large layout / compatibility mode

Sheet Defect Log
A1: Defect ID | B1: Test case ID | C1: Title | D1: Severity | E1: Module | F1: Steps to reproduce | G1: Expected | H1: Actual | I1: Build | J1: Device / OS | K1: Reported by | L1: Date found | M1: Status | N1: Assigned to | O1: Fixed in build | P1: Retest
A2: DEF-001 | B2: BL-AUTH-008 | C2: Non-Indian country codes | D2: Medium | E2: Authentication & session | F2: 1. Pick +971 in the country picker 2. Enter a valid 9-digit UAE number | G2: Decide what is correct: the picker offers other countries, but validation is always the Indian rule, so the number is rejected. | H2: Country picker offers +971 (and 8 other non-Indian codes); with +971 selected a valid 9-digit UAE mobile (501234567) is rejected with 'Mobile number must be 10 digits'. The non-Indian options can never be used. | I2: 1.0.0+1 debug | J2: emulator-5554 / Android 14 | K2: Claude (adb) | L2: 46299 | M2: Verified | O2: 1.0.0+1 debug (rebuilt 5 Oct 2026) | P2: Pass
A3: DEF-002 | B3: BL-AUTH-020 | C3: Resend cooldown and code-expiry countdown | D3: High | E3: Authentication & session | F3: Arrive on the verify screen and tap 'Resend Code' immediately, several times | G3: A 30 s cooldown / countdown is expected. The code leaves the button always tappable and relies on the server's 'too many attempts' answer. | H3: No resend cooldown or countdown on the verify screen: 'Resend code' is tappable immediately on arrival; tapping it at once gave the server banner 'Too many attempts. Please wait a moment and try again.' No expiry countdown for the 180 s code either. | I3: 1.0.0+1 debug | J3: emulator-5554 / Android 14 | K3: Claude (adb) | L3: 46299 | M3: Verified | O3: 1.0.0+1 debug (rebuilt 5 Oct 2026) | P3: Pass
A4: DEF-003 | B4: BL-AUTH-032 | C4: Warning text states the real pause length | D4: High | E4: Authentication & session | F4: 1. Read the warning before lockout 2. Get locked out and read the countdown | G4: They should agree. The warning says 'paused for 60 seconds' while the server locks for about an hour. | H4: The warnings say sign-in will be 'paused for 60 seconds', but after the fifth failure the lockout countdown starts at 59:57 — about one hour. The warning understates the pause sixty-fold. | I4: 1.0.0+1 debug | J4: emulator-5554 / Android 14 | K4: Claude (adb) | L4: 46299 | M4: Verified | O4: 1.0.0+1 debug (rebuilt 5 Oct 2026) | P4: Pass
A5: DEF-004 | B5: BL-AUTH-035 | C5: Lockout scope on a shared device | D5: High | E5: Authentication & session | F5: 1. Lock account A 2. On the same device try to sign in as B, sign up, and use Forgot password | G5: Decide what is correct: the code blocks all of these locally while A's lock runs, although the warning itself suggests using 'Forgot password?'. | H5: With the device locked out by one account's failed attempts, 'Forgot password?' for a DIFFERENT account's number is refused locally: 'Too many failed attempts. Try again in 60 minutes.' The lock is device-wide — nobody else can sign in, sign up or reset a password on this device for an hour, and it blocks the very 'Forgot password?' route the last-attempt warning recommends. | I5: 1.0.0+1 debug | J5: emulator-5554 / Android 14 | K5: Claude (adb) | L5: 46299 | M5: Verified | O5: 1.0.0+1 debug (rebuilt 5 Oct 2026) | P5: Pass
A6: DEF-005 | B6: BL-AUTH-036 | C6: Wrong OTP must not show a password-attempt warning | D6: Medium | E6: Authentication & session | F6: 1. On mobile sign-in enter one wrong code 2. Go back to the sign-in screen | G6: No password warning. The code shows '2 attempts left before sign-in is paused…' although no password was tried. | H6: After one wrong OTP on mobile sign-in, going back to the sign-in screen shows the password warning 'Sign-in attempts — 2 attempts left before sign-in is paused for 60 seconds.' although no password was tried (OTP attempts are written into the password-attempt counter). | I6: 1.0.0+1 debug | J6: emulator-5554 / Android 14 | K6: Claude (adb) | L6: 46299 | M6: Verified | O6: 1.0.0+1 debug (rebuilt 5 Oct 2026) | P6: Pass
A7: DEF-006 | B7: BL-AUTH-043 | C7: New password rules | D7: High | E7: Authentication & session | F7: 1. Submit with current empty 2. 9-character new 3. New equal to current 4. Mismatched confirmation | G7: 'Enter your password' / 'At least 10 characters' / 'Choose a password you have not used before' / 'Passwords do not match'. | H7: The rules themselves work: empty current 'Enter your password'; 9-character new 'At least 10 characters'; new = current 'Choose a password you have not used before'; mismatch 'Passwords do not match'. But the New Password placeholder and helper both read 'At least 6 characters' (KB-09), contradicting the enforced 10 — a user following the hint is always rejected. | I7: 1.0.0+1 debug | J7: emulator-5554 / Android 14 | K7: Claude (adb) | L7: 46299 | M7: Verified | O7: 1.0.0+1 debug (rebuilt 5 Oct 2026) | P7: Pass
A8: DEF-007 | B8: BL-AUTH-050 | C8: User is told why they were signed out | D8: High | E8: Authentication & session | F8: 1. Have the session revoked 2. Look at the sign-in screen | G8: A reason should be visible ('Your session has expired. Please sign in again.'). The code stores the reason but the sign-in screen does not display it. | H8: After the session was revoked remotely the user lands on the plain sign-in screen ('Hi, Welcome Back!') with no message at all — nothing says the session ended or why. | I8: 1.0.0+1 debug | J8: emulator-5554 / Android 14 | K8: Claude (adb) | L8: 46299 | M8: Verified | O8: 1.0.0+1 debug (rebuilt 5 Oct 2026) | P8: Pass
A9: DEF-008 | B9: BL-BOOK-026 | C9: Booking from Doctor Details carries the slot | D9: High | E9: Booking | F9: 1. Open a doctor from Search 2. Pick a time 3. Tap 'Book <time>' 4. Repeat after another user takes that slot | G9: Step 3 shows the chosen time; if it was taken, step 3 asks to pick a time again. | H9: From a clean start: Search -> Dr. Meera Varghese -> picked 9:40 AM -> footer 'Book 9:40 AM tomorrow' -> tapped. The booking opens on step 3 with 'Pick a doctor and a time first.' / 'Choose a doctor' — the chosen time (and the doctor) is not carried over, and step 2 shows the hospital as 'This hospital' with no doctor selected. Reproduced twice (the slot was still free). Doctor Details footer states work: 'Pick a time to continue' disabled until a time is tapped. | I9: 1.0.0+1 debug | J9: emulator-5554 / Android 14 | K9: Claude (adb) | L9: 46299 | M9: Verified | O9: 1.0.0+1 debug (rebuilt 5 Oct 2026) | P9: Pass
A10: DEF-009 | B10: BL-BOOK-034 | C10: Pay stays disabled without a quote | D10: High | E10: Booking | F10: Cut the network on step 4 | G10: Inline error with Retry; 'Pay ₹…' disabled. | H10: On booking step 3 with a doctor, time and patient chosen, the device was put in airplane mode and Continue tapped: instead of an inline error with Retry, the ENTIRE app is replaced by a red Flutter error screen reading 'NetworkFailure(network): The connection errored … DioException [connection error] … SocketException: Connection failed (OS Error: Network is unreachable, errno = 101), address = 62.171.151.149, port = 8443 — See also: https://docs.flutter.dev/testing/errors'. Reproduced twice. System Back then exits the app. (In a release build this would be a blank grey screen.) Screenshot: docs/emulator-run-redscreen-booking-offline.png. | I10: 1.0.0+1 debug | J10: emulator-5554 / Android 14 | K10: Claude (adb) | L10: 46299 | M10: Verified | O10: 1.0.0+1 debug (rebuilt 5 Oct 2026) | P10: Pass
A11: DEF-010 | B11: BL-BOOK-045 | C11: Changing the draft after a booking exists | D11: Critical | E11: Booking | F11: 1. Tap Pay 2. Back out 3. Change the slot, patient or coupon on earlier steps 4. Tap 'Complete payment' | G11: The user must not be misled. The code resumes the ORIGINAL booking while the summary shows the new choices. | H11: With booking LKSB-2610-00187 already created for Sanjay Varma, went back to step 3, chose Tara Varma, returned to step 4 (summary shows Tara) and tapped 'Complete payment': the original booking for Sanjay is resumed, and the payment screen's Order summary now shows 'Patient: Tara Varma' for it. The user is shown a different patient from the one actually booked. | I11: 1.0.0+1 debug | J11: emulator-5554 / Android 14 | K11: Claude (adb) | L11: 46299 | M11: Verified | O11: 1.0.0+1 debug (rebuilt 5 Oct 2026) | P11: Pass
A12: DEF-011 | B12: BL-PAY-003 | C12: Expired screen names the booking | D12: Low | E12: Payment | F12: Let the timer expire and read the result body | G12: It should describe the lapsed booking. The code shows 'There is no booking attached to this outcome in this session.' | H12: The expired result body reads 'There is no booking attached to this outcome in this session.' although the session had just held booking LKSB-2610-00187; the lapsed booking is not named. | I12: 1.0.0+1 debug | J12: emulator-5554 / Android 14 | K12: Claude (adb) | L12: 46299 | M12: Verified | O12: 1.0.0+1 debug (rebuilt 5 Oct 2026) | P12: Pass
A13: DEF-012 | B13: BL-PAY-027 | C13: Leaving the payment screen | D13: High | E13: Payment | F13: 1. Press Back before paying 2. Press Back while it says 'Confirming payment…' | G13: 'Leave payment?' dialog before paying. While confirming, leaving should be blocked or confirmed — the code lets Back leave with no dialog exactly then. | H13: Pressing Back on the payment screen before paying (timer running, booking LKSB-2610-00188 held) leaves immediately with no 'Leave payment?' confirmation; same after a failed attempt. The user drops back to the booking flow without being warned that the hold keeps counting down. | I13: 1.0.0+1 debug | J13: emulator-5554 / Android 14 | K13: Claude (adb) | L13: 46299 | M13: Verified | O13: 1.0.0+1 debug (rebuilt 5 Oct 2026) | P13: Pass
... A29: DEF-028 | B29: BL-NOTIF-014 | C29: Open list shows the new notification | D29: High | E29: Notifications | F29: Stay on the Notifications screen while a new one is created | G29: The new row should appear. The code may answer the reload from memory, so the badge rises but the row is missing until pull-to-refresh. | H29: Same run: the count rose to 42 but the new 'Appointment cancelled' notification (created seconds earlier) did not appear in the open list — the first row was still '1 hour ago' until pull-to-refresh. | I29: 1.0.0+1 debug | J29: emulator-5554 / Android 14 | K29: Claude (adb) | L29: 46299 | M29: Verified | O29: 1.0.0+1 debug (rebuilt 5 Oct 2026) | P29: Pass
A30: DEF-029 | B30: BL-NOTIF-017 | C30: Device is registered for push after sign-in | D30: Critical | E30: Notifications | F30: 1. Sign in with a proxy attached 2. Look for the device registration call | G30: A registration is expected. The code never calls it and has no push SDK, so push cannot be tested yet. | H30: KB-04 confirmed: after signing in on the emulator the server's device list for the account contains only a seeded iOS demo device last seen on 12 Aug; no Android device was registered by this sign-in. The app never registers for push, so no push notification can be delivered. | I30: 1.0.0+1 debug | J30: emulator-5554 / Android 14 | K30: Claude (adb) | L30: 46299 | M30: Open
A31: DEF-030 | B31: BL-PROF-005 | C31: Clearing the blood group | D31: High | E31: Profile & account | F31: 1. Set blood group O+ and save 2. Reopen, choose 'Not known', save 3. Reopen | G31: Blood group should be cleared. The code sends nothing and keeps O+ while showing 'Profile updated'. | H31: Blood group O+ saved. Reopened Edit Profile, chose 'Not known' (form shows 'not set'), tapped Save Changes: the app returns to Profile as if saved, but the server still has O+ (version unchanged) and Profile still shows 'Blood group O+'. The blood group cannot be cleared. | I31: 1.0.0+1 debug | J31: emulator-5554 / Android 14 | K31: Claude (adb) | L31: 46299 | M31: Verified | O31: 1.0.0+1 debug (rebuilt 5 Oct 2026) | P31: Pass
A32: DEF-031 | B32: BL-PROF-009 | C32: Unsaved-changes guard | D32: Medium | E32: Profile & account | F32: 1. Edit a field 2. Press Back | G32: 'Discard your changes?' | H32: System Back with an edited field shows 'Discard your changes? The details you have edited will not be saved to your account.' (Keep Editing / Discard). But the header back arrow ('Back to profile') leaves Edit Profile immediately with no confirmation — tried after changing the first name and after changing the date of birth; the edits are lost silently. | I32: 1.0.0+1 debug | J32: emulator-5554 / Android 14 | K32: Claude (adb) | L32: 46299 | M32: Verified | O32: 1.0.0+1 debug (rebuilt 5 Oct 2026) | P32: Pass
